Workbook
Name account_balance_table_header: #REF!
Name NewTaipeiCity: 'Custom分類'!$D$2:$D$30
Name account_list: #REF!
Name account_balance_table: #REF!
Name account_list_with_id: #REF!
Name TaipeiCity: 'Custom分類'!$C$2:$C$13
Name filter_project: #REF!
Name categorized_expense_over_month: #REF!

Sheet room_list
A1: case | B1: room_key | C1: property | D1: room_number | E1: room_type | F1: extension_or_unregistered_building | G1: rental_area | H1: base_rent | I1: vacant_for_rent | J1: room_title | K1: video_link | L1: sorting | M1: specific_public_video | N1: mutex_group | O1: vacant_for_rent_check
A2: {=IFERROR( INDEX(big_rental_contract!A:A, MATCH(C2, big_rental_contract!F:F, 0)), "" )} -> A0001 | B2: RL00002 | C2: 永春四號 | D2: A | E2: 分租雅房 | F2: 無 | G2: 9.38 | H2: 12900 | I2: =IF(O2<>"空房招租中", O2, IF(N2="", "空房招租中", IF(ISNUMBER(SEARCH("分層", E2)), IF(COUNTIFS(N:N, N2, O:O, "<>空房招租中") > 0, "入住中", "空房招租中"), IF(COUNTIFS(N:N, N2, O:O, "<>空房招租中", E:E, "*分層*") > 0, "入住中", IF(COUNTIFS(N:N, N2, O:O, "空房招租中", E:E, "*分層*") > 0, "分層優先(隱藏)", "空房招租中") ) ) ) ) -> 入住中 | L2: =IF(AND(A2="", C2="", D2=""), "Z", "A") -> A | O2: =IF(AND(C2<>"", D2<>""), IF(COUNTIFS(sublease_contract!$C:$C, C2, sublease_contract!$D:$D, "*" & D2 & "*", sublease_contract!$G:$G, "<>已退租") = 0, "空房招租中", IF(COUNTIFS(sublease_contract!$C:$C, C2, sublease_contract!$D:$D, "*" & D2 & "*", sublease_contract!$G:$G, "<>已退租", sublease_contract!$N:$N, ">" & (TODAY()+20)) > 0, "入住中", IF(COUNTIFS(sublease_contract!$C:$C, C2, sublease_contract!$D:$D, "*" & D2 & "*", sublease_contract!$G:$G, "<>已退租", sublease_contract!$N:$N, ">=" & TODAY(), sublease_contract!$N:$N, "<=" & (TODAY()+20)) > 0, MINIFS(sublease_contract!$N:$N, sublease_contract!$C:$C, C2, sublease_contract!$D:$D, "*" & D2 & "*", sublease_contract!$G:$G, "<>已退租", sublease_contract!$N:$N, ">=" & TODAY(), sublease_contract!$N:$N, "<=" & (TODAY()+20)), "入住中"))), "") -> 入住中
A3: {=IFERROR( INDEX(big_rental_contract!A:A, MATCH(C3, big_rental_contract!F:F, 0)), "" )} -> A0001 | B3: RL00003 | C3: 永春四號 | D3: B | E3: 分租雅房 | F3: 無 | G3: 10.56 | H3: 13500 | I3: =IF(O3<>"空房招租中", O3, IF(N3="", "空房招租中", IF(ISNUMBER(SEARCH("分層", E3)), IF(COUNTIFS(N:N, N3, O:O, "<>空房招租中") > 0, "入住中", "空房招租中"), IF(COUNTIFS(N:N, N3, O:O, "<>空房招租中", E:E, "*分層*") > 0, "入住中", IF(COUNTIFS(N:N, N3, O:O, "空房招租中", E:E, "*分層*") > 0, "分層優先(隱藏)", "空房招租中") ) ) ) ) -> 入住中 | L3: =IF(AND(A3="", C3="", D3=""), "Z", "A") -> A | O3: =IF(AND(C3<>"", D3<>""), IF(COUNTIFS(sublease_contract!$C:$C, C3, sublease_contract!$D:$D, "*" & D3 & "*", sublease_contract!$G:$G, "<>已退租") = 0, "空房招租中", IF(COUNTIFS(sublease_contract!$C:$C, C3, sublease_contract!$D:$D, "*" & D3 & "*", sublease_contract!$G:$G, "<>已退租", sublease_contract!$N:$N, ">" & (TODAY()+20)) > 0, "入住中", IF(COUNTIFS(sublease_contract!$C:$C, C3, sublease_contract!$D:$D, "*" & D3 & "*", sublease_contract!$G:$G, "<>已退租", sublease_contract!$N:$N, ">=" & TODAY(), sublease_contract!$N:$N, "<=" & (TODAY()+20)) > 0, MINIFS(sublease_contract!$N:$N, sublease_contract!$C:$C, C3, sublease_contract!$D:$D, "*" & D3 & "*", sublease_contract!$G:$G, "<>已退租", sublease_contract!$N:$N, ">=" & TODAY(), sublease_contract!$N:$N, "<=" & (TODAY()+20)), "入住中"))), "") -> 入住中
A4: {=IFERROR( INDEX(big_rental_contract!A:A, MATCH(C4, big_rental_contract!F:F, 0)), "" )} -> A0001 | B4: RL00004 | C4: 永春四號 | D4: C | E4: 分租雅房 | F4: 無 | G4: 13.39 | H4: 13300 | I4: =IF(O4<>"空房招租中", O4, IF(N4="", "空房招租中", IF(ISNUMBER(SEARCH("分層", E4)), IF(COUNTIFS(N:N, N4, O:O, "<>空房招租中") > 0, "入住中", "空房招租中"), IF(COUNTIFS(N:N, N4, O:O, "<>空房招租中", E:E, "*分層*") > 0, "入住中", IF(COUNTIFS(N:N, N4, O:O, "空房招租中", E:E, "*分層*") > 0, "分層優先(隱藏)", "空房招租中") ) ) ) ) -> 入住中 | L4: =IF(AND(A4="", C4="", D4=""), "Z", "A") -> A | O4: =IF(AND(C4<>"", D4<>""), IF(COUNTIFS(sublease_contract!$C:$C, C4, sublease_contract!$D:$D, "*" & D4 & "*", sublease_contract!$G:$G, "<>已退租") = 0, "空房招租中", IF(COUNTIFS(sublease_contract!$C:$C, C4, sublease_contract!$D:$D, "*" & D4 & "*", sublease_contract!$G:$G, "<>已退租", sublease_contract!$N:$N, ">" & (TODAY()+20)) > 0, "入住中", IF(COUNTIFS(sublease_contract!$C:$C, C4, sublease_contract!$D:$D, "*" & D4 & "*", sublease_contract!$G:$G, "<>已退租", sublease_contract!$N:$N, ">=" & TODAY(), sublease_contract!$N:$N, "<=" & (TODAY()+20)) > 0, MINIFS(sublease_contract!$N:$N, sublease_contract!$C:$C, C4, sublease_contract!$D:$D, "*" & D4 & "*", sublease_contract!$G:$G, "<>已退租", sublease_contract!$N:$N, ">=" & TODAY(), sublease_contract!$N:$N, "<=" & (TODAY()+20)), "入住中"))), "") -> 入住中
A5: {=IFERROR( INDEX(big_rental_contract!A:A, MATCH(C5, big_rental_contract!F:F, 0)), "" )} -> A0001 | B5: RL00005 | C5: 永春四號 | D5: D | E5: 分租雅房 | F5: 無 | G5: 11.47 | H5: 14300 | I5: =IF(O5<>"空房招租中", O5, IF(N5="", "空房招租中", IF(ISNUMBER(SEARCH("分層", E5)), IF(COUNTIFS(N:N, N5, O:O, "<>空房招租中") > 0, "入住中", "空房招租中"), IF(COUNTIFS(N:N, N5, O:O, "<>空房招租中", E:E, "*分層*") > 0, "入住中", IF(COUNTIFS(N:N, N5, O:O, "空房招租中", E:E, "*分層*") > 0, "分層優先(隱藏)", "空房招租中") ) ) ) ) -> 入住中 | L5: =IF(AND(A5="", C5="", D5=""), "Z", "A") -> A | O5: =IF(AND(C5<>"", D5<>""), IF(COUNTIFS(sublease_contract!$C:$C, C5, sublease_contract!$D:$D, "*" & D5 & "*", sublease_contract!$G:$G, "<>已退租") = 0, "空房招租中", IF(COUNTIFS(sublease_contract!$C:$C, C5, sublease_contract!$D:$D, "*" & D5 & "*", sublease_contract!$G:$G, "<>已退租", sublease_contract!$N:$N, ">" & (TODAY()+20)) > 0, "入住中", IF(COUNTIFS(sublease_contract!$C:$C, C5, sublease_contract!$D:$D, "*" & D5 & "*", sublease_contract!$G:$G, "<>已退租", sublease_contract!$N:$N, ">=" & TODAY(), sublease_contract!$N:$N, "<=" & (TODAY()+20)) > 0, MINIFS(sublease_contract!$N:$N, sublease_contract!$C:$C, C5, sublease_contract!$D:$D, "*" & D5 & "*", sublease_contract!$G:$G, "<>已退租", sublease_contract!$N:$N, ">=" & TODAY(), sublease_contract!$N:$N, "<=" & (TODAY()+20)), "入住中"))), "") -> 入住中
A6: {=IFERROR( INDEX(big_rental_contract!A:A, MATCH(C6, big_rental_contract!F:F, 0)), "" )} -> A0002 | B6: RL00006 | C6: 內湖秘境 | D6: A | E6: 分租雅房 | F6: 無 | G6: 11.38 | H6: 12300 | I6: =IF(O6<>"空房招租中", O6, IF(N6="", "空房招租中", IF(ISNUMBER(SEARCH("分層", E6)), IF(COUNTIFS(N:N, N6, O:O, "<>空房招租中") > 0, "入住中", "空房招租中"), IF(COUNTIFS(N:N, N6, O:O, "<>空房招租中", E:E, "*分層*") > 0, "入住中", IF(COUNTIFS(N:N, N6, O:O, "空房招租中", E:E, "*分層*") > 0, "分層優先(隱藏)", "空房招租中") ) ) ) ) -> 入住中 | J6: 面山綠景清幽雅房 | L6: =IF(AND(A6="", C6="", D6=""), "Z", "A") -> A | O6: =IF(AND(C6<>"", D6<>""), IF(COUNTIFS(sublease_contract!$C:$C, C6, sublease_contract!$D:$D, "*" & D6 & "*", sublease_contract!$G:$G, "<>已退租") = 0, "空房招租中", IF(COUNTIFS(sublease_contract!$C:$C, C6, sublease_contract!$D:$D, "*" & D6 & "*", sublease_contract!$G:$G, "<>已退租", sublease_contract!$N:$N, ">" & (TODAY()+20)) > 0, "入住中", IF(COUNTIFS(sublease_contract!$C:$C, C6, sublease_contract!$D:$D, "*" & D6 & "*", sublease_contract!$G:$G, "<>已退租", sublease_contract!$N:$N, ">=" & TODAY(), sublease_contract!$N:$N, "<=" & (TODAY()+20)) > 0, MINIFS(sublease_contract!$N:$N, sublease_contract!$C:$C, C6, sublease_contract!$D:$D, "*" & D6 & "*", sublease_contract!$G:$G, "<>已退租", sublease_contract!$N:$N, ">=" & TODAY(), sublease_contract!$N:$N, "<=" & (TODAY()+20)), "入住中"))), "") -> 入住中
A7: {=IFERROR( INDEX(big_rental_contract!A:A, MATCH(C7, big_rental_contract!F:F, 0)), "" )} -> A0002 | B7: RL00007 | C7: 內湖秘境 | D7: B | E7: 分租雅房 | F7: 無 | G7: 9.21 | H7: 12300 | I7: =IF(O7<>"空房招租中", O7, IF(N7="", "空房招租中", IF(ISNUMBER(SEARCH("分層", E7)), IF(COUNTIFS(N:N, N7, O:O, "<>空房招租中") > 0, "入住中", "空房招租中"), IF(COUNTIFS(N:N, N7, O:O, "<>空房招租中", E:E, "*分層*") > 0, "入住中", IF(COUNTIFS(N:N, N7, O:O, "空房招租中", E:E, "*分層*") > 0, "分層優先(隱藏)", "空房招租中") ) ) ) ) -> 入住中 | J7: 面山綠景清幽雅房 | K7: https://youtube.com/shorts/rd6OLksk1pk | L7: =IF(AND(A7="", C7="", D7=""), "Z", "A") -> A | O7: =IF(AND(C7<>"", D7<>""), IF(COUNTIFS(sublease_contract!$C:$C, C7, sublease_contract!$D:$D, "*" & D7 & "*", sublease_contract!$G:$G, "<>已退租") = 0, "空房招租中", IF(COUNTIFS(sublease_contract!$C:$C, C7, sublease_contract!$D:$D, "*" & D7 & "*", sublease_contract!$G:$G, "<>已退租", sublease_contract!$N:$N, ">" & (TODAY()+20)) > 0, "入住中", IF(COUNTIFS(sublease_contract!$C:$C, C7, sublease_contract!$D:$D, "*" & D7 & "*", sublease_contract!$G:$G, "<>已退租", sublease_contract!$N:$N, ">=" & TODAY(), sublease_contract!$N:$N, "<=" & (TODAY()+20)) > 0, MINIFS(sublease_contract!$N:$N, sublease_contract!$C:$C, C7, sublease_contract!$D:$D, "*" & D7 & "*", sublease_contract!$G:$G, "<>已退租", sublease_contract!$N:$N, ">=" & TODAY(), sublease_contract!$N:$N, "<=" & (TODAY()+20)), "入住中"))), "") -> 入住中
A8: {=IFERROR( INDEX(big_rental_contract!A:A, MATCH(C8, big_rental_contract!F:F, 0)), "" )} -> A0002 | B8: RL00008 | C8: 內湖秘境 | D8: C | E8: 分租雅房 | F8: 無 | G8: 17.59 | H8: 14800 | I8: =IF(O8<>"空房招租中", O8, IF(N8="", "空房招租中", IF(ISNUMBER(SEARCH("分層", E8)), IF(COUNTIFS(N:N, N8, O:O, "<>空房招租中") > 0, "入住中", "空房招租中"), IF(COUNTIFS(N:N, N8, O:O, "<>空房招租中", E:E, "*分層*") > 0, "入住中", IF(COUNTIFS(N:N, N8, O:O, "空房招租中", E:E, "*分層*") > 0, "分層優先(隱藏)", "空房招租中") ) ) ) ) -> 入住中 | L8: =IF(AND(A8="", C8="", D8=""), "Z", "A") -> A | O8: =IF(AND(C8<>"", D8<>""), IF(COUNTIFS(sublease_contract!$C:$C, C8, sublease_contract!$D:$D, "*" & D8 & "*", sublease_contract!$G:$G, "<>已退租") = 0, "空房招租中", IF(COUNTIFS(sublease_contract!$C:$C, C8, sublease_contract!$D:$D, "*" & D8 & "*", sublease_contract!$G:$G, "<>已退租", sublease_contract!$N:$N, ">" & (TODAY()+20)) > 0, "入住中", IF(COUNTIFS(sublease_contract!$C:$C, C8, sublease_contract!$D:$D, "*" & D8 & "*", sublease_contract!$G:$G, "<>已退租", sublease_contract!$N:$N, ">=" & TODAY(), sublease_contract!$N:$N, "<=" & (TODAY()+20)) > 0, MINIFS(sublease_contract!$N:$N, sublease_contract!$C:$C, C8, sublease_contract!$D:$D, "*" & D8 & "*", sublease_contract!$G:$G, "<>已退租", sublease_contract!$N:$N, ">=" & TODAY(), sublease_contract!$N:$N, "<=" & (TODAY()+20)), "入住中"))), "") -> 入住中
A9: {=IFERROR( INDEX(big_rental_contract!A:A, MATCH(C9, big_rental_contract!F:F, 0)), "" )} -> A0002 | B9: RL00009 | C9: 內湖秘境 | D9: D | E9: 分租雅房 | F9: 無 | G9: 13.44 | H9: 13200 | I9: =IF(O9<>"空房招租中", O9, IF(N9="", "空房招租中", IF(ISNUMBER(SEARCH("分層", E9)), IF(COUNTIFS(N:N, N9, O:O, "<>空房招租中") > 0, "入住中", "空房招租中"), IF(COUNTIFS(N:N, N9, O:O, "<>空房招租中", E:E, "*分層*") > 0, "入住中", IF(COUNTIFS(N:N, N9, O:O, "空房招租中", E:E, "*分層*") > 0, "分層優先(隱藏)", "空房招租中") ) ) ) ) -> 入住中 | L9: =IF(AND(A9="", C9="", D9=""), "Z", "A") -> A | O9: =IF(AND(C9<>"", D9<>""), IF(COUNTIFS(sublease_contract!$C:$C, C9, sublease_contract!$D:$D, "*" & D9 & "*", sublease_contract!$G:$G, "<>已退租") = 0, "空房招租中", IF(COUNTIFS(sublease_contract!$C:$C, C9, sublease_contract!$D:$D, "*" & D9 & "*", sublease_contract!$G:$G, "<>已退租", sublease_contract!$N:$N, ">" & (TODAY()+20)) > 0, "入住中", IF(COUNTIFS(sublease_contract!$C:$C, C9, sublease_contract!$D:$D, "*" & D9 & "*", sublease_contract!$G:$G, "<>已退租", sublease_contract!$N:$N, ">=" & TODAY(), sublease_contract!$N:$N, "<=" & (TODAY()+20)) > 0, MINIFS(sublease_contract!$N:$N, sublease_contract!$C:$C, C9, sublease_contract!$D:$D, "*" & D9 & "*", sublease_contract!$G:$G, "<>已退租", sublease_contract!$N:$N, ">=" & TODAY(), sublease_contract!$N:$N, "<=" & (TODAY()+20)), "入住中"))), "") -> 入住中
A10: {=IFERROR( INDEX(big_rental_contract!A:A, MATCH(C10, big_rental_contract!F:F, 0)), "" )} -> A0002 | B10: RL00010 | C10: 內湖秘境 | D10: E | E10: 分租雅房 | F10: 無 | G10: 14.84 | H10: 13600 | I10: =IF(O10<>"空房招租中", O10, IF(N10="", "空房招租中", IF(ISNUMBER(SEARCH("分層", E10)), IF(COUNTIFS(N:N, N10, O:O, "<>空房招租中") > 0, "入住中", "空房招租中"), IF(COUNTIFS(N:N, N10, O:O, "<>空房招租中", E:E, "*分層*") > 0, "入住中", IF(COUNTIFS(N:N, N10, O:O, "空房招租中", E:E, "*分層*") > 0, "分層優先(隱藏)", "空房招租中") ) ) ) ) -> 入住中 | L10: =IF(AND(A10="", C10="", D10=""), "Z", "A") -> A | O10: =IF(AND(C10<>"", D10<>""), IF(COUNTIFS(sublease_contract!$C:$C, C10, sublease_contract!$D:$D, "*" & D10 & "*", sublease_contract!$G:$G, "<>已退租") = 0, "空房招租中", IF(COUNTIFS(sublease_contract!$C:$C, C10, sublease_contract!$D:$D, "*" & D10 & "*", sublease_contract!$G:$G, "<>已退租", sublease_contract!$N:$N, ">" & (TODAY()+20)) > 0, "入住中", IF(COUNTIFS(sublease_contract!$C:$C, C10, sublease_contract!$D:$D, "*" & D10 & "*", sublease_contract!$G:$G, "<>已退租", sublease_contract!$N:$N, ">=" & TODAY(), sublease_contract!$N:$N, "<=" & (TODAY()+20)) > 0, MINIFS(sublease_contract!$N:$N, sublease_contract!$C:$C, C10, sublease_contract!$D:$D, "*" & D10 & "*", sublease_contract!$G:$G, "<>已退租", sublease_contract!$N:$N, ">=" & TODAY(), sublease_contract!$N:$N, "<=" & (TODAY()+20)), "入住中"))), "") -> 入住中
A11: {=IFERROR( INDEX(big_rental_contract!A:A, MATCH(C11, big_rental_contract!F:F, 0)), "" )} -> A0002 | B11: RL00011 | C11: 內湖秘境 | D11: F | E11: 分租雅房 | F11: 頂加 | G11: 11.8 | H11: 13500 | I11: =IF(O11<>"空房招租中", O11, IF(N11="", "空房招租中", IF(ISNUMBER(SEARCH("分層", E11)), IF(COUNTIFS(N:N, N11, O:O, "<>空房招租中") > 0, "入住中", "空房招租中"), IF(COUNTIFS(N:N, N11, O:O, "<>空房招租中", E:E, "*分層*") > 0, "入住中", IF(COUNTIFS(N:N, N11, O:O, "空房招租中", E:E, "*分層*") > 0, "分層優先(隱藏)", "空房招租中") ) ) ) ) -> 入住中 | L11: =IF(AND(A11="", C11="", D11=""), "Z", "A") -> A | O11: =IF(AND(C11<>"", D11<>""), IF(COUNTIFS(sublease_contract!$C:$C, C11, sublease_contract!$D:$D, "*" & D11 & "*", sublease_contract!$G:$G, "<>已退租") = 0, "空房招租中", IF(COUNTIFS(sublease_contract!$C:$C, C11, sublease_contract!$D:$D, "*" & D11 & "*", sublease_contract!$G:$G, "<>已退租", sublease_contract!$N:$N, ">" & (TODAY()+20)) > 0, "入住中", IF(COUNTIFS(sublease_contract!$C:$C, C11, sublease_contract!$D:$D, "*" & D11 & "*", sublease_contract!$G:$G, "<>已退租", sublease_contract!$N:$N, ">=" & TODAY(), sublease_contract!$N:$N, "<=" & (TODAY()+20)) > 0, MINIFS(sublease_contract!$N:$N, sublease_contract!$C:$C, C11, sublease_contract!$D:$D, "*" & D11 & "*", sublease_contract!$G:$G, "<>已退租", sublease_contract!$N:$N, ">=" & TODAY(), sublease_contract!$N:$N, "<=" & (TODAY()+20)), "入住中"))), "") -> 入住中
A12: {=IFERROR( INDEX(big_rental_contract!A:A, MATCH(C12, big_rental_contract!F:F, 0)), "" )} -> A0002 | B12: RL00012 | C12: 內湖秘境 | D12: G | E12: 分租雅房 | F12: 頂加 | G12: 11.26 | H12: 12600 | I12: =IF(O12<>"空房招租中", O12, IF(N12="", "空房招租中", IF(ISNUMBER(SEARCH("分層", E12)), IF(COUNTIFS(N:N, N12, O:O, "<>空房招租中") > 0, "入住中", "空房招租中"), IF(COUNTIFS(N:N, N12, O:O, "<>空房招租中", E:E, "*分層*") > 0, "入住中", IF(COUNTIFS(N:N, N12, O:O, "空房招租中", E:E, "*分層*") > 0, "分層優先(隱藏)", "空房招租中") ) ) ) ) -> 入住中 | L12: =IF(AND(A12="", C12="", D12=""), "Z", "A") -> A | O12: =IF(AND(C12<>"", D12<>""), IF(COUNTIFS(sublease_contract!$C:$C, C12, sublease_contract!$D:$D, "*" & D12 & "*", sublease_contract!$G:$G, "<>已退租") = 0, "空房招租中", IF(COUNTIFS(sublease_contract!$C:$C, C12, sublease_contract!$D:$D, "*" & D12 & "*", sublease_contract!$G:$G, "<>已退租", sublease_contract!$N:$N, ">" & (TODAY()+20)) > 0, "入住中", IF(COUNTIFS(sublease_contract!$C:$C, C12, sublease_contract!$D:$D, "*" & D12 & "*", sublease_contract!$G:$G, "<>已退租", sublease_contract!$N:$N, ">=" & TODAY(), sublease_contract!$N:$N, "<=" & (TODAY()+20)) > 0, MINIFS(sublease_contract!$N:$N, sublease_contract!$C:$C, C12, sublease_contract!$D:$D, "*" & D12 & "*", sublease_contract!$G:$G, "<>已退租", sublease_contract!$N:$N, ">=" & TODAY(), sublease_contract!$N:$N, "<=" & (TODAY()+20)), "入住中"))), "") -> 入住中
A13: {=IFERROR( INDEX(big_rental_contract!A:A, MATCH(C13, big_rental_contract!F:F, 0)), "" )} -> A0003 | B13: RL00017 | C13: 龍江229 | D13: A | E13: 分租雅房 | F13: 無 | G13: 8.58 | H13: 13800 | I13: =IF(O13<>"空房招租中", O13, IF(N13="", "空房招租中", IF(ISNUMBER(SEARCH("分層", E13)), IF(COUNTIFS(N:N, N13, O:O, "<>空房招租中") > 0, "入住中", "空房招租中"), IF(COUNTIFS(N:N, N13, O:O, "<>空房招租中", E:E, "*分層*") > 0, "入住中", IF(COUNTIFS(N:N, N13, O:O, "空房招租中", E:E, "*分層*") > 0, "分層優先(隱藏)", "空房招租中") ) ) ) ) -> 入住中 | J13: 採光陽台雅房 | K13: https://youtube.com/shorts/f__aKIJfxsI?si=_5d10MINdTP7j2Da | L13: =IF(AND(A13="", C13="", D13=""), "Z", "A") -> A | O13: =IF(AND(C13<>"", D13<>""), IF(COUNTIFS(sublease_contract!$C:$C, C13, sublease_contract!$D:$D, "*" & D13 & "*", sublease_contract!$G:$G, "<>已退租") = 0, "空房招租中", IF(COUNTIFS(sublease_contract!$C:$C, C13, sublease_contract!$D:$D, "*" & D13 & "*", sublease_contract!$G:$G, "<>已退租", sublease_contract!$N:$N, ">" & (TODAY()+20)) > 0, "入住中", IF(COUNTIFS(sublease_contract!$C:$C, C13, sublease_contract!$D:$D, "*" & D13 & "*", sublease_contract!$G:$G, "<>已退租", sublease_contract!$N:$N, ">=" & TODAY(), sublease_contract!$N:$N, "<=" & (TODAY()+20)) > 0, MINIFS(sublease_contract!$N:$N, sublease_contract!$C:$C, C13, sublease_contract!$D:$D, "*" & D13 & "*", sublease_contract!$G:$G, "<>已退租", sublease_contract!$N:$N, ">=" & TODAY(), sublease_contract!$N:$N, "<=" & (TODAY()+20)), "入住中"))), "") -> 入住中
A14: {=IFERROR( INDEX(big_rental_contract!A:A, MATCH(C14, big_rental_contract!F:F, 0)), "" )} -> A0003 | B14: RL00018 | C14: 龍江229 | D14: B | E14: 分租雅房 | F14: 無 | G14: 8.86 | H14: 13500 | I14: =IF(O14<>"空房招租中", O14, IF(N14="", "空房招租中", IF(ISNUMBER(SEARCH("分層", E14)), IF(COUNTIFS(N:N, N14, O:O, "<>空房招租中") > 0, "入住中", "空房招租中"), IF(COUNTIFS(N:N, N14, O:O, "<>空房招租中", E:E, "*分層*") > 0, "入住中", IF(COUNTIFS(N:N, N14, O:O, "空房招租中", E:E, "*分層*") > 0, "分層優先(隱藏)", "空房招租中") ) ) ) ) -> 入住中 | J14: 採光陽台雅房 | K14: https://youtube.com/shorts/HCk9m8FNmF0?si=FaWFCcxbs1UKny1L | L14: =IF(AND(A14="", C14="", D14=""), "Z", "A") -> A | O14: =IF(AND(C14<>"", D14<>""), IF(COUNTIFS(sublease_contract!$C:$C, C14, sublease_contract!$D:$D, "*" & D14 & "*", sublease_contract!$G:$G, "<>已退租") = 0, "空房招租中", IF(COUNTIFS(sublease_contract!$C:$C, C14, sublease_contract!$D:$D, "*" & D14 & "*", sublease_contract!$G:$G, "<>已退租", sublease_contract!$N:$N, ">" & (TODAY()+20)) > 0, "入住中", IF(COUNTIFS(sublease_contract!$C:$C, C14, sublease_contract!$D:$D, "*" & D14 & "*", sublease_contract!$G:$G, "<>已退租", sublease_contract!$N:$N, ">=" & TODAY(), sublease_contract!$N:$N, "<=" & (TODAY()+20)) > 0, MINIFS(sublease_contract!$N:$N, sublease_contract!$C:$C, C14, sublease_contract!$D:$D, "*" & D14 & "*", sublease_contract!$G:$G, "<>已退租", sublease_contract!$N:$N, ">=" & TODAY(), sublease_contract!$N:$N, "<=" & (TODAY()+20)), "入住中"))), "") -> 入住中
A15: {=IFERROR( INDEX(big_rental_contract!A:A, MATCH(C15, big_rental_contract!F:F, 0)), "" )} -> A0003 | B15: RL00019 | C15: 龍江229 | D15: C | E15: 分租套房 | F15: 無 | G15: 14.58 | H15: 18800 | I15: =IF(O15<>"空房招租中", O15, IF(N15="", "空房招租中", IF(ISNUMBER(SEARCH("分層", E15)), IF(COUNTIFS(N:N, N15, O:O, "<>空房招租中") > 0, "入住中", "空房招租中"), IF(COUNTIFS(N:N, N15, O:O, "<>空房招租中", E:E, "*分層*") > 0, "入住中", IF(COUNTIFS(N:N, N15, O:O, "空房招租中", E:E, "*分層*") > 0, "分層優先(隱藏)", "空房招租中") ) ) ) ) -> 入住中 | J15: 全實牆大樹景採光高級大浴室套房 | K15: https://youtube.com/shorts/kl5RXn92Rrs?feature=share | L15: =IF(AND(A15="", C15="", D15=""), "Z", "A") -> A | O15: =IF(AND(C15<>"", D15<>""), IF(COUNTIFS(sublease_contract!$C:$C, C15, sublease_contract!$D:$D, "*" & D15 & "*", sublease_contract!$G:$G, "<>已退租") = 0, "空房招租中", IF(COUNTIFS(sublease_contract!$C:$C, C15, sublease_contract!$D:$D, "*" & D15 & "*", sublease_contract!$G:$G, "<>已退租", sublease_contract!$N:$N, ">" & (TODAY()+20)) > 0, "入住中", IF(COUNTIFS(sublease_contract!$C:$C, C15, sublease_contract!$D:$D, "*" & D15 & "*", sublease_contract!$G:$G, "<>已退租", sublease_contract!$N:$N, ">=" & TODAY(), sublease_contract!$N:$N, "<=" & (TODAY()+20)) > 0, MINIFS(sublease_contract!$N:$N, sublease_contract!$C:$C, C15, sublease_contract!$D:$D, "*" & D15 & "*", sublease_contract!$G:$G, "<>已退租", sublease_contract!$N:$N, ">=" & TODAY(), sublease_contract!$N:$N, "<=" & (TODAY()+20)), "入住中"))), "") -> 入住中
A16: {=IFERROR( INDEX(big_rental_contract!A:A, MATCH(C16, big_rental_contract!F:F, 0)), "" )} -> A0003 | B16: RL00020 | C16: 龍江229 | D16: D | E16: 分租雅房 | F16: 無 | G16: 8.85 | H16: 13300 | I16: =IF(O16<>"空房招租中", O16, IF(N16="", "空房招租中", IF(ISNUMBER(SEARCH("分層", E16)), IF(COUNTIFS(N:N, N16, O:O, "<>空房招租中") > 0, "入住中", "空房招租中"), IF(COUNTIFS(N:N, N16, O:O, "<>空房招租中", E:E, "*分層*") > 0, "入住中", IF(COUNTIFS(N:N, N16, O:O, "空房招租中", E:E, "*分層*") > 0, "分層優先(隱藏)", "空房招租中") ) ) ) ) -> 入住中 | J16: 全實牆雅房 | L16: =IF(AND(A16="", C16="", D16=""), "Z", "A") -> A | O16: =IF(AND(C16<>"", D16<>""), IF(COUNTIFS(sublease_contract!$C:$C, C16, sublease_contract!$D:$D, "*" & D16 & "*", sublease_contract!$G:$G, "<>已退租") = 0, "空房招租中", IF(COUNTIFS(sublease_contract!$C:$C, C16, sublease_contract!$D:$D, "*" & D16 & "*", sublease_contract!$G:$G, "<>已退租", sublease_contract!$N:$N, ">" & (TODAY()+20)) > 0, "入住中", IF(COUNTIFS(sublease_contract!$C:$C, C16, sublease_contract!$D:$D, "*" & D16 & "*", sublease_contract!$G:$G, "<>已退租", sublease_contract!$N:$N, ">=" & TODAY(), sublease_contract!$N:$N, "<=" & (TODAY()+20)) > 0, MINIFS(sublease_contract!$N:$N, sublease_contract!$C:$C, C16, sublease_contract!$D:$D, "*" & D16 & "*", sublease_contract!$G:$G, "<>已退租", sublease_contract!$N:$N, ">=" & TODAY(), sublease_contract!$N:$N, "<=" & (TODAY()+20)), "入住中"))), "") -> 入住中
A17: {=IFERROR( INDEX(big_rental_contract!A:A, MATCH(C17, big_rental_contract!F:F, 0)), "" )} -> A0003 | B17: RL00021 | C17: 龍江229 | D17: E | E17: 分租雅房 | F17: 無 | G17: 7.69 | H17: 11500 | I17: =IF(O17<>"空房招租中", O17, IF(N17="", "空房招租中", IF(ISNUMBER(SEARCH("分層", E17)), IF(COUNTIFS(N:N, N17, O:O, "<>空房招租中") > 0, "入住中", "空房招租中"), IF(COUNTIFS(N:N, N17, O:O, "<>空房招租中", E:E, "*分層*") > 0, "入住中", IF(COUNTIFS(N:N, N17, O:O, "空房招租中", E:E, "*分層*") > 0, "分層優先(隱藏)", "空房招租中") ) ) ) ) -> 入住中 | J17: 全實牆方正小雅房 | K17: https://youtu.be/HKUVG1fCFzg?si=sbMTrUIXQ4L8SwwB | L17: =IF(AND(A17="", C17="", D17=""), "Z", "A") -> A | O17: =IF(AND(C17<>"", D17<>""), IF(COUNTIFS(sublease_contract!$C:$C, C17, sublease_contract!$D:$D, "*" & D17 & "*", sublease_contract!$G:$G, "<>已退租") = 0, "空房招租中", IF(COUNTIFS(sublease_contract!$C:$C, C17, sublease_contract!$D:$D, "*" & D17 & "*", sublease_contract!$G:$G, "<>已退租", sublease_contract!$N:$N, ">" & (TODAY()+20)) > 0, "入住中", IF(COUNTIFS(sublease_contract!$C:$C, C17, sublease_contract!$D:$D, "*" & D17 & "*", sublease_contract!$G:$G, "<>已退租", sublease_contract!$N:$N, ">=" & TODAY(), sublease_contract!$N:$N, "<=" & (TODAY()+20)) > 0, MINIFS(sublease_contract!$N:$N, sublease_contract!$C:$C, C17, sublease_contract!$D:$D, "*" & D17 & "*", sublease_contract!$G:$G, "<>已退租", sublease_contract!$N:$N, ">=" & TODAY(), sublease_contract!$N:$N, "<=" & (TODAY()+20)), "入住中"))), "") -> 入住中
A18: {=IFERROR( INDEX(big_rental_contract!A:A, MATCH(C18, big_rental_contract!F:F, 0)), "" )} -> A0004 | B18: RL00022 | C18: 哈拉對面 | D18: A | E18: 分租雅房 | F18: 無 | G18: 7.18 | H18: 11000 | I18: =IF(O18<>"空房招租中", O18, IF(N18="", "空房招租中", IF(ISNUMBER(SEARCH("分層", E18)), IF(COUNTIFS(N:N, N18, O:O, "<>空房招租中") > 0, "入住中", "空房招租中"), IF(COUNTIFS(N:N, N18, O:O, "<>空房招租中", E:E, "*分層*") > 0, "入住中", IF(COUNTIFS(N:N, N18, O:O, "空房招租中", E:E, "*分層*") > 0, "分層優先(隱藏)", "空房招租中") ) ) ) ) -> 入住中 | J18: 落地採光窗雅房 | K18: https://youtu.be/_KXCqnnWhgw | L18: =IF(AND(A18="", C18="", D18=""), "Z", "A") -> A | O18: =IF(AND(C18<>"", D18<>""), IF(COUNTIFS(sublease_contract!$C:$C, C18, sublease_contract!$D:$D, "*" & D18 & "*", sublease_contract!$G:$G, "<>已退租") = 0, "空房招租中", IF(COUNTIFS(sublease_contract!$C:$C, C18, sublease_contract!$D:$D, "*" & D18 & "*", sublease_contract!$G:$G, "<>已退租", sublease_contract!$N:$N, ">" & (TODAY()+20)) > 0, "入住中", IF(COUNTIFS(sublease_contract!$C:$C, C18, sublease_contract!$D:$D, "*" & D18 & "*", sublease_contract!$G:$G, "<>已退租", sublease_contract!$N:$N, ">=" & TODAY(), sublease_contract!$N:$N, "<=" & (TODAY()+20)) > 0, MINIFS(sublease_contract!$N:$N, sublease_contract!$C:$C, C18, sublease_contract!$D:$D, "*" & D18 & "*", sublease_contract!$G:$G, "<>已退租", sublease_contract!$N:$N, ">=" & TODAY(), sublease_contract!$N:$N, "<=" & (TODAY()+20)), "入住中"))), "") -> 入住中
A19: {=IFERROR( INDEX(big_rental_contract!A:A, MATCH(C19, big_rental_contract!F:F, 0)), "" )} -> A0004 | B19: RL00023 | C19: 哈拉對面 | D19: B | E19: 分租套房 | F19: 無 | G19: 14.56 | H19: 15800 | I19: =IF(O19<>"空房招租中", O19, IF(N19="", "空房招租中", IF(ISNUMBER(SEARCH("分層", E19)), IF(COUNTIFS(N:N, N19, O:O, "<>空房招租中") > 0, "入住中", "空房招租中"), IF(COUNTIFS(N:N, N19, O:O, "<>空房招租中", E:E, "*分層*") > 0, "入住中", IF(COUNTIFS(N:N, N19, O:O, "空房招租中", E:E, "*分層*") > 0, "分層優先(隱藏)", "空房招租中") ) ) ) ) -> 入住中 | J19: 雙人床採光大套房 | K19: https://youtu.be/5cuncaRJsgQ | L19: =IF(AND(A19="", C19="", D19=""), "Z", "A") -> A | O19: =IF(AND(C19<>"", D19<>""), IF(COUNTIFS(sublease_contract!$C:$C, C19, sublease_contract!$D:$D, "*" & D19 & "*", sublease_contract!$G:$G, "<>已退租") = 0, "空房招租中", IF(COUNTIFS(sublease_contract!$C:$C, C19, sublease_contract!$D:$D, "*" & D19 & "*", sublease_contract!$G:$G, "<>已退租", sublease_contract!$N:$N, ">" & (TODAY()+20)) > 0, "入住中", IF(COUNTIFS(sublease_contract!$C:$C, C19, sublease_contract!$D:$D, "*" & D19 & "*", sublease_contract!$G:$G, "<>已退租", sublease_contract!$N:$N, ">=" & TODAY(), sublease_contract!$N:$N, "<=" & (TODAY()+20)) > 0, MINIFS(sublease_contract!$N:$N, sublease_contract!$C:$C, C19, sublease_contract!$D:$D, "*" & D19 & "*", sublease_contract!$G:$G, "<>已退租", sublease_contract!$N:$N, ">=" & TODAY(), sublease_contract!$N:$N, "<=" & (TODAY()+20)), "入住中"))), "") -> 入住中
A20: {=IFERROR( INDEX(big_rental_contract!A:A, MATCH(C20, big_rental_contract!F:F, 0)), "" )} -> A0004 | B20: RL00024 | C20: 哈拉對面 | D20: C | E20: 分租雅房 | F20: 無 | G20: 8.68 | H20: 11800 | I20: =IF(O20<>"空房招租中", O20, IF(N20="", "空房招租中", IF(ISNUMBER(SEARCH("分層", E20)), IF(COUNTIFS(N:N, N20, O:O, "<>空房招租中") > 0, "入住中", "空房招租中"), IF(COUNTIFS(N:N, N20, O:O, "<>空房招租中", E:E, "*分層*") > 0, "入住中", IF(COUNTIFS(N:N, N20, O:O, "空房招租中", E:E, "*分層*") > 0, "分層優先(隱藏)", "空房招租中") ) ) ) ) -> 入住中 | J20: 全實牆衣櫃雅房 | K20: https://youtu.be/sypXJ2lqQ3o | L20: =IF(AND(A20="", C20="", D20=""), "Z", "A") -> A | O20: =IF(AND(C20<>"", D20<>""), IF(COUNTIFS(sublease_contract!$C:$C, C20, sublease_contract!$D:$D, "*" & D20 & "*", sublease_contract!$G:$G, "<>已退租") = 0, "空房招租中", IF(COUNTIFS(sublease_contract!$C:$C, C20, sublease_contract!$D:$D, "*" & D20 & "*", sublease_contract!$G:$G, "<>已退租", sublease_contract!$N:$N, ">" & (TODAY()+20)) > 0, "入住中", IF(COUNTIFS(sublease_contract!$C:$C, C20, sublease_contract!$D:$D, "*" & D20 & "*", sublease_contract!$G:$G, "<>已退租", sublease_contract!$N:$N, ">=" & TODAY(), sublease_contract!$N:$N, "<=" & (TODAY()+20)) > 0, MINIFS(sublease_contract!$N:$N, sublease_contract!$C:$C, C20, sublease_contract!$D:$D, "*" & D20 & "*", sublease_contract!$G:$G, "<>已退租", sublease_contract!$N:$N, ">=" & TODAY(), sublease_contract!$N:$N, "<=" & (TODAY()+20)), "入住中"))), "") -> 入住中
A21: {=IFERROR( INDEX(big_rental_contract!A:A, MATCH(C21, big_rental_contract!F:F, 0)), "" )} -> A0004 | B21: RL00025 | C21: 哈拉對面 | D21: D | E21: 分租雅房 | F21: 無 | G21: 8.13 | H21: 12300 | I21: =IF(O21<>"空房招租中", O21, IF(N21="", "空房招租中", IF(ISNUMBER(SEARCH("分層", E21)), IF(COUNTIFS(N:N, N21, O:O, "<>空房招租中") > 0, "入住中", "空房招租中"), IF(COUNTIFS(N:N, N21, O:O, "<>空房招租中", E:E, "*分層*") > 0, "入住中", IF(COUNTIFS(N:N, N21, O:O, "空房招租中", E:E, "*分層*") > 0, "分層優先(隱藏)", "空房招租中") ) ) ) ) -> 入住中 | J21: 大大大衣櫃雅房 | K21: https://youtube.com/shorts/7DcBnbE-QfQ?si=vKq2e4gpMYhtGy7W | L21: =IF(AND(A21="", C21="", D21=""), "Z", "A") -> A | O21: =IF(AND(C21<>"", D21<>""), IF(COUNTIFS(sublease_contract!$C:$C, C21, sublease_contract!$D:$D, "*" & D21 & "*", sublease_contract!$G:$G, "<>已退租") = 0, "空房招租中", IF(COUNTIFS(sublease_contract!$C:$C, C21, sublease_contract!$D:$D, "*" & D21 & "*", sublease_contract!$G:$G, "<>已退租", sublease_contract!$N:$N, ">" & (TODAY()+20)) > 0, "入住中", IF(COUNTIFS(sublease_contract!$C:$C, C21, sublease_contract!$D:$D, "*" & D21 & "*", sublease_contract!$G:$G, "<>已退租", sublease_contract!$N:$N, ">=" & TODAY(), sublease_contract!$N:$N, "<=" & (TODAY()+20)) > 0, MINIFS(sublease_contract!$N:$N, sublease_contract!$C:$C, C21, sublease_contract!$D:$D, "*" & D21 & "*", sublease_contract!$G:$G, "<>已退租", sublease_contract!$N:$N, ">=" & TODAY(), sublease_contract!$N:$N, "<=" & (TODAY()+20)), "入住中"))), "") -> 入住中
A22: {=IFERROR( INDEX(big_rental_contract!A:A, MATCH(C22, big_rental_contract!F:F, 0)), "" )} -> A0005 | B22: RL00026 | C22: 北醫醫師府 | D22: A | E22: 分租雅房 | F22: 無 | G22: 8.95 | H22: 13000 | I22: =IF(O22<>"空房招租中", O22, IF(N22="", "空房招租中", IF(ISNUMBER(SEARCH("分層", E22)), IF(COUNTIFS(N:N, N22, O:O, "<>空房招租中") > 0, "入住中", "空房招租中"), IF(COUNTIFS(N:N, N22, O:O, "<>空房招租中", E:E, "*分層*") > 0, "入住中", IF(COUNTIFS(N:N, N22, O:O, "空房招租中", E:E, "*分層*") > 0, "分層優先(隱藏)", "空房招租中") ) ) ) ) -> 入住中 | K22: https://youtube.com/shorts/Hc8fDLPxR2s?si=yi_8BaevlJvKThX8 | L22: =IF(AND(A22="", C22="", D22=""), "Z", "A") -> A | O22: =IF(AND(C22<>"", D22<>""), IF(COUNTIFS(sublease_contract!$C:$C, C22, sublease_contract!$D:$D, "*" & D22 & "*", sublease_contract!$G:$G, "<>已退租") = 0, "空房招租中", IF(COUNTIFS(sublease_contract!$C:$C, C22, sublease_contract!$D:$D, "*" & D22 & "*", sublease_contract!$G:$G, "<>已退租", sublease_contract!$N:$N, ">" & (TODAY()+20)) > 0, "入住中", IF(COUNTIFS(sublease_contract!$C:$C, C22, sublease_contract!$D:$D, "*" & D22 & "*", sublease_contract!$G:$G, "<>已退租", sublease_contract!$N:$N, ">=" & TODAY(), sublease_contract!$N:$N, "<=" & (TODAY()+20)) > 0, MINIFS(sublease_contract!$N:$N, sublease_contract!$C:$C, C22, sublease_contract!$D:$D, "*" & D22 & "*", sublease_contract!$G:$G, "<>已退租", sublease_contract!$N:$N, ">=" & TODAY(), sublease_contract!$N:$N, "<=" & (TODAY()+20)), "入住中"))), "") -> 入住中
A23: {=IFERROR( INDEX(big_rental_contract!A:A, MATCH(C23, big_rental_contract!F:F, 0)), "" )} -> A0005 | B23: RL00027 | C23: 北醫醫師府 | D23: B | E23: 分租套房 | F23: 無 | G23: 14.27 | H23: 17800 | I23: =IF(O23<>"空房招租中", O23, IF(N23="", "空房招租中", IF(ISNUMBER(SEARCH("分層", E23)), IF(COUNTIFS(N:N, N23, O:O, "<>空房招租中") > 0, "入住中", "空房招租中"), IF(COUNTIFS(N:N, N23, O:O, "<>空房招租中", E:E, "*分層*") > 0, "入住中", IF(COUNTIFS(N:N, N23, O:O, "空房招租中", E:E, "*分層*") > 0, "分層優先(隱藏)", "空房招租中") ) ) ) ) -> 入住中 | L23: =IF(AND(A23="", C23="", D23=""), "Z", "A") -> A | O23: =IF(AND(C23<>"", D23<>""), IF(COUNTIFS(sublease_contract!$C:$C, C23, sublease_contract!$D:$D, "*" & D23 & "*", sublease_contract!$G:$G, "<>已退租") = 0, "空房招租中", IF(COUNTIFS(sublease_contract!$C:$C, C23, sublease_contract!$D:$D, "*" & D23 & "*", sublease_contract!$G:$G, "<>已退租", sublease_contract!$N:$N, ">" & (TODAY()+20)) > 0, "入住中", IF(COUNTIFS(sublease_contract!$C:$C, C23, sublease_contract!$D:$D, "*" & D23 & "*", sublease_contract!$G:$G, "<>已退租", sublease_contract!$N:$N, ">=" & TODAY(), sublease_contract!$N:$N, "<=" & (TODAY()+20)) > 0, MINIFS(sublease_contract!$N:$N, sublease_contract!$C:$C, C23, sublease_contract!$D:$D, "*" & D23 & "*", sublease_contract!$G:$G, "<>已退租", sublease_contract!$N:$N, ">=" & TODAY(), sublease_contract!$N:$N, "<=" & (TODAY()+20)), "入住中"))), "") -> 入住中
A24: {=IFERROR( INDEX(big_rental_contract!A:A, MATCH(C24, big_rental_contract!F:F, 0)), "" )} -> A0005 | B24: RL00028 | C24: 北醫醫師府 | D24: C | E24: 分租雅房 | F24: 無 | G24: 9.12 | H24: 13000 | I24: =IF(O24<>"空房招租中", O24, IF(N24="", "空房招租中", IF(ISNUMBER(SEARCH("分層", E24)), IF(COUNTIFS(N:N, N24, O:O, "<>空房招租中") > 0, "入住中", "空房招租中"), IF(COUNTIFS(N:N, N24, O:O, "<>空房招租中", E:E, "*分層*") > 0, "入住中", IF(COUNTIFS(N:N, N24, O:O, "空房招租中", E:E, "*分層*") > 0, "分層優先(隱藏)", "空房招租中") ) ) ) ) -> 入住中 | L24: =IF(AND(A24="", C24="", D24=""), "Z", "A") -> A | O24: =IF(AND(C24<>"", D24<>""), IF(COUNTIFS(sublease_contract!$C:$C, C24, sublease_contract!$D:$D, "*" & D24 & "*", sublease_contract!$G:$G, "<>已退租") = 0, "空房招租中", IF(COUNTIFS(sublease_contract!$C:$C, C24, sublease_contract!$D:$D, "*" & D24 & "*", sublease_contract!$G:$G, "<>已退租", sublease_contract!$N:$N, ">" & (TODAY()+20)) > 0, "入住中", IF(COUNTIFS(sublease_contract!$C:$C, C24, sublease_contract!$D:$D, "*" & D24 & "*", sublease_contract!$G:$G, "<>已退租", sublease_contract!$N:$N, ">=" & TODAY(), sublease_contract!$N:$N, "<=" & (TODAY()+20)) > 0, MINIFS(sublease_contract!$N:$N, sublease_contract!$C:$C, C24, sublease_contract!$D:$D, "*" & D24 & "*", sublease_contract!$G:$G, "<>已退租", sublease_contract!$N:$N, ">=" & TODAY(), sublease_contract!$N:$N, "<=" & (TODAY()+20)), "入住中"))), "") -> 入住中
A25: {=IFERROR( INDEX(big_rental_contract!A:A, MATCH(C25, big_rental_contract!F:F, 0)), "" )} -> A0005 | B25: RL00029 | C25: 北醫醫師府 | D25: D | E25: 分租雅房 | F25: 無 | G25: 7.75 | H25: 12500 | I25: =IF(O25<>"空房招租中", O25, IF(N25="", "空房招租中", IF(ISNUMBER(SEARCH("分層", E25)), IF(COUNTIFS(N:N, N25, O:O, "<>空房招租中") > 0, "入住中", "空房招租中"), IF(COUNTIFS(N:N, N25, O:O, "<>空房招租中", E:E, "*分層*") > 0, "入住中", IF(COUNTIFS(N:N, N25, O:O, "空房招租中", E:E, "*分層*") > 0, "分層優先(隱藏)", "空房招租中") ) ) ) ) -> 入住中 | L25: =IF(AND(A25="", C25="", D25=""), "Z", "A") -> A | O25: =IF(AND(C25<>"", D25<>""), IF(COUNTIFS(sublease_contract!$C:$C, C25, sublease_contract!$D:$D, "*" & D25 & "*", sublease_contract!$G:$G, "<>已退租") = 0, "空房招租中", IF(COUNTIFS(sublease_contract!$C:$C, C25, sublease_contract!$D:$D, "*" & D25 & "*", sublease_contract!$G:$G, "<>已退租", sublease_contract!$N:$N, ">" & (TODAY()+20)) > 0, "入住中", IF(COUNTIFS(sublease_contract!$C:$C, C25, sublease_contract!$D:$D, "*" & D25 & "*", sublease_contract!$G:$G, "<>已退租", sublease_contract!$N:$N, ">=" & TODAY(), sublease_contract!$N:$N, "<=" & (TODAY()+20)) > 0, MINIFS(sublease_contract!$N:$N, sublease_contract!$C:$C, C25, sublease_contract!$D:$D, "*" & D25 & "*", sublease_contract!$G:$G, "<>已退租", sublease_contract!$N:$N, ">=" & TODAY(), sublease_contract!$N:$N, "<=" & (TODAY()+20)), "入住中"))), "") -> 入住中
A26: {=IFERROR( INDEX(big_rental_contract!A:A, MATCH(C26, big_rental_contract!F:F, 0)), "" )} -> A0005 | B26: RL00030 | C26: 北醫醫師府 | D26: E | E26: 分租雅房 | F26: 頂加 | G26: 13.35 | H26: 14800 | I26: =IF(O26<>"空房招租中", O26, IF(N26="", "空房招租中", IF(ISNUMBER(SEARCH("分層", E26)), IF(COUNTIFS(N:N, N26, O:O, "<>空房招租中") > 0, "入住中", "空房招租中"), IF(COUNTIFS(N:N, N26, O:O, "<>空房招租中", E:E, "*分層*") > 0, "入住中", IF(COUNTIFS(N:N, N26, O:O, "空房招租中", E:E, "*分層*") > 0, "分層優先(隱藏)", "空房招租中") ) ) ) ) -> 入住中 | J26: 落地窗大採光超多收納雅房 | K26: https://youtu.be/OQCdRPBv1HU | L26: =IF(AND(A26="", C26="", D26=""), "Z", "A") -> A | M26: 無 | N26: Group_Top_01 | O26: =IF(AND(C26<>"", D26<>""), IF(COUNTIFS(sublease_contract!$C:$C, C26, sublease_contract!$D:$D, "*" & D26 & "*", sublease_contract!$G:$G, "<>已退租") = 0, "空房招租中", IF(COUNTIFS(sublease_contract!$C:$C, C26, sublease_contract!$D:$D, "*" & D26 & "*", sublease_contract!$G:$G, "<>已退租", sublease_contract!$N:$N, ">" & (TODAY()+20)) > 0, "入住中", IF(COUNTIFS(sublease_contract!$C:$C, C26, sublease_contract!$D:$D, "*" & D26 & "*", sublease_contract!$G:$G, "<>已退租", sublease_contract!$N:$N, ">=" & TODAY(), sublease_contract!$N:$N, "<=" & (TODAY()+20)) > 0, MINIFS(sublease_contract!$N:$N, sublease_contract!$C:$C, C26, sublease_contract!$D:$D, "*" & D26 & "*", sublease_contract!$G:$G, "<>已退租", sublease_contract!$N:$N, ">=" & TODAY(), sublease_contract!$N:$N, "<=" & (TODAY()+20)), "入住中"))), "") -> 入住中
A27: {=IFERROR( INDEX(big_rental_contract!A:A, MATCH(C27, big_rental_contract!F:F, 0)), "" )} -> A0005 | B27: RL00031 | C27: 北醫醫師府 | D27: F | E27: 分租雅房 | F27: 頂加 | G27: 14.25 | H27: 14800 | I27: =IF(O27<>"空房招租中", O27, IF(N27="", "空房招租中", IF(ISNUMBER(SEARCH("分層", E27)), IF(COUNTIFS(N:N, N27, O:O, "<>空房招租中") > 0, "入住中", "空房招租中"), IF(COUNTIFS(N:N, N27, O:O, "<>空房招租中", E:E, "*分層*") > 0, "入住中", IF(COUNTIFS(N:N, N27, O:O, "空房招租中", E:E, "*分層*") > 0, "分層優先(隱藏)", "空房招租中") ) ) ) ) -> 入住中 | J27: 雙面採光開窗賞101夜景雅房F | K27: https://youtu.be/0Mv8x7Ghvjs | L27: =IF(AND(A27="", C27="", D27=""), "Z", "A") -> A | M27: 無 | N27: Group_Top_01 | O27: =IF(AND(C27<>"", D27<>""), IF(COUNTIFS(sublease_contract!$C:$C, C27, sublease_contract!$D:$D, "*" & D27 & "*", sublease_contract!$G:$G, "<>已退租") = 0, "空房招租中", IF(COUNTIFS(sublease_contract!$C:$C, C27, sublease_contract!$D:$D, "*" & D27 & "*", sublease_contract!$G:$G, "<>已退租", sublease_contract!$N:$N, ">" & (TODAY()+20)) > 0, "入住中", IF(COUNTIFS(sublease_contract!$C:$C, C27, sublease_contract!$D:$D, "*" & D27 & "*", sublease_contract!$G:$G, "<>已退租", sublease_contract!$N:$N, ">=" & TODAY(), sublease_contract!$N:$N, "<=" & (TODAY()+20)) > 0, MINIFS(sublease_contract!$N:$N, sublease_contract!$C:$C, C27, sublease_contract!$D:$D, "*" & D27 & "*", sublease_contract!$G:$G, "<>已退租", sublease_contract!$N:$N, ">=" & TODAY(), sublease_contract!$N:$N, "<=" & (TODAY()+20)), "入住中"))), "") -> 入住中
A28: {=IFERROR( INDEX(big_rental_contract!A:A, MATCH(C28, big_rental_contract!F:F, 0)), "" )} -> A0006 | B28: RL00032 | C28: 大湖山莊 | D28: A | E28: 分租雅房 | F28: 無 | G28: 10.13 | H28: 13000 | I28: =IF(O28<>"空房招租中", O28, IF(N28="", "空房招租中", IF(ISNUMBER(SEARCH("分層", E28)), IF(COUNTIFS(N:N, N28, O:O, "<>空房招租中") > 0, "入住中", "空房招租中"), IF(COUNTIFS(N:N, N28, O:O, "<>空房招租中", E:E, "*分層*") > 0, "入住中", IF(COUNTIFS(N:N, N28, O:O, "空房招租中", E:E, "*分層*") > 0, "分層優先(隱藏)", "空房招租中") ) ) ) ) -> 入住中 | J28: 挑高3米通風大雅房 | K28: https://www.youtube.com/shorts/BVANUELortA | L28: =IF(AND(A28="", C28="", D28=""), "Z", "A") -> A | O28: =IF(AND(C28<>"", D28<>""), IF(COUNTIFS(sublease_contract!$C:$C, C28, sublease_contract!$D:$D, "*" & D28 & "*", sublease_contract!$G:$G, "<>已退租") = 0, "空房招租中", IF(COUNTIFS(sublease_contract!$C:$C, C28, sublease_contract!$D:$D, "*" & D28 & "*", sublease_contract!$G:$G, "<>已退租", sublease_contract!$N:$N, ">" & (TODAY()+20)) > 0, "入住中", IF(COUNTIFS(sublease_contract!$C:$C, C28, sublease_contract!$D:$D, "*" & D28 & "*", sublease_contract!$G:$G, "<>已退租", sublease_contract!$N:$N, ">=" & TODAY(), sublease_contract!$N:$N, "<=" & (TODAY()+20)) > 0, MINIFS(sublease_contract!$N:$N, sublease_contract!$C:$C, C28, sublease_contract!$D:$D, "*" & D28 & "*", sublease_contract!$G:$G, "<>已退租", sublease_contract!$N:$N, ">=" & TODAY(), sublease_contract!$N:$N, "<=" & (TODAY()+20)), "入住中"))), "") -> 入住中
A29: {=IFERROR( INDEX(big_rental_contract!A:A, MATCH(C29, big_rental_contract!F:F, 0)), "" )} -> A0006 | B29: RL00033 | C29: 大湖山莊 | D29: B | E29: 分租雅房 | F29: 無 | G29: 8.94 | H29: 12000 | I29: =IF(O29<>"空房招租中", O29, IF(N29="", "空房招租中", IF(ISNUMBER(SEARCH("分層", E29)), IF(COUNTIFS(N:N, N29, O:O, "<>空房招租中") > 0, "入住中", "空房招租中"), IF(COUNTIFS(N:N, N29, O:O, "<>空房招租中", E:E, "*分層*") > 0, "入住中", IF(COUNTIFS(N:N, N29, O:O, "空房招租中", E:E, "*分層*") > 0, "分層優先(隱藏)", "空房招租中") ) ) ) ) -> 入住中 | J29: 方正實心牆典雅雅房 | K29: https://youtube.com/shorts/Fvij9jinV0I?si=tbMFzPki-t7Xte74 | L29: =IF(AND(A29="", C29="", D29=""), "Z", "A") -> A | O29: =IF(AND(C29<>"", D29<>""), IF(COUNTIFS(sublease_contract!$C:$C, C29, sublease_contract!$D:$D, "*" & D29 & "*", sublease_contract!$G:$G, "<>已退租") = 0, "空房招租中", IF(COUNTIFS(sublease_contract!$C:$C, C29, sublease_contract!$D:$D, "*" & D29 & "*", sublease_contract!$G:$G, "<>已退租", sublease_contract!$N:$N, ">" & (TODAY()+20)) > 0, "入住中", IF(COUNTIFS(sublease_contract!$C:$C, C29, sublease_contract!$D:$D, "*" & D29 & "*", sublease_contract!$G:$G, "<>已退租", sublease_contract!$N:$N, ">=" & TODAY(), sublease_contract!$N:$N, "<=" & (TODAY()+20)) > 0, MINIFS(sublease_contract!$N:$N, sublease_contract!$C:$C, C29, sublease_contract!$D:$D, "*" & D29 & "*", sublease_contract!$G:$G, "<>已退租", sublease_contract!$N:$N, ">=" & TODAY(), sublease_contract!$N:$N, "<=" & (TODAY()+20)), "入住中"))), "") -> 入住中
A30: {=IFERROR( INDEX(big_rental_contract!A:A, MATCH(C30, big_rental_contract!F:F, 0)), "" )} -> A0006 | B30: RL00034 | C30: 大湖山莊 | D30: C | E30: 分租套房 | F30: 無 | G30: 26.72 | H30: 20800 | I30: =IF(O30<>"空房招租中", O30, IF(N30="", "空房招租中", IF(ISNUMBER(SEARCH("分層", E30)), IF(COUNTIFS(N:N, N30, O:O, "<>空房招租中") > 0, "入住中", "空房招租中"), IF(COUNTIFS(N:N, N30, O:O, "<>空房招租中", E:E, "*分層*") > 0, "入住中", IF(COUNTIFS(N:N, N30, O:O, "空房招租中", E:E, "*分層*") > 0, "分層優先(隱藏)", "空房招租中") ) ) ) ) -> 入住中 | J30: 獨立陽台獨立洗衣機大套房 | L30: =IF(AND(A30="", C30="", D30=""), "Z", "A") -> A | O30: =IF(AND(C30<>"", D30<>""), IF(COUNTIFS(sublease_contract!$C:$C, C30, sublease_contract!$D:$D, "*" & D30 & "*", sublease_contract!$G:$G, "<>已退租") = 0, "空房招租中", IF(COUNTIFS(sublease_contract!$C:$C, C30, sublease_contract!$D:$D, "*" & D30 & "*", sublease_contract!$G:$G, "<>已退租", sublease_contract!$N:$N, ">" & (TODAY()+20)) > 0, "入住中", IF(COUNTIFS(sublease_contract!$C:$C, C30, sublease_contract!$D:$D, "*" & D30 & "*", sublease_contract!$G:$G, "<>已退租", sublease_contract!$N:$N, ">=" & TODAY(), sublease_contract!$N:$N, "<=" & (TODAY()+20)) > 0, MINIFS(sublease_contract!$N:$N, sublease_contract!$C:$C, C30, sublease_contract!$D:$D, "*" & D30 & "*", sublease_contract!$G:$G, "<>已退租", sublease_contract!$N:$N, ">=" & TODAY(), sublease_contract!$N:$N, "<=" & (TODAY()+20)), "入住中"))), "") -> 入住中
A31: {=IFERROR( INDEX(big_rental_contract!A:A, MATCH(C31, big_rental_contract!F:F, 0)), "" )} -> A0006 | B31: RL00035 | C31: 大湖山莊 | D31: D | E31: 分租雅房 | F31: 無 | G31: 14.7 | H31: 14800 | I31: =IF(O31<>"空房招租中", O31, IF(N31="", "空房招租中", IF(ISNUMBER(SEARCH("分層", E31)), IF(COUNTIFS(N:N, N31, O:O, "<>空房招租中") > 0, "入住中", "空房招租中"), IF(COUNTIFS(N:N, N31, O:O, "<>空房招租中", E:E, "*分層*") > 0, "入住中", IF(COUNTIFS(N:N, N31, O:O, "空房招租中", E:E, "*分層*") > 0, "分層優先(隱藏)", "空房招租中") ) ) ) ) -> 入住中 | J31: 四櫃收納瑜珈人大雅房 | L31: =IF(AND(A31="", C31="", D31=""), "Z", "A") -> A | O31: =IF(AND(C31<>"", D31<>""), IF(COUNTIFS(sublease_contract!$C:$C, C31, sublease_contract!$D:$D, "*" & D31 & "*", sublease_contract!$G:$G, "<>已退租") = 0, "空房招租中", IF(COUNTIFS(sublease_contract!$C:$C, C31, sublease_contract!$D:$D, "*" & D31 & "*", sublease_contract!$G:$G, "<>已退租", sublease_contract!$N:$N, ">" & (TODAY()+20)) > 0, "入住中", IF(COUNTIFS(sublease_contract!$C:$C, C31, sublease_contract!$D:$D, "*" & D31 & "*", sublease_contract!$G:$G, "<>已退租", sublease_contract!$N:$N, ">=" & TODAY(), sublease_contract!$N:$N, "<=" & (TODAY()+20)) > 0, MINIFS(sublease_contract!$N:$N, sublease_contract!$C:$C, C31, sublease_contract!$D:$D, "*" & D31 & "*", sublease_contract!$G:$G, "<>已退租", sublease_contract!$N:$N, ">=" & TODAY(), sublease_contract!$N:$N, "<=" & (TODAY()+20)), "入住中"))), "") -> 入住中
A32: {=IFERROR( INDEX(big_rental_contract!A:A, MATCH(C32, big_rental_contract!F:F, 0)), "" )} -> A0006 | B32: RL00036 | C32: 大湖山莊 | D32: E | E32: 分租雅房 | F32: 無 | G32: 9.2 | H32: 12500 | I32: =IF(O32<>"空房招租中", O32, IF(N32="", "空房招租中", IF(ISNUMBER(SEARCH("分層", E32)), IF(COUNTIFS(N:N, N32, O:O, "<>空房招租中") > 0, "入住中", "空房招租中"), IF(COUNTIFS(N:N, N32, O:O, "<>空房招租中", E:E, "*分層*") > 0, "入住中", IF(COUNTIFS(N:N, N32, O:O, "空房招租中", E:E, "*分層*") > 0, "分層優先(隱藏)", "空房招租中") ) ) ) ) -> 入住中 | J32: 有標準門的和式清幽雅房 | L32: =IF(AND(A32="", C32="", D32=""), "Z", "A") -> A | O32: =IF(AND(C32<>"", D32<>""), IF(COUNTIFS(sublease_contract!$C:$C, C32, sublease_contract!$D:$D, "*" & D32 & "*", sublease_contract!$G:$G, "<>已退租") = 0, "空房招租中", IF(COUNTIFS(sublease_contract!$C:$C, C32, sublease_contract!$D:$D, "*" & D32 & "*", sublease_contract!$G:$G, "<>已退租", sublease_contract!$N:$N, ">" & (TODAY()+20)) > 0, "入住中", IF(COUNTIFS(sublease_contract!$C:$C, C32, sublease_contract!$D:$D, "*" & D32 & "*", sublease_contract!$G:$G, "<>已退租", sublease_contract!$N:$N, ">=" & TODAY(), sublease_contract!$N:$N, "<=" & (TODAY()+20)) > 0, MINIFS(sublease_contract!$N:$N, sublease_contract!$C:$C, C32, sublease_contract!$D:$D, "*" & D32 & "*", sublease_contract!$G:$G, "<>已退租", sublease_contract!$N:$N, ">=" & TODAY(), sublease_contract!$N:$N, "<=" & (TODAY()+20)), "入住中"))), "") -> 入住中
A33: {=IFERROR( INDEX(big_rental_contract!A:A, MATCH(C33, big_rental_contract!F:F, 0)), "" )} -> A0006 | B33: RL00037 | C33: 大湖山莊 | D33: F | E33: 分租雅房 | F33: 頂加 | G33: 22.3 | H33: 17800 | I33: =IF(O33<>"空房招租中", O33, IF(N33="", "空房招租中", IF(ISNUMBER(SEARCH("分層", E33)), IF(COUNTIFS(N:N, N33, O:O, "<>空房招租中") > 0, "入住中", "空房招租中"), IF(COUNTIFS(N:N, N33, O:O, "<>空房招租中", E:E, "*分層*") > 0, "入住中", IF(COUNTIFS(N:N, N33, O:O, "空房招租中", E:E, "*分層*") > 0, "分層優先(隱藏)", "空房招租中") ) ) ) ) -> 入住中 | J33: 大空間超多收納一房一廳頂加採光雅房 | K33: https://youtu.be/X1mOO7o74Uk | L33: =IF(AND(A33="", C33="", D33=""), "Z", "A") -> A | O33: =IF(AND(C33<>"", D33<>""), IF(COUNTIFS(sublease_contract!$C:$C, C33, sublease_contract!$D:$D, "*" & D33 & "*", sublease_contract!$G:$G, "<>已退租") = 0, "空房招租中", IF(COUNTIFS(sublease_contract!$C:$C, C33, sublease_contract!$D:$D, "*" & D33 & "*", sublease_contract!$G:$G, "<>已退租", sublease_contract!$N:$N, ">" & (TODAY()+20)) > 0, "入住中", IF(COUNTIFS(sublease_contract!$C:$C, C33, sublease_contract!$D:$D, "*" & D33 & "*", sublease_contract!$G:$G, "<>已退租", sublease_contract!$N:$N, ">=" & TODAY(), sublease_contract!$N:$N, "<=" & (TODAY()+20)) > 0, MINIFS(sublease_contract!$N:$N, sublease_contract!$C:$C, C33, sublease_contract!$D:$D, "*" & D33 & "*", sublease_contract!$G:$G, "<>已退租", sublease_contract!$N:$N, ">=" & TODAY(), sublease_contract!$N:$N, "<=" & (TODAY()+20)), "入住中"))), "") -> 入住中
A34: {=IFERROR( INDEX(big_rental_contract!A:A, MATCH(C34, big_rental_contract!F:F, 0)), "" )} -> A0006 | B34: RL00038 | C34: 大湖山莊 | D34: G | E34: 分租雅房 | F34: 頂加 | G34: 12.96 | H34: 15800 | I34: =IF(O34<>"空房招租中", O34, IF(N34="", "空房招租中", IF(ISNUMBER(SEARCH("分層", E34)), IF(COUNTIFS(N:N, N34, O:O, "<>空房招租中") > 0, "入住中", "空房招租中"), IF(COUNTIFS(N:N, N34, O:O, "<>空房招租中", E:E, "*分層*") > 0, "入住中", IF(COUNTIFS(N:N, N34, O:O, "空房招租中", E:E, "*分層*") > 0, "分層優先(隱藏)", "空房招租中") ) ) ) ) -> 入住中 | J34: 大片採光 獨立陽台 獨立洗衣機 頂加雅房 | K34: https://www.youtube.com/shorts/H7Gx0qFtcmI | L34: =IF(AND(A34="", C34="", D34=""), "Z", "A") -> A | O34: =IF(AND(C34<>"", D34<>""), IF(COUNTIFS(sublease_contract!$C:$C, C34, sublease_contract!$D:$D, "*" & D34 & "*", sublease_contract!$G:$G, "<>已退租") = 0, "空房招租中", IF(COUNTIFS(sublease_contract!$C:$C, C34, sublease_contract!$D:$D, "*" & D34 & "*", sublease_contract!$G:$G, "<>已退租", sublease_contract!$N:$N, ">" & (TODAY()+20)) > 0, "入住中", IF(COUNTIFS(sublease_contract!$C:$C, C34, sublease_contract!$D:$D, "*" & D34 & "*", sublease_contract!$G:$G, "<>已退租", sublease_contract!$N:$N, ">=" & TODAY(), sublease_contract!$N:$N, "<=" & (TODAY()+20)) > 0, MINIFS(sublease_contract!$N:$N, sublease_contract!$C:$C, C34, sublease_contract!$D:$D, "*" & D34 & "*", sublease_contract!$G:$G, "<>已退租", sublease_contract!$N:$N, ">=" & TODAY(), sublease_contract!$N:$N, "<=" & (TODAY()+20)), "入住中"))), "") -> 入住中
A35: {=IFERROR( INDEX(big_rental_contract!A:A, MATCH(C35, big_rental_contract!F:F, 0)), "" )} -> A0007 | B35: RL00013 | C35: 士林和豐 | D35: A | E35: 分租套房 | F35: 無 | G35: 20.95 | H35: 19500 | I35: =IF(O35<>"空房招租中", O35, IF(N35="", "空房招租中", IF(ISNUMBER(SEARCH("分層", E35)), IF(COUNTIFS(N:N, N35, O:O, "<>空房招租中") > 0, "入住中", "空房招租中"), IF(COUNTIFS(N:N, N35, O:O, "<>空房招租中", E:E, "*分層*") > 0, "入住中", IF(COUNTIFS(N:N, N35, O:O, "空房招租中", E:E, "*分層*") > 0, "分層優先(隱藏)", "空房招租中") ) ) ) ) -> 入住中 | L35: =IF(AND(A35="", C35="", D35=""), "Z", "A") -> A | O35: =IF(AND(C35<>"", D35<>""), IF(COUNTIFS(sublease_contract!$C:$C, C35, sublease_contract!$D:$D, "*" & D35 & "*", sublease_contract!$G:$G, "<>已退租") = 0, "空房招租中", IF(COUNTIFS(sublease_contract!$C:$C, C35, sublease_contract!$D:$D, "*" & D35 & "*", sublease_contract!$G:$G, "<>已退租", sublease_contract!$N:$N, ">" & (TODAY()+20)) > 0, "入住中", IF(COUNTIFS(sublease_contract!$C:$C, C35, sublease_contract!$D:$D, "*" & D35 & "*", sublease_contract!$G:$G, "<>已退租", sublease_contract!$N:$N, ">=" & TODAY(), sublease_contract!$N:$N, "<=" & (TODAY()+20)) > 0, MINIFS(sublease_contract!$N:$N, sublease_contract!$C:$C, C35, sublease_contract!$D:$D, "*" & D35 & "*", sublease_contract!$G:$G, "<>已退租", sublease_contract!$N:$N, ">=" & TODAY(), sublease_contract!$N:$N, "<=" & (TODAY()+20)), "入住中"))), "") -> 入住中
A36: {=IFERROR( INDEX(big_rental_contract!A:A, MATCH(C36, big_rental_contract!F:F, 0)), "" )} -> A0007 | B36: RL00014 | C36: 士林和豐 | D36: B | E36: 分租雅房 | F36: 無 | G36: 10.34 | H36: 13500 | I36: =IF(O36<>"空房招租中", O36, IF(N36="", "空房招租中", IF(ISNUMBER(SEARCH("分層", E36)), IF(COUNTIFS(N:N, N36, O:O, "<>空房招租中") > 0, "入住中", "空房招租中"), IF(COUNTIFS(N:N, N36, O:O, "<>空房招租中", E:E, "*分層*") > 0, "入住中", IF(COUNTIFS(N:N, N36, O:O, "空房招租中", E:E, "*分層*") > 0, "分層優先(隱藏)", "空房招租中") ) ) ) ) -> 入住中 | J36: 獨立陽台大採光雅房 | K36: https://youtube.com/shorts/w4m3C_SQfU0?si=AG4_Bc2RFth2LSdH | L36: =IF(AND(A36="", C36="", D36=""), "Z", "A") -> A | O36: =IF(AND(C36<>"", D36<>""), IF(COUNTIFS(sublease_contract!$C:$C, C36, sublease_contract!$D:$D, "*" & D36 & "*", sublease_contract!$G:$G, "<>已退租") = 0, "空房招租中", IF(COUNTIFS(sublease_contract!$C:$C, C36, sublease_contract!$D:$D, "*" & D36 & "*", sublease_contract!$G:$G, "<>已退租", sublease_contract!$N:$N, ">" & (TODAY()+20)) > 0, "入住中", IF(COUNTIFS(sublease_contract!$C:$C, C36, sublease_contract!$D:$D, "*" & D36 & "*", sublease_contract!$G:$G, "<>已退租", sublease_contract!$N:$N, ">=" & TODAY(), sublease_contract!$N:$N, "<=" & (TODAY()+20)) > 0, MINIFS(sublease_contract!$N:$N, sublease_contract!$C:$C, C36, sublease_contract!$D:$D, "*" & D36 & "*", sublease_contract!$G:$G, "<>已退租", sublease_contract!$N:$N, ">=" & TODAY(), sublease_contract!$N:$N, "<=" & (TODAY()+20)), "入住中"))), "") -> 入住中
A37: {=IFERROR( INDEX(big_rental_contract!A:A, MATCH(C37, big_rental_contract!F:F, 0)), "" )} -> A0007 | B37: RL00015 | C37: 士林和豐 | D37: C | E37: 分租雅房 | F37: 無 | G37: 11.92 | H37: 13000 | I37: =IF(O37<>"空房招租中", O37, IF(N37="", "空房招租中", IF(ISNUMBER(SEARCH("分層", E37)), IF(COUNTIFS(N:N, N37, O:O, "<>空房招租中") > 0, "入住中", "空房招租中"), IF(COUNTIFS(N:N, N37, O:O, "<>空房招租中", E:E, "*分層*") > 0, "入住中", IF(COUNTIFS(N:N, N37, O:O, "空房招租中", E:E, "*分層*") > 0, "分層優先(隱藏)", "空房招租中") ) ) ) ) -> 入住中 | J37: 方正全實心牆雅房 | K37: https://youtube.com/shorts/f59bfvV6lkw?si=X-Lx2UbnA76uz6Ac | L37: =IF(AND(A37="", C37="", D37=""), "Z", "A") -> A | O37: =IF(AND(C37<>"", D37<>""), IF(COUNTIFS(sublease_contract!$C:$C, C37, sublease_contract!$D:$D, "*" & D37 & "*", sublease_contract!$G:$G, "<>已退租") = 0, "空房招租中", IF(COUNTIFS(sublease_contract!$C:$C, C37, sublease_contract!$D:$D, "*" & D37 & "*", sublease_contract!$G:$G, "<>已退租", sublease_contract!$N:$N, ">" & (TODAY()+20)) > 0, "入住中", IF(COUNTIFS(sublease_contract!$C:$C, C37, sublease_contract!$D:$D, "*" & D37 & "*", sublease_contract!$G:$G, "<>已退租", sublease_contract!$N:$N, ">=" & TODAY(), sublease_contract!$N:$N, "<=" & (TODAY()+20)) > 0, MINIFS(sublease_contract!$N:$N, sublease_contract!$C:$C, C37, sublease_contract!$D:$D, "*" & D37 & "*", sublease_contract!$G:$G, "<>已退租", sublease_contract!$N:$N, ">=" & TODAY(), sublease_contract!$N:$N, "<=" & (TODAY()+20)), "入住中"))), "") -> 入住中
A38: {=IFERROR( INDEX(big_rental_contract!A:A, MATCH(C38, big_rental_contract!F:F, 0)), "" )} -> A0007 | B38: RL00016 | C38: 士林和豐 | D38: D | E38: 分租雅房 | F38: 無 | G38: 10.91 | H38: 12500 | I38: =IF(O38<>"空房招租中", O38, IF(N38="", "空房招租中", IF(ISNUMBER(SEARCH("分層", E38)), IF(COUNTIFS(N:N, N38, O:O, "<>空房招租中") > 0, "入住中", "空房招租中"), IF(COUNTIFS(N:N, N38, O:O, "<>空房招租中", E:E, "*分層*") > 0, "入住中", IF(COUNTIFS(N:N, N38, O:O, "空房招租中", E:E, "*分層*") > 0, "分層優先(隱藏)", "空房招租中") ) ) ) ) -> 入住中 | L38: =IF(AND(A38="", C38="", D38=""), "Z", "A") -> A | O38: =IF(AND(C38<>"", D38<>""), IF(COUNTIFS(sublease_contract!$C:$C, C38, sublease_contract!$D:$D, "*" & D38 & "*", sublease_contract!$G:$G, "<>已退租") = 0, "空房招租中", IF(COUNTIFS(sublease_contract!$C:$C, C38, sublease_contract!$D:$D, "*" & D38 & "*", sublease_contract!$G:$G, "<>已退租", sublease_contract!$N:$N, ">" & (TODAY()+20)) > 0, "入住中", IF(COUNTIFS(sublease_contract!$C:$C, C38, sublease_contract!$D:$D, "*" & D38 & "*", sublease_contract!$G:$G, "<>已退租", sublease_contract!$N:$N, ">=" & TODAY(), sublease_contract!$N:$N, "<=" & (TODAY()+20)) > 0, MINIFS(sublease_contract!$N:$N, sublease_contract!$C:$C, C38, sublease_contract!$D:$D, "*" & D38 & "*", sublease_contract!$G:$G, "<>已退租", sublease_contract!$N:$N, ">=" & TODAY(), sublease_contract!$N:$N, "<=" & (TODAY()+20)), "入住中"))), "") -> 入住中
A39: {=IFERROR( INDEX(big_rental_contract!A:A, MATCH(C39, big_rental_contract!F:F, 0)), "" )} -> A0008 | B39: RL00040 | C39: 南港站挑高宅 | D39: A | E39: 分租雅房 | F39: 無 | G39: 8.48 | H39: 13000 | I39: =IF(O39<>"空房招租中", O39, IF(N39="", "空房招租中", IF(ISNUMBER(SEARCH("分層", E39)), IF(COUNTIFS(N:N, N39, O:O, "<>空房招租中") > 0, "入住中", "空房招租中"), IF(COUNTIFS(N:N, N39, O:O, "<>空房招租中", E:E, "*分層*") > 0, "入住中", IF(COUNTIFS(N:N, N39, O:O, "空房招租中", E:E, "*分層*") > 0, "分層優先(隱藏)", "空房招租中") ) ) ) ) -> 入住中 | L39: =IF(AND(A39="", C39="", D39=""), "Z", "A") -> A | O39: =IF(AND(C39<>"", D39<>""), IF(COUNTIFS(sublease_contract!$C:$C, C39, sublease_contract!$D:$D, "*" & D39 & "*", sublease_contract!$G:$G, "<>已退租") = 0, "空房招租中", IF(COUNTIFS(sublease_contract!$C:$C, C39, sublease_contract!$D:$D, "*" & D39 & "*", sublease_contract!$G:$G, "<>已退租", sublease_contract!$N:$N, ">" & (TODAY()+20)) > 0, "入住中", IF(COUNTIFS(sublease_contract!$C:$C, C39, sublease_contract!$D:$D, "*" & D39 & "*", sublease_contract!$G:$G, "<>已退租", sublease_contract!$N:$N, ">=" & TODAY(), sublease_contract!$N:$N, "<=" & (TODAY()+20)) > 0, MINIFS(sublease_contract!$N:$N, sublease_contract!$C:$C, C39, sublease_contract!$D:$D, "*" & D39 & "*", sublease_contract!$G:$G, "<>已退租", sublease_contract!$N:$N, ">=" & TODAY(), sublease_contract!$N:$N, "<=" & (TODAY()+20)), "入住中"))), "") -> 入住中
A40: {=IFERROR( INDEX(big_rental_contract!A:A, MATCH(C40, big_rental_contract!F:F, 0)), "" )} -> A0008 | B40: RL00041 | C40: 南港站挑高宅 | D40: B | E40: 分租雅房 | F40: 無 | G40: 7.76 | H40: 11500 | I40: =IF(O40<>"空房招租中", O40, IF(N40="", "空房招租中", IF(ISNUMBER(SEARCH("分層", E40)), IF(COUNTIFS(N:N, N40, O:O, "<>空房招租中") > 0, "入住中", "空房招租中"), IF(COUNTIFS(N:N, N40, O:O, "<>空房招租中", E:E, "*分層*") > 0, "入住中", IF(COUNTIFS(N:N, N40, O:O, "空房招租中", E:E, "*分層*") > 0, "分層優先(隱藏)", "空房招租中") ) ) ) ) -> 入住中 | K40: https://youtu.be/a5mQVdGrbrU | L40: =IF(AND(A40="", C40="", D40=""), "Z", "A") -> A | O40: =IF(AND(C40<>"", D40<>""), IF(COUNTIFS(sublease_contract!$C:$C, C40, sublease_contract!$D:$D, "*" & D40 & "*", sublease_contract!$G:$G, "<>已退租") = 0, "空房招租中", IF(COUNTIFS(sublease_contract!$C:$C, C40, sublease_contract!$D:$D, "*" & D40 & "*", sublease_contract!$G:$G, "<>已退租", sublease_contract!$N:$N, ">" & (TODAY()+20)) > 0, "入住中", IF(COUNTIFS(sublease_contract!$C:$C, C40, sublease_contract!$D:$D, "*" & D40 & "*", sublease_contract!$G:$G, "<>已退租", sublease_contract!$N:$N, ">=" & TODAY(), sublease_contract!$N:$N, "<=" & (TODAY()+20)) > 0, MINIFS(sublease_contract!$N:$N, sublease_contract!$C:$C, C40, sublease_contract!$D:$D, "*" & D40 & "*", sublease_contract!$G:$G, "<>已退租", sublease_contract!$N:$N, ">=" & TODAY(), sublease_contract!$N:$N, "<=" & (TODAY()+20)), "入住中"))), "") -> 入住中
A41: {=IFERROR( INDEX(big_rental_contract!A:A, MATCH(C41, big_rental_contract!F:F, 0)), "" )} -> A0008 | B41: RL00042 | C41: 南港站挑高宅 | D41: C | E41: 分租套房 | F41: 無 | G41: 12.1 | H41: 15800 | I41: =IF(O41<>"空房招租中", O41, IF(N41="", "空房招租中", IF(ISNUMBER(SEARCH("分層", E41)), IF(COUNTIFS(N:N, N41, O:O, "<>空房招租中") > 0, "入住中", "空房招租中"), IF(COUNTIFS(N:N, N41, O:O, "<>空房招租中", E:E, "*分層*") > 0, "入住中", IF(COUNTIFS(N:N, N41, O:O, "空房招租中", E:E, "*分層*") > 0, "分層優先(隱藏)", "空房招租中") ) ) ) ) -> 入住中 | K41: https://youtu.be/uyYhNAPko2U | L41: =IF(AND(A41="", C41="", D41=""), "Z", "A") -> A | O41: =IF(AND(C41<>"", D41<>""), IF(COUNTIFS(sublease_contract!$C:$C, C41, sublease_contract!$D:$D, "*" & D41 & "*", sublease_contract!$G:$G, "<>已退租") = 0, "空房招租中", IF(COUNTIFS(sublease_contract!$C:$C, C41, sublease_contract!$D:$D, "*" & D41 & "*", sublease_contract!$G:$G, "<>已退租", sublease_contract!$N:$N, ">" & (TODAY()+20)) > 0, "入住中", IF(COUNTIFS(sublease_contract!$C:$C, C41, sublease_contract!$D:$D, "*" & D41 & "*", sublease_contract!$G:$G, "<>已退租", sublease_contract!$N:$N, ">=" & TODAY(), sublease_contract!$N:$N, "<=" & (TODAY()+20)) > 0, MINIFS(sublease_contract!$N:$N, sublease_contract!$C:$C, C41, sublease_contract!$D:$D, "*" & D41 & "*", sublease_contract!$G:$G, "<>已退租", sublease_contract!$N:$N, ">=" & TODAY(), sublease_contract!$N:$N, "<=" & (TODAY()+20)), "入住中"))), "") -> 入住中
A42: {=IFERROR( INDEX(big_rental_contract!A:A, MATCH(C42, big_rental_contract!F:F, 0)), "" )} -> A0008 | B42: RL00043 | C42: 南港站挑高宅 | D42: D | E42: 分租雅房 | F42: 無 | G42: 10.91 | H42: 14500 | I42: =IF(O42<>"空房招租中", O42, IF(N42="", "空房招租中", IF(ISNUMBER(SEARCH("分層", E42)), IF(COUNTIFS(N:N, N42, O:O, "<>空房招租中") > 0, "入住中", "空房招租中"), IF(COUNTIFS(N:N, N42, O:O, "<>空房招租中", E:E, "*分層*") > 0, "入住中", IF(COUNTIFS(N:N, N42, O:O, "空房招租中", E:E, "*分層*") > 0, "分層優先(隱藏)", "空房招租中") ) ) ) ) -> 入住中 | L42: =IF(AND(A42="", C42="", D42=""), "Z", "A") -> A | O42: =IF(AND(C42<>"", D42<>""), IF(COUNTIFS(sublease_contract!$C:$C, C42, sublease_contract!$D:$D, "*" & D42 & "*", sublease_contract!$G:$G, "<>已退租") = 0, "空房招租中", IF(COUNTIFS(sublease_contract!$C:$C, C42, sublease_contract!$D:$D, "*" & D42 & "*", sublease_contract!$G:$G, "<>已退租", sublease_contract!$N:$N, ">" & (TODAY()+20)) > 0, "入住中", IF(COUNTIFS(sublease_contract!$C:$C, C42, sublease_contract!$D:$D, "*" & D42 & "*", sublease_contract!$G:$G, "<>已退租", sublease_contract!$N:$N, ">=" & TODAY(), sublease_contract!$N:$N, "<=" & (TODAY()+20)) > 0, MINIFS(sublease_contract!$N:$N, sublease_contract!$C:$C, C42, sublease_contract!$D:$D, "*" & D42 & "*", sublease_contract!$G:$G, "<>已退租", sublease_contract!$N:$N, ">=" & TODAY(), sublease_contract!$N:$N, "<=" & (TODAY()+20)), "入住中"))), "") -> 入住中
A43: {=IFERROR( INDEX(big_rental_contract!A:A, MATCH(C43, big_rental_contract!F:F, 0)), "" )} -> A0008 | B43: RL00044 | C43: 南港站挑高宅 | D43: E | E43: 分租雅房 | F43: 無 | G43: 5.18 | H43: 12800 | I43: =IF(O43<>"空房招租中", O43, IF(N43="", "空房招租中", IF(ISNUMBER(SEARCH("分層", E43)), IF(COUNTIFS(N:N, N43, O:O, "<>空房招租中") > 0, "入住中", "空房招租中"), IF(COUNTIFS(N:N, N43, O:O, "<>空房招租中", E:E, "*分層*") > 0, "入住中", IF(COUNTIFS(N:N, N43, O:O, "空房招租中", E:E, "*分層*") > 0, "分層優先(隱藏)", "空房招租中") ) ) ) ) -> 入住中 | K43: https://youtube.com/shorts/1n4Pq5wyeHU?si=lUmenjBixSrfLuTc | L43: =IF(AND(A43="", C43="", D43=""), "Z", "A") -> A | O43: =IF(AND(C43<>"", D43<>""), IF(COUNTIFS(sublease_contract!$C:$C, C43, sublease_contract!$D:$D, "*" & D43 & "*", sublease_contract!$G:$G, "<>已退租") = 0, "空房招租中", IF(COUNTIFS(sublease_contract!$C:$C, C43, sublease_contract!$D:$D, "*" & D43 & "*", sublease_contract!$G:$G, "<>已退租", sublease_contract!$N:$N, ">" & (TODAY()+20)) > 0, "入住中", IF(COUNTIFS(sublease_contract!$C:$C, C43, sublease_contract!$D:$D, "*" & D43 & "*", sublease_contract!$G:$G, "<>已退租", sublease_contract!$N:$N, ">=" & TODAY(), sublease_contract!$N:$N, "<=" & (TODAY()+20)) > 0, MINIFS(sublease_contract!$N:$N, sublease_contract!$C:$C, C43, sublease_contract!$D:$D, "*" & D43 & "*", sublease_contract!$G:$G, "<>已退租", sublease_contract!$N:$N, ">=" & TODAY(), sublease_contract!$N:$N, "<=" & (TODAY()+20)), "入住中"))), "") -> 入住中
A44: {=IFERROR( INDEX(big_rental_contract!A:A, MATCH(C44, big_rental_contract!F:F, 0)), "" )} -> A0009 | B44: RL00039 | C44: 市府爺爺家 | D44: A | E44: 分租套房 | F44: 無 | G44: 22.11 | H44: 22000 | I44: =IF(O44<>"空房招租中", O44, IF(N44="", "空房招租中", IF(ISNUMBER(SEARCH("分層", E44)), IF(COUNTIFS(N:N, N44, O:O, "<>空房招租中") > 0, "入住中", "空房招租中"), IF(COUNTIFS(N:N, N44, O:O, "<>空房招租中", E:E, "*分層*") > 0, "入住中", IF(COUNTIFS(N:N, N44, O:O, "空房招租中", E:E, "*分層*") > 0, "分層優先(隱藏)", "空房招租中") ) ) ) ) -> 入住中 | K44: https://youtu.be/Ap6HqUFDxZk | L44: =IF(AND(A44="", C44="", D44=""), "Z", "A") -> A | O44: =IF(AND(C44<>"", D44<>""), IF(COUNTIFS(sublease_contract!$C:$C, C44, sublease_contract!$D:$D, "*" & D44 & "*", sublease_contract!$G:$G, "<>已退租") = 0, "空房招租中", IF(COUNTIFS(sublease_contract!$C:$C, C44, sublease_contract!$D:$D, "*" & D44 & "*", sublease_contract!$G:$G, "<>已退租", sublease_contract!$N:$N, ">" & (TODAY()+20)) > 0, "入住中", IF(COUNTIFS(sublease_contract!$C:$C, C44, sublease_contract!$D:$D, "*" & D44 & "*", sublease_contract!$G:$G, "<>已退租", sublease_contract!$N:$N, ">=" & TODAY(), sublease_contract!$N:$N, "<=" & (TODAY()+20)) > 0, MINIFS(sublease_contract!$N:$N, sublease_contract!$C:$C, C44, sublease_contract!$D:$D, "*" & D44 & "*", sublease_contract!$G:$G, "<>已退租", sublease_contract!$N:$N, ">=" & TODAY(), sublease_contract!$N:$N, "<=" & (TODAY()+20)), "入住中"))), "") -> 入住中
A45: {=IFERROR( INDEX(big_rental_contract!A:A, MATCH(C45, big_rental_contract!F:F, 0)), "" )} -> A0010 | B45: RL00045 | C45: 金龍帽子先生 | D45: A | E45: 分租套房 | F45: 無 | G45: 17.72 | H45: 17200 | I45: =IF(O45<>"空房招租中", O45, IF(N45="", "空房招租中", IF(ISNUMBER(SEARCH("分層", E45)), IF(COUNTIFS(N:N, N45, O:O, "<>空房招租中") > 0, "入住中", "空房招租中"), IF(COUNTIFS(N:N, N45, O:O, "<>空房招租中", E:E, "*分層*") > 0, "入住中", IF(COUNTIFS(N:N, N45, O:O, "空房招租中", E:E, "*分層*") > 0, "分層優先(隱藏)", "空房招租中") ) ) ) ) -> 入住中 | J45: 獨立衣帽間洗衣機大套房 | K45: https://youtu.be/Nhw-XDtzIX0 | L45: =IF(AND(A45="", C45="", D45=""), "Z", "A") -> A | O45: =IF(AND(C45<>"", D45<>""), IF(COUNTIFS(sublease_contract!$C:$C, C45, sublease_contract!$D:$D, "*" & D45 & "*", sublease_contract!$G:$G, "<>已退租") = 0, "空房招租中", IF(COUNTIFS(sublease_contract!$C:$C, C45, sublease_contract!$D:$D, "*" & D45 & "*", sublease_contract!$G:$G, "<>已退租", sublease_contract!$N:$N, ">" & (TODAY()+20)) > 0, "入住中", IF(COUNTIFS(sublease_contract!$C:$C, C45, sublease_contract!$D:$D, "*" & D45 & "*", sublease_contract!$G:$G, "<>已退租", sublease_contract!$N:$N, ">=" & TODAY(), sublease_contract!$N:$N, "<=" & (TODAY()+20)) > 0, MINIFS(sublease_contract!$N:$N, sublease_contract!$C:$C, C45, sublease_contract!$D:$D, "*" & D45 & "*", sublease_contract!$G:$G, "<>已退租", sublease_contract!$N:$N, ">=" & TODAY(), sublease_contract!$N:$N, "<=" & (TODAY()+20)), "入住中"))), "") -> 入住中
A46: {=IFERROR( INDEX(big_rental_contract!A:A, MATCH(C46, big_rental_contract!F:F, 0)), "" )} -> A0010 | B46: RL00046 | C46: 金龍帽子先生 | D46: B | E46: 分租雅房 | F46: 無 | G46: 8.61 | H46: 12700 | I46: =IF(O46<>"空房招租中", O46, IF(N46="", "空房招租中", IF(ISNUMBER(SEARCH("分層", E46)), IF(COUNTIFS(N:N, N46, O:O, "<>空房招租中") > 0, "入住中", "空房招租中"), IF(COUNTIFS(N:N, N46, O:O, "<>空房招租中", E:E, "*分層*") > 0, "入住中", IF(COUNTIFS(N:N, N46, O:O, "空房招租中", E:E, "*分層*") > 0, "分層優先(隱藏)", "空房招租中") ) ) ) ) -> 入住中 | J46: 大採光獨立陽台雅房 | K46: https://youtu.be/R9pHDkA1O5E | L46: =IF(AND(A46="", C46="", D46=""), "Z", "A") -> A | O46: =IF(AND(C46<>"", D46<>""), IF(COUNTIFS(sublease_contract!$C:$C, C46, sublease_contract!$D:$D, "*" & D46 & "*", sublease_contract!$G:$G, "<>已退租") = 0, "空房招租中", IF(COUNTIFS(sublease_contract!$C:$C, C46, sublease_contract!$D:$D, "*" & D46 & "*", sublease_contract!$G:$G, "<>已退租", sublease_contract!$N:$N, ">" & (TODAY()+20)) > 0, "入住中", IF(COUNTIFS(sublease_contract!$C:$C, C46, sublease_contract!$D:$D, "*" & D46 & "*", sublease_contract!$G:$G, "<>已退租", sublease_contract!$N:$N, ">=" & TODAY(), sublease_contract!$N:$N, "<=" & (TODAY()+20)) > 0, MINIFS(sublease_contract!$N:$N, sublease_contract!$C:$C, C46, sublease_contract!$D:$D, "*" & D46 & "*", sublease_contract!$G:$G, "<>已退租", sublease_contract!$N:$N, ">=" & TODAY(), sublease_contract!$N:$N, "<=" & (TODAY()+20)), "入住中"))), "") -> 入住中
A47: {=IFERROR( INDEX(big_rental_contract!A:A, MATCH(C47, big_rental_contract!F:F, 0)), "" )} -> A0010 | B47: RL00047 | C47: 金龍帽子先生 | D47: C | E47: 分租雅房 | F47: 無 | G47: 11.48 | H47: 14000 | I47: =IF(O47<>"空房招租中", O47, IF(N47="", "空房招租中", IF(ISNUMBER(SEARCH("分層", E47)), IF(COUNTIFS(N:N, N47, O:O, "<>空房招租中") > 0, "入住中", "空房招租中"), IF(COUNTIFS(N:N, N47, O:O, "<>空房招租中", E:E, "*分層*") > 0, "入住中", IF(COUNTIFS(N:N, N47, O:O, "空房招租中", E:E, "*分層*") > 0, "分層優先(隱藏)", "空房招租中") ) ) ) ) -> 入住中 | J47: 好多好多衣櫃 中雅房 | K47: https://www.youtube.com/shorts/vR6bJZjIVYI | L47: =IF(AND(A47="", C47="", D47=""), "Z", "A") -> A | O47: =IF(AND(C47<>"", D47<>""), IF(COUNTIFS(sublease_contract!$C:$C, C47, sublease_contract!$D:$D, "*" & D47 & "*", sublease_contract!$G:$G, "<>已退租") = 0, "空房招租中", IF(COUNTIFS(sublease_contract!$C:$C, C47, sublease_contract!$D:$D, "*" & D47 & "*", sublease_contract!$G:$G, "<>已退租", sublease_contract!$N:$N, ">" & (TODAY()+20)) > 0, "入住中", IF(COUNTIFS(sublease_contract!$C:$C, C47, sublease_contract!$D:$D, "*" & D47 & "*", sublease_contract!$G:$G, "<>已退租", sublease_contract!$N:$N, ">=" & TODAY(), sublease_contract!$N:$N, "<=" & (TODAY()+20)) > 0, MINIFS(sublease_contract!$N:$N, sublease_contract!$C:$C, C47, sublease_contract!$D:$D, "*" & D47 & "*", sublease_contract!$G:$G, "<>已退租", sublease_contract!$N:$N, ">=" & TODAY(), sublease_contract!$N:$N, "<=" & (TODAY()+20)), "入住中"))), "") -> 入住中
A48: {=IFERROR( INDEX(big_rental_contract!A:A, MATCH(C48, big_rental_contract!F:F, 0)), "" )} -> A0010 | B48: RL00048 | C48: 金龍帽子先生 | D48: D | E48: 分租雅房 | F48: 無 | G48: 12.14 | H48: 14500 | I48: =IF(O48<>"空房招租中", O48, IF(N48="", "空房招租中", IF(ISNUMBER(SEARCH("分層", E48)), IF(COUNTIFS(N:N, N48, O:O, "<>空房招租中") > 0, "入住中", "空房招租中"), IF(COUNTIFS(N:N, N48, O:O, "<>空房招租中", E:E, "*分層*") > 0, "入住中", IF(COUNTIFS(N:N, N48, O:O, "空房招租中", E:E, "*分層*") > 0, "分層優先(隱藏)", "空房招租中") ) ) ) ) -> 入住中 | J48: 大採光美景大雅房 | K48: https://youtu.be/fwAwpXaMEj4 | L48: =IF(AND(A48="", C48="", D48=""), "Z", "A") -> A | O48: =IF(AND(C48<>"", D48<>""), IF(COUNTIFS(sublease_contract!$C:$C, C48, sublease_contract!$D:$D, "*" & D48 & "*", sublease_contract!$G:$G, "<>已退租") = 0, "空房招租中", IF(COUNTIFS(sublease_contract!$C:$C, C48, sublease_contract!$D:$D, "*" & D48 & "*", sublease_contract!$G:$G, "<>已退租", sublease_contract!$N:$N, ">" & (TODAY()+20)) > 0, "入住中", IF(COUNTIFS(sublease_contract!$C:$C, C48, sublease_contract!$D:$D, "*" & D48 & "*", sublease_contract!$G:$G, "<>已退租", sublease_contract!$N:$N, ">=" & TODAY(), sublease_contract!$N:$N, "<=" & (TODAY()+20)) > 0, MINIFS(sublease_contract!$N:$N, sublease_contract!$C:$C, C48, sublease_contract!$D:$D, "*" & D48 & "*", sublease_contract!$G:$G, "<>已退租", sublease_contract!$N:$N, ">=" & TODAY(), sublease_contract!$N:$N, "<=" & (TODAY()+20)), "入住中"))), "") -> 入住中
A49: {=IFERROR( INDEX(big_rental_contract!A:A, MATCH(C49, big_rental_contract!F:F, 0)), "" )} -> A0011 | B49: RL00049 | C49: 景安2分鐘 | D49: A | E49: 分租雅房 | F49: 無 | G49: 20.21 | H49: 13800 | I49: =IF(O49<>"空房招租中", O49, IF(N49="", "空房招租中", IF(ISNUMBER(SEARCH("分層", E49)), IF(COUNTIFS(N:N, N49, O:O, "<>空房招租中") > 0, "入住中", "空房招租中"), IF(COUNTIFS(N:N, N49, O:O, "<>空房招租中", E:E, "*分層*") > 0, "入住中", IF(COUNTIFS(N:N, N49, O:O, "空房招租中", E:E, "*分層*") > 0, "分層優先(隱藏)", "空房招租中") ) ) ) ) -> 入住中 | J49: 獨立陽台洗衣機超大雅房 | K49: https://youtu.be/jXlShe5u2WU | L49: =IF(AND(A49="", C49="", D49=""), "Z", "A") -> A | O49: =IF(AND(C49<>"", D49<>""), IF(COUNTIFS(sublease_contract!$C:$C, C49, sublease_contract!$D:$D, "*" & D49 & "*", sublease_contract!$G:$G, "<>已退租") = 0, "空房招租中", IF(COUNTIFS(sublease_contract!$C:$C, C49, sublease_contract!$D:$D, "*" & D49 & "*", sublease_contract!$G:$G, "<>已退租", sublease_contract!$N:$N, ">" & (TODAY()+20)) > 0, "入住中", IF(COUNTIFS(sublease_contract!$C:$C, C49, sublease_contract!$D:$D, "*" & D49 & "*", sublease_contract!$G:$G, "<>已退租", sublease_contract!$N:$N, ">=" & TODAY(), sublease_contract!$N:$N, "<=" & (TODAY()+20)) > 0, MINIFS(sublease_contract!$N:$N, sublease_contract!$C:$C, C49, sublease_contract!$D:$D, "*" & D49 & "*", sublease_contract!$G:$G, "<>已退租", sublease_contract!$N:$N, ">=" & TODAY(), sublease_contract!$N:$N, "<=" & (TODAY()+20)), "入住中"))), "") -> 入住中
A50: {=IFERROR( INDEX(big_rental_contract!A:A, MATCH(C50, big_rental_contract!F:F, 0)), "" )} -> A0011 | B50: RL00050 | C50: 景安2分鐘 | D50: B | E50: 分租套房 | F50: 無 | G50: 20.53 | H50: 18800 | I50: =IF(O50<>"空房招租中", O50, IF(N50="", "空房招租中", IF(ISNUMBER(SEARCH("分層", E50)), IF(COUNTIFS(N:N, N50, O:O, "<>空房招租中") > 0, "入住中", "空房招租中"), IF(COUNTIFS(N:N, N50, O:O, "<>空房招租中", E:E, "*分層*") > 0, "入住中", IF(COUNTIFS(N:N, N50, O:O, "空房招租中", E:E, "*分層*") > 0, "分層優先(隱藏)", "空房招租中") ) ) ) ) -> 入住中 | J50: 獨立衛浴超大套房 | L50: =IF(AND(A50="", C50="", D50=""), "Z", "A") -> A | O50: =IF(AND(C50<>"", D50<>""), IF(COUNTIFS(sublease_contract!$C:$C, C50, sublease_contract!$D:$D, "*" & D50 & "*", sublease_contract!$G:$G, "<>已退租") = 0, "空房招租中", IF(COUNTIFS(sublease_contract!$C:$C, C50, sublease_contract!$D:$D, "*" & D50 & "*", sublease_contract!$G:$G, "<>已退租", sublease_contract!$N:$N, ">" & (TODAY()+20)) > 0, "入住中", IF(COUNTIFS(sublease_contract!$C:$C, C50, sublease_contract!$D:$D, "*" & D50 & "*", sublease_contract!$G:$G, "<>已退租", sublease_contract!$N:$N, ">=" & TODAY(), sublease_contract!$N:$N, "<=" & (TODAY()+20)) > 0, MINIFS(sublease_contract!$N:$N, sublease_contract!$C:$C, C50, sublease_contract!$D:$D, "*" & D50 & "*", sublease_contract!$G:$G, "<>已退租", sublease_contract!$N:$N, ">=" & TODAY(), sublease_contract!$N:$N, "<=" & (TODAY()+20)), "入住中"))), "") -> 入住中
A51: {=IFERROR( INDEX(big_rental_contract!A:A, MATCH(C51, big_rental_contract!F:F, 0)), "" )} -> A0011 | B51: RL00051 | C51: 景安2分鐘 | D51: C | E51: 分租雅房 | F51: 無 | G51: 10.31 | H51: 12500 | I51: =IF(O51<>"空房招租中", O51, IF(N51="", "空房招租中", IF(ISNUMBER(SEARCH("分層", E51)), IF(COUNTIFS(N:N, N51, O:O, "<>空房招租中") > 0, "入住中", "空房招租中"), IF(COUNTIFS(N:N, N51, O:O, "<>空房招租中", E:E, "*分層*") > 0, "入住中", IF(COUNTIFS(N:N, N51, O:O, "空房招租中", E:E, "*分層*") > 0, "分層優先(隱藏)", "空房招租中") ) ) ) ) -> 入住中 | J51: 採光實牆大雅房 | K51: https://youtu.be/8dskuxjWPGQ | L51: =IF(AND(A51="", C51="", D51=""), "Z", "A") -> A | O51: =IF(AND(C51<>"", D51<>""), IF(COUNTIFS(sublease_contract!$C:$C, C51, sublease_contract!$D:$D, "*" & D51 & "*", sublease_contract!$G:$G, "<>已退租") = 0, "空房招租中", IF(COUNTIFS(sublease_contract!$C:$C, C51, sublease_contract!$D:$D, "*" & D51 & "*", sublease_contract!$G:$G, "<>已退租", sublease_contract!$N:$N, ">" & (TODAY()+20)) > 0, "入住中", IF(COUNTIFS(sublease_contract!$C:$C, C51, sublease_contract!$D:$D, "*" & D51 & "*", sublease_contract!$G:$G, "<>已退租", sublease_contract!$N:$N, ">=" & TODAY(), sublease_contract!$N:$N, "<=" & (TODAY()+20)) > 0, MINIFS(sublease_contract!$N:$N, sublease_contract!$C:$C, C51, sublease_contract!$D:$D, "*" & D51 & "*", sublease_contract!$G:$G, "<>已退租", sublease_contract!$N:$N, ">=" & TODAY(), sublease_contract!$N:$N, "<=" & (TODAY()+20)), "入住中"))), "") -> 入住中
A52: {=IFERROR( INDEX(big_rental_contract!A:A, MATCH(C52, big_rental_contract!F:F, 0)), "" )} -> A0011 | B52: RL00052 | C52: 景安2分鐘 | D52: D | E52: 分租雅房 | F52: 無 | G52: 6 | H52: 9600 | I52: =IF(O52<>"空房招租中", O52, IF(N52="", "空房招租中", IF(ISNUMBER(SEARCH("分層", E52)), IF(COUNTIFS(N:N, N52, O:O, "<>空房招租中") > 0, "入住中", "空房招租中"), IF(COUNTIFS(N:N, N52, O:O, "<>空房招租中", E:E, "*分層*") > 0, "入住中", IF(COUNTIFS(N:N, N52, O:O, "空房招租中", E:E, "*分層*") > 0, "分層優先(隱藏)", "空房招租中") ) ) ) ) -> 入住中 | J52: 採光實牆小雅房 | K52: https://youtu.be/2eWqR1-x7ZY | L52: =IF(AND(A52="", C52="", D52=""), "Z", "A") -> A | O52: =IF(AND(C52<>"", D52<>""), IF(COUNTIFS(sublease_contract!$C:$C, C52, sublease_contract!$D:$D, "*" & D52 & "*", sublease_contract!$G:$G, "<>已退租") = 0, "空房招租中", IF(COUNTIFS(sublease_contract!$C:$C, C52, sublease_contract!$D:$D, "*" & D52 & "*", sublease_contract!$G:$G, "<>已退租", sublease_contract!$N:$N, ">" & (TODAY()+20)) > 0, "入住中", IF(COUNTIFS(sublease_contract!$C:$C, C52, sublease_contract!$D:$D, "*" & D52 & "*", sublease_contract!$G:$G, "<>已退租", sublease_contract!$N:$N, ">=" & TODAY(), sublease_contract!$N:$N, "<=" & (TODAY()+20)) > 0, MINIFS(sublease_contract!$N:$N, sublease_contract!$C:$C, C52, sublease_contract!$D:$D, "*" & D52 & "*", sublease_contract!$G:$G, "<>已退租", sublease_contract!$N:$N, ">=" & TODAY(), sublease_contract!$N:$N, "<=" & (TODAY()+20)), "入住中"))), "") -> 入住中
A53: {=IFERROR( INDEX(big_rental_contract!A:A, MATCH(C53, big_rental_contract!F:F, 0)), "" )} -> A0011 | B53: RL00053 | C53: 景安2分鐘 | D53: E | E53: 分租雅房 | F53: 無 | G53: 8.73 | H53: 11300 | I53: =IF(O53<>"空房招租中", O53, IF(N53="", "空房招租中", IF(ISNUMBER(SEARCH("分層", E53)), IF(COUNTIFS(N:N, N53, O:O, "<>空房招租中") > 0, "入住中", "空房招租中"), IF(COUNTIFS(N:N, N53, O:O, "<>空房招租中", E:E, "*分層*") > 0, "入住中", IF(COUNTIFS(N:N, N53, O:O, "空房招租中", E:E, "*分層*") > 0, "分層優先(隱藏)", "空房招租中") ) ) ) ) -> 入住中 | J53: 採光實牆中雅房 | K53: https://youtu.be/aKv8_cRJPqE | L53: =IF(AND(A53="", C53="", D53=""), "Z", "A") -> A | O53: =IF(AND(C53<>"", D53<>""), IF(COUNTIFS(sublease_contract!$C:$C, C53, sublease_contract!$D:$D, "*" & D53 & "*", sublease_contract!$G:$G, "<>已退租") = 0, "空房招租中", IF(COUNTIFS(sublease_contract!$C:$C, C53, sublease_contract!$D:$D, "*" & D53 & "*", sublease_contract!$G:$G, "<>已退租", sublease_contract!$N:$N, ">" & (TODAY()+20)) > 0, "入住中", IF(COUNTIFS(sublease_contract!$C:$C, C53, sublease_contract!$D:$D, "*" & D53 & "*", sublease_contract!$G:$G, "<>已退租", sublease_contract!$N:$N, ">=" & TODAY(), sublease_contract!$N:$N, "<=" & (TODAY()+20)) > 0, MINIFS(sublease_contract!$N:$N, sublease_contract!$C:$C, C53, sublease_contract!$D:$D, "*" & D53 & "*", sublease_contract!$G:$G, "<>已退租", sublease_contract!$N:$N, ">=" & TODAY(), sublease_contract!$N:$N, "<=" & (TODAY()+20)), "入住中"))), "") -> 入住中
A54: {=IFERROR( INDEX(big_rental_contract!A:A, MATCH(C54, big_rental_contract!F:F, 0)), "" )} -> A0012 | B54: RL00054 | C54: 中山北娘家旁 | D54: A | E54: 分租雅房 | F54: 無 | G54: 11.29 | H54: 12800 | I54: =IF(O54<>"空房招租中", O54, IF(N54="", "空房招租中", IF(ISNUMBER(SEARCH("分層", E54)), IF(COUNTIFS(N:N, N54, O:O, "<>空房招租中") > 0, "入住中", "空房招租中"), IF(COUNTIFS(N:N, N54, O:O, "<>空房招租中", E:E, "*分層*") > 0, "入住中", IF(COUNTIFS(N:N, N54, O:O, "空房招租中", E:E, "*分層*") > 0, "分層優先(隱藏)", "空房招租中") ) ) ) ) -> 46081 | J54: 方正橙黃大衣櫃雅房 | K54: https://youtu.be/hhOdPDFVPQk?si=9daJZkMcRTyLKjws | L54: =IF(AND(A54="", C54="", D54=""), "Z", "A") -> A | O54: =IF(AND(C54<>"", D54<>""), IF(COUNTIFS(sublease_contract!$C:$C, C54, sublease_contract!$D:$D, "*" & D54 & "*", sublease_contract!$G:$G, "<>已退租") = 0, "空房招租中", IF(COUNTIFS(sublease_contract!$C:$C, C54, sublease_contract!$D:$D, "*" & D54 & "*", sublease_contract!$G:$G, "<>已退租", sublease_contract!$N:$N, ">" & (TODAY()+20)) > 0, "入住中", IF(COUNTIFS(sublease_contract!$C:$C, C54, sublease_contract!$D:$D, "*" & D54 & "*", sublease_contract!$G:$G, "<>已退租", sublease_contract!$N:$N, ">=" & TODAY(), sublease_contract!$N:$N, "<=" & (TODAY()+20)) > 0, MINIFS(sublease_contract!$N:$N, sublease_contract!$C:$C, C54, sublease_contract!$D:$D, "*" & D54 & "*", sublease_contract!$G:$G, "<>已退租", sublease_contract!$N:$N, ">=" & TODAY(), sublease_contract!$N:$N, "<=" & (TODAY()+20)), "入住中"))), "") -> 46081
A55: {=IFERROR( INDEX(big_rental_contract!A:A, MATCH(C55, big_rental_contract!F:F, 0)), "" )} -> A0012 | B55: RL00055 | C55: 中山北娘家旁 | D55: B | E55: 分租雅房 | F55: 無 | G55: 11.96 | H55: 12800 | I55: =IF(O55<>"空房招租中", O55, IF(N55="", "空房招租中", IF(ISNUMBER(SEARCH("分層", E55)), IF(COUNTIFS(N:N, N55, O:O, "<>空房招租中") > 0, "入住中", "空房招租中"), IF(COUNTIFS(N:N, N55, O:O, "<>空房招租中", E:E, "*分層*") > 0, "入住中", IF(COUNTIFS(N:N, N55, O:O, "空房招租中", E:E, "*分層*") > 0, "分層優先(隱藏)", "空房招租中") ) ) ) ) -> 入住中 | J55: 方正卡其綠大衣櫃雅房 | K55: https://youtu.be/NA8RGArVaj4?si=LBCsYT5aB6UQjPRT | L55: =IF(AND(A55="", C55="", D55=""), "Z", "A") -> A | O55: =IF(AND(C55<>"", D55<>""), IF(COUNTIFS(sublease_contract!$C:$C, C55, sublease_contract!$D:$D, "*" & D55 & "*", sublease_contract!$G:$G, "<>已退租") = 0, "空房招租中", IF(COUNTIFS(sublease_contract!$C:$C, C55, sublease_contract!$D:$D, "*" & D55 & "*", sublease_contract!$G:$G, "<>已退租", sublease_contract!$N:$N, ">" & (TODAY()+20)) > 0, "入住中", IF(COUNTIFS(sublease_contract!$C:$C, C55, sublease_contract!$D:$D, "*" & D55 & "*", sublease_contract!$G:$G, "<>已退租", sublease_contract!$N:$N, ">=" & TODAY(), sublease_contract!$N:$N, "<=" & (TODAY()+20)) > 0, MINIFS(sublease_contract!$N:$N, sublease_contract!$C:$C, C55, sublease_contract!$D:$D, "*" & D55 & "*", sublease_contract!$G:$G, "<>已退租", sublease_contract!$N:$N, ">=" & TODAY(), sublease_contract!$N:$N, "<=" & (TODAY()+20)), "入住中"))), "") -> 入住中
A56: {=IFERROR( INDEX(big_rental_contract!A:A, MATCH(C56, big_rental_contract!F:F, 0)), "" )} -> A0012 | B56: RL00056 | C56: 中山北娘家旁 | D56: C | E56: 分租雅房 | F56: 無 | G56: 10.48 | H56: 14800 | I56: =IF(O56<>"空房招租中", O56, IF(N56="", "空房招租中", IF(ISNUMBER(SEARCH("分層", E56)), IF(COUNTIFS(N:N, N56, O:O, "<>空房招租中") > 0, "入住中", "空房招租中"), IF(COUNTIFS(N:N, N56, O:O, "<>空房招租中", E:E, "*分層*") > 0, "入住中", IF(COUNTIFS(N:N, N56, O:O, "空房招租中", E:E, "*分層*") > 0, "分層優先(隱藏)", "空房招租中") ) ) ) ) -> 入住中 | J56: 雙採光中雅房 | K56: https://youtu.be/hcnf0ZuEW7M?si=ZFugzpKZkqz-KvTx | L56: =IF(AND(A56="", C56="", D56=""), "Z", "A") -> A | O56: =IF(AND(C56<>"", D56<>""), IF(COUNTIFS(sublease_contract!$C:$C, C56, sublease_contract!$D:$D, "*" & D56 & "*", sublease_contract!$G:$G, "<>已退租") = 0, "空房招租中", IF(COUNTIFS(sublease_contract!$C:$C, C56, sublease_contract!$D:$D, "*" & D56 & "*", sublease_contract!$G:$G, "<>已退租", sublease_contract!$N:$N, ">" & (TODAY()+20)) > 0, "入住中", IF(COUNTIFS(sublease_contract!$C:$C, C56, sublease_contract!$D:$D, "*" & D56 & "*", sublease_contract!$G:$G, "<>已退租", sublease_contract!$N:$N, ">=" & TODAY(), sublease_contract!$N:$N, "<=" & (TODAY()+20)) > 0, MINIFS(sublease_contract!$N:$N, sublease_contract!$C:$C, C56, sublease_contract!$D:$D, "*" & D56 & "*", sublease_contract!$G:$G, "<>已退租", sublease_contract!$N:$N, ">=" & TODAY(), sublease_contract!$N:$N, "<=" & (TODAY()+20)), "入住中"))), "") -> 入住中
A57: {=IFERROR( INDEX(big_rental_contract!A:A, MATCH(C57, big_rental_contract!F:F, 0)), "" )} -> A0012 | B57: RL00057 | C57: 中山北娘家旁 | D57: D | E57: 分租雅房 | F57: 無 | G57: 8.69 | H57: 14500 | I57: =IF(O57<>"空房招租中", O57, IF(N57="", "空房招租中", IF(ISNUMBER(SEARCH("分層", E57)), IF(COUNTIFS(N:N, N57, O:O, "<>空房招租中") > 0, "入住中", "空房招租中"), IF(COUNTIFS(N:N, N57, O:O, "<>空房招租中", E:E, "*分層*") > 0, "入住中", IF(COUNTIFS(N:N, N57, O:O, "空房招租中", E:E, "*分層*") > 0, "分層優先(隱藏)", "空房招租中") ) ) ) ) -> 入住中 | J57: 樹景採光雅房 | K57: https://youtu.be/tV0Cz-yGN0o?si=iQT9CJYGeFdvXHAd | L57: =IF(AND(A57="", C57="", D57=""), "Z", "A") -> A | O57: =IF(AND(C57<>"", D57<>""), IF(COUNTIFS(sublease_contract!$C:$C, C57, sublease_contract!$D:$D, "*" & D57 & "*", sublease_contract!$G:$G, "<>已退租") = 0, "空房招租中", IF(COUNTIFS(sublease_contract!$C:$C, C57, sublease_contract!$D:$D, "*" & D57 & "*", sublease_contract!$G:$G, "<>已退租", sublease_contract!$N:$N, ">" & (TODAY()+20)) > 0, "入住中", IF(COUNTIFS(sublease_contract!$C:$C, C57, sublease_contract!$D:$D, "*" & D57 & "*", sublease_contract!$G:$G, "<>已退租", sublease_contract!$N:$N, ">=" & TODAY(), sublease_contract!$N:$N, "<=" & (TODAY()+20)) > 0, MINIFS(sublease_contract!$N:$N, sublease_contract!$C:$C, C57, sublease_contract!$D:$D, "*" & D57 & "*", sublease_contract!$G:$G, "<>已退租", sublease_contract!$N:$N, ">=" & TODAY(), sublease_contract!$N:$N, "<=" & (TODAY()+20)), "入住中"))), "") -> 入住中
A58: {=IFERROR( INDEX(big_rental_contract!A:A, MATCH(C58, big_rental_contract!F:F, 0)), "" )} -> A0013 | B58: RL00058 | C58: 行天宮夏野良栗 | D58: A | E58: 分租雅房 | F58: 無 | G58: 11.01 | H58: 14500 | I58: =IF(O58<>"空房招租中", O58, IF(N58="", "空房招租中", IF(ISNUMBER(SEARCH("分層", E58)), IF(COUNTIFS(N:N, N58, O:O, "<>空房招租中") > 0, "入住中", "空房招租中"), IF(COUNTIFS(N:N, N58, O:O, "<>空房招租中", E:E, "*分層*") > 0, "入住中", IF(COUNTIFS(N:N, N58, O:O, "空房招租中", E:E, "*分層*") > 0, "分層優先(隱藏)", "空房招租中") ) ) ) ) -> 46081 | J58: 行天宮站2分鐘 大採光A房 | K58: https://youtu.be/DCogbWAwCkY?si=N4RGD3Aw7LN_1sa3 | L58: =IF(AND(A58="", C58="", D58=""), "Z", "A") -> A | O58: =IF(AND(C58<>"", D58<>""), IF(COUNTIFS(sublease_contract!$C:$C, C58, sublease_contract!$D:$D, "*" & D58 & "*", sublease_contract!$G:$G, "<>已退租") = 0, "空房招租中", IF(COUNTIFS(sublease_contract!$C:$C, C58, sublease_contract!$D:$D, "*" & D58 & "*", sublease_contract!$G:$G, "<>已退租", sublease_contract!$N:$N, ">" & (TODAY()+20)) > 0, "入住中", IF(COUNTIFS(sublease_contract!$C:$C, C58, sublease_contract!$D:$D, "*" & D58 & "*", sublease_contract!$G:$G, "<>已退租", sublease_contract!$N:$N, ">=" & TODAY(), sublease_contract!$N:$N, "<=" & (TODAY()+20)) > 0, MINIFS(sublease_contract!$N:$N, sublease_contract!$C:$C, C58, sublease_contract!$D:$D, "*" & D58 & "*", sublease_contract!$G:$G, "<>已退租", sublease_contract!$N:$N, ">=" & TODAY(), sublease_contract!$N:$N, "<=" & (TODAY()+20)), "入住中"))), "") -> 46081
A59: {=IFERROR( INDEX(big_rental_contract!A:A, MATCH(C59, big_rental_contract!F:F, 0)), "" )} -> A0013 | B59: RL00059 | C59: 行天宮夏野良栗 | D59: B | E59: 分租雅房 | F59: 無 | G59: 10.83 | H59: 14500 | I59: =IF(O59<>"空房招租中", O59, IF(N59="", "空房招租中", IF(ISNUMBER(SEARCH("分層", E59)), IF(COUNTIFS(N:N, N59, O:O, "<>空房招租中") > 0, "入住中", "空房招租中"), IF(COUNTIFS(N:N, N59, O:O, "<>空房招租中", E:E, "*分層*") > 0, "入住中", IF(COUNTIFS(N:N, N59, O:O, "空房招租中", E:E, "*分層*") > 0, "分層優先(隱藏)", "空房招租中") ) ) ) ) -> 46081 | J59: 行天宮站2分鐘 大採光B房 | K59: https://youtube.com/shorts/ukuVqe3alAM?si=0QQNUxEQykpjNbxT | L59: =IF(AND(A59="", C59="", D59=""), "Z", "A") -> A | O59: =IF(AND(C59<>"", D59<>""), IF(COUNTIFS(sublease_contract!$C:$C, C59, sublease_contract!$D:$D, "*" & D59 & "*", sublease_contract!$G:$G, "<>已退租") = 0, "空房招租中", IF(COUNTIFS(sublease_contract!$C:$C, C59, sublease_contract!$D:$D, "*" & D59 & "*", sublease_contract!$G:$G, "<>已退租", sublease_contract!$N:$N, ">" & (TODAY()+20)) > 0, "入住中", IF(COUNTIFS(sublease_contract!$C:$C, C59, sublease_contract!$D:$D, "*" & D59 & "*", sublease_contract!$G:$G, "<>已退租", sublease_contract!$N:$N, ">=" & TODAY(), sublease_contract!$N:$N, "<=" & (TODAY()+20)) > 0, MINIFS(sublease_contract!$N:$N, sublease_contract!$C:$C, C59, sublease_contract!$D:$D, "*" & D59 & "*", sublease_contract!$G:$G, "<>已退租", sublease_contract!$N:$N, ">=" & TODAY(), sublease_contract!$N:$N, "<=" & (TODAY()+20)), "入住中"))), "") -> 46081
A60: {=IFERROR( INDEX(big_rental_contract!A:A, MATCH(C60, big_rental_contract!F:F, 0)), "" )} -> A0013 | B60: RL00060 | C60: 行天宮夏野良栗 | D60: C | E60: 分租雅房 | F60: 無 | G60: 8.01 | H60: 12000 | I60: =IF(O60<>"空房招租中", O60, IF(N60="", "空房招租中", IF(ISNUMBER(SEARCH("分層", E60)), IF(COUNTIFS(N:N, N60, O:O, "<>空房招租中") > 0, "入住中", "空房招租中"), IF(COUNTIFS(N:N, N60, O:O, "<>空房招租中", E:E, "*分層*") > 0, "入住中", IF(COUNTIFS(N:N, N60, O:O, "空房招租中", E:E, "*分層*") > 0, "分層優先(隱藏)", "空房招租中") ) ) ) ) -> 入住中 | K60: https://youtube.com/shorts/MY1BoXAwgIE?si=sAfAFWOstlzyzIZD | L60: =IF(AND(A60="", C60="", D60=""), "Z", "A") -> A | O60: =IF(AND(C60<>"", D60<>""), IF(COUNTIFS(sublease_contract!$C:$C, C60, sublease_contract!$D:$D, "*" & D60 & "*", sublease_contract!$G:$G, "<>已退租") = 0, "空房招租中", IF(COUNTIFS(sublease_contract!$C:$C, C60, sublease_contract!$D:$D, "*" & D60 & "*", sublease_contract!$G:$G, "<>已退租", sublease_contract!$N:$N, ">" & (TODAY()+20)) > 0, "入住中", IF(COUNTIFS(sublease_contract!$C:$C, C60, sublease_contract!$D:$D, "*" & D60 & "*", sublease_contract!$G:$G, "<>已退租", sublease_contract!$N:$N, ">=" & TODAY(), sublease_contract!$N:$N, "<=" & (TODAY()+20)) > 0, MINIFS(sublease_contract!$N:$N, sublease_contract!$C:$C, C60, sublease_contract!$D:$D, "*" & D60 & "*", sublease_contract!$G:$G, "<>已退租", sublease_contract!$N:$N, ">=" & TODAY(), sublease_contract!$N:$N, "<=" & (TODAY()+20)), "入住中"))), "") -> 入住中
A61: {=IFERROR( INDEX(big_rental_contract!A:A, MATCH(C61, big_rental_contract!F:F, 0)), "" )} -> A0013 | B61: RL00061 | C61: 行天宮夏野良栗 | D61: D | E61: 分租雅房 | F61: 無 | G61: 8.03 | H61: 12000 | I61: =IF(O61<>"空房招租中", O61, IF(N61="", "空房招租中", IF(ISNUMBER(SEARCH("分層", E61)), IF(COUNTIFS(N:N, N61, O:O, "<>空房招租中") > 0, "入住中", "空房招租中"), IF(COUNTIFS(N:N, N61, O:O, "<>空房招租中", E:E, "*分層*") > 0, "入住中", IF(COUNTIFS(N:N, N61, O:O, "空房招租中", E:E, "*分層*") > 0, "分層優先(隱藏)", "空房招租中") ) ) ) ) -> 入住中 | K61: https://youtube.com/shorts/sf_ZarNVvz0?si=wwQrCBGg-vk7ERsg | L61: =IF(AND(A61="", C61="", D61=""), "Z", "A") -> A | O61: =IF(AND(C61<>"", D61<>""), IF(COUNTIFS(sublease_contract!$C:$C, C61, sublease_contract!$D:$D, "*" & D61 & "*", sublease_contract!$G:$G, "<>已退租") = 0, "空房招租中", IF(COUNTIFS(sublease_contract!$C:$C, C61, sublease_contract!$D:$D, "*" & D61 & "*", sublease_contract!$G:$G, "<>已退租", sublease_contract!$N:$N, ">" & (TODAY()+20)) > 0, "入住中", IF(COUNTIFS(sublease_contract!$C:$C, C61, sublease_contract!$D:$D, "*" & D61 & "*", sublease_contract!$G:$G, "<>已退租", sublease_contract!$N:$N, ">=" & TODAY(), sublease_contract!$N:$N, "<=" & (TODAY()+20)) > 0, MINIFS(sublease_contract!$N:$N, sublease_contract!$C:$C, C61, sublease_contract!$D:$D, "*" & D61 & "*", sublease_contract!$G:$G, "<>已退租", sublease_contract!$N:$N, ">=" & TODAY(), sublease_contract!$N:$N, "<=" & (TODAY()+20)), "入住中"))), "") -> 入住中
A62: {=IFERROR( INDEX(big_rental_contract!A:A, MATCH(C62, big_rental_contract!F:F, 0)), "" )} -> A0013 | B62: RL00062 | C62: 行天宮夏野良栗 | D62: E | E62: 分租雅房 | F62: 頂加 | G62: 12.91 | H62: 13900 | I62: =IF(O62<>"空房招租中", O62, IF(N62="", "空房招租中", IF(ISNUMBER(SEARCH("分層", E62)), IF(COUNTIFS(N:N, N62, O:O, "<>空房招租中") > 0, "入住中", "空房招租中"), IF(COUNTIFS(N:N, N62, O:O, "<>空房招租中", E:E, "*分層*") > 0, "入住中", IF(COUNTIFS(N:N, N62, O:O, "空房招租中", E:E, "*分層*") > 0, "分層優先(隱藏)", "空房招租中") ) ) ) ) -> 入住中 | K62: https://youtu.be/ZscsdId_Mg8 | L62: =IF(AND(A62="", C62="", D62=""), "Z", "A") -> A | M62: 無 | N62: Group_Top_02 | O62: =IF(AND(C62<>"", D62<>""), IF(COUNTIFS(sublease_contract!$C:$C, C62, sublease_contract!$D:$D, "*" & D62 & "*", sublease_contract!$G:$G, "<>已退租") = 0, "空房招租中", IF(COUNTIFS(sublease_contract!$C:$C, C62, sublease_contract!$D:$D, "*" & D62 & "*", sublease_contract!$G:$G, "<>已退租", sublease_contract!$N:$N, ">" & (TODAY()+20)) > 0, "入住中", IF(COUNTIFS(sublease_contract!$C:$C, C62, sublease_contract!$D:$D, "*" & D62 & "*", sublease_contract!$G:$G, "<>已退租", sublease_contract!$N:$N, ">=" & TODAY(), sublease_contract!$N:$N, "<=" & (TODAY()+20)) > 0, MINIFS(sublease_contract!$N:$N, sublease_contract!$C:$C, C62, sublease_contract!$D:$D, "*" & D62 & "*", sublease_contract!$G:$G, "<>已退租", sublease_contract!$N:$N, ">=" & TODAY(), sublease_contract!$N:$N, "<=" & (TODAY()+20)), "入住中"))), "") -> 空房招租中
A63: {=IFERROR( INDEX(big_rental_contract!A:A, MATCH(C63, big_rental_contract!F:F, 0)), "" )} -> A0013 | B63: RL00063 | C63: 行天宮夏野良栗 | D63: F | E63: 分租雅房 | F63: 頂加 | G63: 14.13 | H63: 13900 | I63: =IF(O63<>"空房招租中", O63, IF(N63="", "空房招租中", IF(ISNUMBER(SEARCH("分層", E63)), IF(COUNTIFS(N:N, N63, O:O, "<>空房招租中") > 0, "入住中", "空房招租中"), IF(COUNTIFS(N:N, N63, O:O, "<>空房招租中", E:E, "*分層*") > 0, "入住中", IF(COUNTIFS(N:N, N63, O:O, "空房招租中", E:E, "*分層*") > 0, "分層優先(隱藏)", "空房招租中") ) ) ) ) -> 入住中 | K63: https://youtu.be/ZscsdId_Mg8 | L63: =IF(AND(A63="", C63="", D63=""), "Z", "A") -> A | M63: 無 | N63: Group_Top_02 | O63: =IF(AND(C63<>"", D63<>""), IF(COUNTIFS(sublease_contract!$C:$C, C63, sublease_contract!$D:$D, "*" & D63 & "*", sublease_contract!$G:$G, "<>已退租") = 0, "空房招租中", IF(COUNTIFS(sublease_contract!$C:$C, C63, sublease_contract!$D:$D, "*" & D63 & "*", sublease_contract!$G:$G, "<>已退租", sublease_contract!$N:$N, ">" & (TODAY()+20)) > 0, "入住中", IF(COUNTIFS(sublease_contract!$C:$C, C63, sublease_contract!$D:$D, "*" & D63 & "*", sublease_contract!$G:$G, "<>已退租", sublease_contract!$N:$N, ">=" & TODAY(), sublease_contract!$N:$N, "<=" & (TODAY()+20)) > 0, MINIFS(sublease_contract!$N:$N, sublease_contract!$C:$C, C63, sublease_contract!$D:$D, "*" & D63 & "*", sublease_contract!$G:$G, "<>已退租", sublease_contract!$N:$N, ">=" & TODAY(), sublease_contract!$N:$N, "<=" & (TODAY()+20)), "入住中"))), "") -> 空房招租中
A64: {=IFERROR( INDEX(big_rental_contract!A:A, MATCH(C64, big_rental_contract!F:F, 0)), "" )} -> A0014 | B64: RL00064 | C64: 中山北Feli家 | D64: A | E64: 分租雅房 | F64: 無 | G64: 12.51 | H64: 13200 | I64: =IF(O64<>"空房招租中", O64, IF(N64="", "空房招租中", IF(ISNUMBER(SEARCH("分層", E64)), IF(COUNTIFS(N:N, N64, O:O, "<>空房招租中") > 0, "入住中", "空房招租中"), IF(COUNTIFS(N:N, N64, O:O, "<>空房招租中", E:E, "*分層*") > 0, "入住中", IF(COUNTIFS(N:N, N64, O:O, "空房招租中", E:E, "*分層*") > 0, "分層優先(隱藏)", "空房招租中") ) ) ) ) -> 46081 | L64: =IF(AND(A64="", C64="", D64=""), "Z", "A") -> A | O64: =IF(AND(C64<>"", D64<>""), IF(COUNTIFS(sublease_contract!$C:$C, C64, sublease_contract!$D:$D, "*" & D64 & "*", sublease_contract!$G:$G, "<>已退租") = 0, "空房招租中", IF(COUNTIFS(sublease_contract!$C:$C, C64, sublease_contract!$D:$D, "*" & D64 & "*", sublease_contract!$G:$G, "<>已退租", sublease_contract!$N:$N, ">" & (TODAY()+20)) > 0, "入住中", IF(COUNTIFS(sublease_contract!$C:$C, C64, sublease_contract!$D:$D, "*" & D64 & "*", sublease_contract!$G:$G, "<>已退租", sublease_contract!$N:$N, ">=" & TODAY(), sublease_contract!$N:$N, "<=" & (TODAY()+20)) > 0, MINIFS(sublease_contract!$N:$N, sublease_contract!$C:$C, C64, sublease_contract!$D:$D, "*" & D64 & "*", sublease_contract!$G:$G, "<>已退租", sublease_contract!$N:$N, ">=" & TODAY(), sublease_contract!$N:$N, "<=" & (TODAY()+20)), "入住中"))), "") -> 46081
A65: {=IFERROR( INDEX(big_rental_contract!A:A, MATCH(C65, big_rental_contract!F:F, 0)), "" )} -> A0014 | B65: RL00065 | C65: 中山北Feli家 | D65: B | E65: 分租套房 | F65: 無 | G65: 19.54 | H65: 17500 | I65: =IF(O65<>"空房招租中", O65, IF(N65="", "空房招租中", IF(ISNUMBER(SEARCH("分層", E65)), IF(COUNTIFS(N:N, N65, O:O, "<>空房招租中") > 0, "入住中", "空房招租中"), IF(COUNTIFS(N:N, N65, O:O, "<>空房招租中", E:E, "*分層*") > 0, "入住中", IF(COUNTIFS(N:N, N65, O:O, "空房招租中", E:E, "*分層*") > 0, "分層優先(隱藏)", "空房招租中") ) ) ) ) -> 入住中 | L65: =IF(AND(A65="", C65="", D65=""), "Z", "A") -> A | O65: =IF(AND(C65<>"", D65<>""), IF(COUNTIFS(sublease_contract!$C:$C, C65, sublease_contract!$D:$D, "*" & D65 & "*", sublease_contract!$G:$G, "<>已退租") = 0, "空房招租中", IF(COUNTIFS(sublease_contract!$C:$C, C65, sublease_contract!$D:$D, "*" & D65 & "*", sublease_contract!$G:$G, "<>已退租", sublease_contract!$N:$N, ">" & (TODAY()+20)) > 0, "入住中", IF(COUNTIFS(sublease_contract!$C:$C, C65, sublease_contract!$D:$D, "*" & D65 & "*", sublease_contract!$G:$G, "<>已退租", sublease_contract!$N:$N, ">=" & TODAY(), sublease_contract!$N:$N, "<=" & (TODAY()+20)) > 0, MINIFS(sublease_contract!$N:$N, sublease_contract!$C:$C, C65, sublease_contract!$D:$D, "*" & D65 & "*", sublease_contract!$G:$G, "<>已退租", sublease_contract!$N:$N, ">=" & TODAY(), sublease_contract!$N:$N, "<=" & (TODAY()+20)), "入住中"))), "") -> 入住中
A66: {=IFERROR( INDEX(big_rental_contract!A:A, MATCH(C66, big_rental_contract!F:F, 0)), "" )} -> A0014 | B66: RL00066 | C66: 中山北Feli家 | D66: C | E66: 分租雅房 | F66: 無 | G66: 9.41 | H66: 11500 | I66: =IF(O66<>"空房招租中", O66, IF(N66="", "空房招租中", IF(ISNUMBER(SEARCH("分層", E66)), IF(COUNTIFS(N:N, N66, O:O, "<>空房招租中") > 0, "入住中", "空房招租中"), IF(COUNTIFS(N:N, N66, O:O, "<>空房招租中", E:E, "*分層*") > 0, "入住中", IF(COUNTIFS(N:N, N66, O:O, "空房招租中", E:E, "*分層*") > 0, "分層優先(隱藏)", "空房招租中") ) ) ) ) -> 入住中 | K66: https://www.youtube.com/shorts/pMkJsIWW1V4 | L66: =IF(AND(A66="", C66="", D66=""), "Z", "A") -> A | O66: =IF(AND(C66<>"", D66<>""), IF(COUNTIFS(sublease_contract!$C:$C, C66, sublease_contract!$D:$D, "*" & D66 & "*", sublease_contract!$G:$G, "<>已退租") = 0, "空房招租中", IF(COUNTIFS(sublease_contract!$C:$C, C66, sublease_contract!$D:$D, "*" & D66 & "*", sublease_contract!$G:$G, "<>已退租", sublease_contract!$N:$N, ">" & (TODAY()+20)) > 0, "入住中", IF(COUNTIFS(sublease_contract!$C:$C, C66, sublease_contract!$D:$D, "*" & D66 & "*", sublease_contract!$G:$G, "<>已退租", sublease_contract!$N:$N, ">=" & TODAY(), sublease_contract!$N:$N, "<=" & (TODAY()+20)) > 0, MINIFS(sublease_contract!$N:$N, sublease_contract!$C:$C, C66, sublease_contract!$D:$D, "*" & D66 & "*", sublease_contract!$G:$G, "<>已退租", sublease_contract!$N:$N, ">=" & TODAY(), sublease_contract!$N:$N, "<=" & (TODAY()+20)), "入住中"))), "") -> 入住中
A67: {=IFERROR( INDEX(big_rental_contract!A:A, MATCH(C67, big_rental_contract!F:F, 0)), "" )} -> A0014 | B67: RL00067 | C67: 中山北Feli家 | D67: D | E67: 分租雅房 | F67: 無 | G67: 7.5 | H67: 10800 | I67: =IF(O67<>"空房招租中", O67, IF(N67="", "空房招租中", IF(ISNUMBER(SEARCH("分層", E67)), IF(COUNTIFS(N:N, N67, O:O, "<>空房招租中") > 0, "入住中", "空房招租中"), IF(COUNTIFS(N:N, N67, O:O, "<>空房招租中", E:E, "*分層*") > 0, "入住中", IF(COUNTIFS(N:N, N67, O:O, "空房招租中", E:E, "*分層*") > 0, "分層優先(隱藏)", "空房招租中") ) ) ) ) -> 入住中 | L67: =IF(AND(A67="", C67="", D67=""), "Z", "A") -> A | O67: =IF(AND(C67<>"", D67<>""), IF(COUNTIFS(sublease_contract!$C:$C, C67, sublease_contract!$D:$D, "*" & D67 & "*", sublease_contract!$G:$G, "<>已退租") = 0, "空房招租中", IF(COUNTIFS(sublease_contract!$C:$C, C67, sublease_contract!$D:$D, "*" & D67 & "*", sublease_contract!$G:$G, "<>已退租", sublease_contract!$N:$N, ">" & (TODAY()+20)) > 0, "入住中", IF(COUNTIFS(sublease_contract!$C:$C, C67, sublease_contract!$D:$D, "*" & D67 & "*", sublease_contract!$G:$G, "<>已退租", sublease_contract!$N:$N, ">=" & TODAY(), sublease_contract!$N:$N, "<=" & (TODAY()+20)) > 0, MINIFS(sublease_contract!$N:$N, sublease_contract!$C:$C, C67, sublease_contract!$D:$D, "*" & D67 & "*", sublease_contract!$G:$G, "<>已退租", sublease_contract!$N:$N, ">=" & TODAY(), sublease_contract!$N:$N, "<=" & (TODAY()+20)), "入住中"))), "") -> 入住中
A68: {=IFERROR( INDEX(big_rental_contract!A:A, MATCH(C68, big_rental_contract!F:F, 0)), "" )} -> A0014 | B68: RL00068 | C68: 中山北Feli家 | D68: E | E68: 分租雅房 | F68: 頂加 | G68: 9.83 | H68: 14900 | I68: =IF(O68<>"空房招租中", O68, IF(N68="", "空房招租中", IF(ISNUMBER(SEARCH("分層", E68)), IF(COUNTIFS(N:N, N68, O:O, "<>空房招租中") > 0, "入住中", "空房招租中"), IF(COUNTIFS(N:N, N68, O:O, "<>空房招租中", E:E, "*分層*") > 0, "入住中", IF(COUNTIFS(N:N, N68, O:O, "空房招租中", E:E, "*分層*") > 0, "分層優先(隱藏)", "空房招租中") ) ) ) ) -> 入住中 | K68: https://youtu.be/TJK-1_1QY_k?si=VSoka00YRegdQaRX | L68: =IF(AND(A68="", C68="", D68=""), "Z", "A") -> A | M68: 無 | N68: Group_Top_03 | O68: =IF(AND(C68<>"", D68<>""), IF(COUNTIFS(sublease_contract!$C:$C, C68, sublease_contract!$D:$D, "*" & D68 & "*", sublease_contract!$G:$G, "<>已退租") = 0, "空房招租中", IF(COUNTIFS(sublease_contract!$C:$C, C68, sublease_contract!$D:$D, "*" & D68 & "*", sublease_contract!$G:$G, "<>已退租", sublease_contract!$N:$N, ">" & (TODAY()+20)) > 0, "入住中", IF(COUNTIFS(sublease_contract!$C:$C, C68, sublease_contract!$D:$D, "*" & D68 & "*", sublease_contract!$G:$G, "<>已退租", sublease_contract!$N:$N, ">=" & TODAY(), sublease_contract!$N:$N, "<=" & (TODAY()+20)) > 0, MINIFS(sublease_contract!$N:$N, sublease_contract!$C:$C, C68, sublease_contract!$D:$D, "*" & D68 & "*", sublease_contract!$G:$G, "<>已退租", sublease_contract!$N:$N, ">=" & TODAY(), sublease_contract!$N:$N, "<=" & (TODAY()+20)), "入住中"))), "") -> 入住中
A69: {=IFERROR( INDEX(big_rental_contract!A:A, MATCH(C69, big_rental_contract!F:F, 0)), "" )} -> A0014 | B69: RL00069 | C69: 中山北Feli家 | D69: F | E69: 分租雅房 | F69: 頂加 | G69: 9.74 | H69: 14900 | I69: =IF(O69<>"空房招租中", O69, IF(N69="", "空房招租中", IF(ISNUMBER(SEARCH("分層", E69)), IF(COUNTIFS(N:N, N69, O:O, "<>空房招租中") > 0, "入住中", "空房招租中"), IF(COUNTIFS(N:N, N69, O:O, "<>空房招租中", E:E, "*分層*") > 0, "入住中", IF(COUNTIFS(N:N, N69, O:O, "空房招租中", E:E, "*分層*") > 0, "分層優先(隱藏)", "空房招租中") ) ) ) ) -> 入住中 | K69: https://youtu.be/TJK-1_1QY_k?si=VSoka00YRegdQaRX | L69: =IF(AND(A69="", C69="", D69=""), "Z", "A") -> A | M69: 無 | N69: Group_Top_03 | O69: =IF(AND(C69<>"", D69<>""), IF(COUNTIFS(sublease_contract!$C:$C, C69, sublease_contract!$D:$D, "*" & D69 & "*", sublease_contract!$G:$G, "<>已退租") = 0, "空房招租中", IF(COUNTIFS(sublease_contract!$C:$C, C69, sublease_contract!$D:$D, "*" & D69 & "*", sublease_contract!$G:$G, "<>已退租", sublease_contract!$N:$N, ">" & (TODAY()+20)) > 0, "入住中", IF(COUNTIFS(sublease_contract!$C:$C, C69, sublease_contract!$D:$D, "*" & D69 & "*", sublease_contract!$G:$G, "<>已退租", sublease_contract!$N:$N, ">=" & TODAY(), sublease_contract!$N:$N, "<=" & (TODAY()+20)) > 0, MINIFS(sublease_contract!$N:$N, sublease_contract!$C:$C, C69, sublease_contract!$D:$D, "*" & D69 & "*", sublease_contract!$G:$G, "<>已退租", sublease_contract!$N:$N, ">=" & TODAY(), sublease_contract!$N:$N, "<=" & (TODAY()+20)), "入住中"))), "") -> 入住中
A70: {=IFERROR( INDEX(big_rental_contract!A:A, MATCH(C70, big_rental_contract!F:F, 0)), "" )} -> A0015 | B70: RL00070 | C70: 書香民生 | D70: A | E70: 分租雅房 | F70: 無 | G70: 11.55 | H70: 13800 | I70: =IF(O70<>"空房招租中", O70, IF(N70="", "空房招租中", IF(ISNUMBER(SEARCH("分層", E70)), IF(COUNTIFS(N:N, N70, O:O, "<>空房招租中") > 0, "入住中", "空房招租中"), IF(COUNTIFS(N:N, N70, O:O, "<>空房招租中", E:E, "*分層*") > 0, "入住中", IF(COUNTIFS(N:N, N70, O:O, "空房招租中", E:E, "*分層*") > 0, "分層優先(隱藏)", "空房招租中") ) ) ) ) -> 入住中 | J70: 淡雅質感明亮中雅房 | K70: https://youtube.com/shorts/5GJvoXUvbds?feature=share | L70: =IF(AND(A70="", C70="", D70=""), "Z", "A") -> A | O70: =IF(AND(C70<>"", D70<>""), IF(COUNTIFS(sublease_contract!$C:$C, C70, sublease_contract!$D:$D, "*" & D70 & "*", sublease_contract!$G:$G, "<>已退租") = 0, "空房招租中", IF(COUNTIFS(sublease_contract!$C:$C, C70, sublease_contract!$D:$D, "*" & D70 & "*", sublease_contract!$G:$G, "<>已退租", sublease_contract!$N:$N, ">" & (TODAY()+20)) > 0, "入住中", IF(COUNTIFS(sublease_contract!$C:$C, C70, sublease_contract!$D:$D, "*" & D70 & "*", sublease_contract!$G:$G, "<>已退租", sublease_contract!$N:$N, ">=" & TODAY(), sublease_contract!$N:$N, "<=" & (TODAY()+20)) > 0, MINIFS(sublease_contract!$N:$N, sublease_contract!$C:$C, C70, sublease_contract!$D:$D, "*" & D70 & "*", sublease_contract!$G:$G, "<>已退租", sublease_contract!$N:$N, ">=" & TODAY(), sublease_contract!$N:$N, "<=" & (TODAY()+20)), "入住中"))), "") -> 入住中
A71: {=IFERROR( INDEX(big_rental_contract!A:A, MATCH(C71, big_rental_contract!F:F, 0)), "" )} -> A0015 | B71: RL00071 | C71: 書香民生 | D71: B | E71: 分租雅房 | F71: 無 | G71: 17.44 | H71: 17800 | I71: =IF(O71<>"空房招租中", O71, IF(N71="", "空房招租中", IF(ISNUMBER(SEARCH("分層", E71)), IF(COUNTIFS(N:N, N71, O:O, "<>空房招租中") > 0, "入住中", "空房招租中"), IF(COUNTIFS(N:N, N71, O:O, "<>空房招租中", E:E, "*分層*") > 0, "入住中", IF(COUNTIFS(N:N, N71, O:O, "空房招租中", E:E, "*分層*") > 0, "分層優先(隱藏)", "空房招租中") ) ) ) ) -> 入住中 | J71: (可雙人承租 雙租補)大落地窗採光聯考大大大雅房 | K71: https://youtube.com/shorts/hWPCPa4Klr0?feature=share | L71: =IF(AND(A71="", C71="", D71=""), "Z", "A") -> A | O71: =IF(AND(C71<>"", D71<>""), IF(COUNTIFS(sublease_contract!$C:$C, C71, sublease_contract!$D:$D, "*" & D71 & "*", sublease_contract!$G:$G, "<>已退租") = 0, "空房招租中", IF(COUNTIFS(sublease_contract!$C:$C, C71, sublease_contract!$D:$D, "*" & D71 & "*", sublease_contract!$G:$G, "<>已退租", sublease_contract!$N:$N, ">" & (TODAY()+20)) > 0, "入住中", IF(COUNTIFS(sublease_contract!$C:$C, C71, sublease_contract!$D:$D, "*" & D71 & "*", sublease_contract!$G:$G, "<>已退租", sublease_contract!$N:$N, ">=" & TODAY(), sublease_contract!$N:$N, "<=" & (TODAY()+20)) > 0, MINIFS(sublease_contract!$N:$N, sublease_contract!$C:$C, C71, sublease_contract!$D:$D, "*" & D71 & "*", sublease_contract!$G:$G, "<>已退租", sublease_contract!$N:$N, ">=" & TODAY(), sublease_contract!$N:$N, "<=" & (TODAY()+20)), "入住中"))), "") -> 入住中
A72: {=IFERROR( INDEX(big_rental_contract!A:A, MATCH(C72, big_rental_contract!F:F, 0)), "" )} -> A0015 | B72: RL00072 | C72: 書香民生 | D72: C | E72: 分租雅房 | F72: 無 | G72: 15.28 | H72: 14800 | I72: =IF(O72<>"空房招租中", O72, IF(N72="", "空房招租中", IF(ISNUMBER(SEARCH("分層", E72)), IF(COUNTIFS(N:N, N72, O:O, "<>空房招租中") > 0, "入住中", "空房招租中"), IF(COUNTIFS(N:N, N72, O:O, "<>空房招租中", E:E, "*分層*") > 0, "入住中", IF(COUNTIFS(N:N, N72, O:O, "空房招租中", E:E, "*分層*") > 0, "分層優先(隱藏)", "空房招租中") ) ) ) ) -> 入住中 | J72: 方正大片採光大雅房 | K72: https://youtube.com/shorts/LpY6OVSP0IU?feature=share | L72: =IF(AND(A72="", C72="", D72=""), "Z", "A") -> A | O72: =IF(AND(C72<>"", D72<>""), IF(COUNTIFS(sublease_contract!$C:$C, C72, sublease_contract!$D:$D, "*" & D72 & "*", sublease_contract!$G:$G, "<>已退租") = 0, "空房招租中", IF(COUNTIFS(sublease_contract!$C:$C, C72, sublease_contract!$D:$D, "*" & D72 & "*", sublease_contract!$G:$G, "<>已退租", sublease_contract!$N:$N, ">" & (TODAY()+20)) > 0, "入住中", IF(COUNTIFS(sublease_contract!$C:$C, C72, sublease_contract!$D:$D, "*" & D72 & "*", sublease_contract!$G:$G, "<>已退租", sublease_contract!$N:$N, ">=" & TODAY(), sublease_contract!$N:$N, "<=" & (TODAY()+20)) > 0, MINIFS(sublease_contract!$N:$N, sublease_contract!$C:$C, C72, sublease_contract!$D:$D, "*" & D72 & "*", sublease_contract!$G:$G, "<>已退租", sublease_contract!$N:$N, ">=" & TODAY(), sublease_contract!$N:$N, "<=" & (TODAY()+20)), "入住中"))), "") -> 入住中
A73: {=IFERROR( INDEX(big_rental_contract!A:A, MATCH(C73, big_rental_contract!F:F, 0)), "" )} -> A0015 | B73: RL00081 | C73: 書香民生 | D73: D | E73: 分租雅房 | F73: 無 | G73: 13.22 | H73: 17800 | I73: =IF(O73<>"空房招租中", O73, IF(N73="", "空房招租中", IF(ISNUMBER(SEARCH("分層", E73)), IF(COUNTIFS(N:N, N73, O:O, "<>空房招租中") > 0, "入住中", "空房招租中"), IF(COUNTIFS(N:N, N73, O:O, "<>空房招租中", E:E, "*分層*") > 0, "入住中", IF(COUNTIFS(N:N, N73, O:O, "空房招租中", E:E, "*分層*") > 0, "分層優先(隱藏)", "空房招租中") ) ) ) ) -> 入住中 | J73: Cozy採光 兩房共享飯店級衛浴 類套房 | K73: https://youtu.be/L7UDBD9pXUw | L73: =IF(AND(A73="", C73="", D73=""), "Z", "A") -> A | O73: =IF(AND(C73<>"", D73<>""), IF(COUNTIFS(sublease_contract!$C:$C, C73, sublease_contract!$D:$D, "*" & D73 & "*", sublease_contract!$G:$G, "<>已退租") = 0, "空房招租中", IF(COUNTIFS(sublease_contract!$C:$C, C73, sublease_contract!$D:$D, "*" & D73 & "*", sublease_contract!$G:$G, "<>已退租", sublease_contract!$N:$N, ">" & (TODAY()+20)) > 0, "入住中", IF(COUNTIFS(sublease_contract!$C:$C, C73, sublease_contract!$D:$D, "*" & D73 & "*", sublease_contract!$G:$G, "<>已退租", sublease_contract!$N:$N, ">=" & TODAY(), sublease_contract!$N:$N, "<=" & (TODAY()+20)) > 0, MINIFS(sublease_contract!$N:$N, sublease_contract!$C:$C, C73, sublease_contract!$D:$D, "*" & D73 & "*", sublease_contract!$G:$G, "<>已退租", sublease_contract!$N:$N, ">=" & TODAY(), sublease_contract!$N:$N, "<=" & (TODAY()+20)), "入住中"))), "") -> 入住中
A74: {=IFERROR( INDEX(big_rental_contract!A:A, MATCH(C74, big_rental_contract!F:F, 0)), "" )} -> A0015 | B74: RL00073 | C74: 書香民生 | D74: E | E74: 分租雅房 | F74: 無 | G74: 13.19 | H74: 17800 | I74: =IF(O74<>"空房招租中", O74, IF(N74="", "空房招租中", IF(ISNUMBER(SEARCH("分層", E74)), IF(COUNTIFS(N:N, N74, O:O, "<>空房招租中") > 0, "入住中", "空房招租中"), IF(COUNTIFS(N:N, N74, O:O, "<>空房招租中", E:E, "*分層*") > 0, "入住中", IF(COUNTIFS(N:N, N74, O:O, "空房招租中", E:E, "*分層*") > 0, "分層優先(隱藏)", "空房招租中") ) ) ) ) -> 入住中 | J74: 沉穩綠意 兩房共享飯店級衛浴 類套房 | K74: https://youtu.be/L7UDBD9pXUw | L74: =IF(AND(A74="", C74="", D74=""), "Z", "A") -> A | O74: =IF(AND(C74<>"", D74<>""), IF(COUNTIFS(sublease_contract!$C:$C, C74, sublease_contract!$D:$D, "*" & D74 & "*", sublease_contract!$G:$G, "<>已退租") = 0, "空房招租中", IF(COUNTIFS(sublease_contract!$C:$C, C74, sublease_contract!$D:$D, "*" & D74 & "*", sublease_contract!$G:$G, "<>已退租", sublease_contract!$N:$N, ">" & (TODAY()+20)) > 0, "入住中", IF(COUNTIFS(sublease_contract!$C:$C, C74, sublease_contract!$D:$D, "*" & D74 & "*", sublease_contract!$G:$G, "<>已退租", sublease_contract!$N:$N, ">=" & TODAY(), sublease_contract!$N:$N, "<=" & (TODAY()+20)) > 0, MINIFS(sublease_contract!$N:$N, sublease_contract!$C:$C, C74, sublease_contract!$D:$D, "*" & D74 & "*", sublease_contract!$G:$G, "<>已退租", sublease_contract!$N:$N, ">=" & TODAY(), sublease_contract!$N:$N, "<=" & (TODAY()+20)), "入住中"))), "") -> 入住中
A75: {=IFERROR( INDEX(big_rental_contract!A:A, MATCH(C75, big_rental_contract!F:F, 0)), "" )} -> A0015 | B75: RL00074 | C75: 書香民生 | D75: F | E75: 分租雅房 | F75: 頂加 | G75: 10.97 | H75: 15800 | I75: =IF(O75<>"空房招租中", O75, IF(N75="", "空房招租中", IF(ISNUMBER(SEARCH("分層", E75)), IF(COUNTIFS(N:N, N75, O:O, "<>空房招租中") > 0, "入住中", "空房招租中"), IF(COUNTIFS(N:N, N75, O:O, "<>空房招租中", E:E, "*分層*") > 0, "入住中", IF(COUNTIFS(N:N, N75, O:O, "空房招租中", E:E, "*分層*") > 0, "分層優先(隱藏)", "空房招租中") ) ) ) ) -> 入住中 | J75: 大片露臺採光Cozy頂加雅房 | K75: https://youtube.com/shorts/CPeNDmdMgvQ?feature=share | L75: =IF(AND(A75="", C75="", D75=""), "Z", "A") -> A | O75: =IF(AND(C75<>"", D75<>""), IF(COUNTIFS(sublease_contract!$C:$C, C75, sublease_contract!$D:$D, "*" & D75 & "*", sublease_contract!$G:$G, "<>已退租") = 0, "空房招租中", IF(COUNTIFS(sublease_contract!$C:$C, C75, sublease_contract!$D:$D, "*" & D75 & "*", sublease_contract!$G:$G, "<>已退租", sublease_contract!$N:$N, ">" & (TODAY()+20)) > 0, "入住中", IF(COUNTIFS(sublease_contract!$C:$C, C75, sublease_contract!$D:$D, "*" & D75 & "*", sublease_contract!$G:$G, "<>已退租", sublease_contract!$N:$N, ">=" & TODAY(), sublease_contract!$N:$N, "<=" & (TODAY()+20)) > 0, MINIFS(sublease_contract!$N:$N, sublease_contract!$C:$C, C75, sublease_contract!$D:$D, "*" & D75 & "*", sublease_contract!$G:$G, "<>已退租", sublease_contract!$N:$N, ">=" & TODAY(), sublease_contract!$N:$N, "<=" & (TODAY()+20)), "入住中"))), "") -> 入住中
A76: {=IFERROR( INDEX(big_rental_contract!A:A, MATCH(C76, big_rental_contract!F:F, 0)), "" )} -> A0015 | B76: RL00082 | C76: 書香民生 | D76: G | E76: 分租雅房 | F76: 頂加 | G76: 16.14 | H76: 16800 | I76: =IF(O76<>"空房招租中", O76, IF(N76="", "空房招租中", IF(ISNUMBER(SEARCH("分層", E76)), IF(COUNTIFS(N:N, N76, O:O, "<>空房招租中") > 0, "入住中", "空房招租中"), IF(COUNTIFS(N:N, N76, O:O, "<>空房招租中", E:E, "*分層*") > 0, "入住中", IF(COUNTIFS(N:N, N76, O:O, "空房招租中", E:E, "*分層*") > 0, "分層優先(隱藏)", "空房招租中") ) ) ) ) -> 入住中 | J76: (可雙人承租 雙租補)大空間全實心牆頂加瑜珈雅房 | K76: https://youtube.com/shorts/z4krI2adQhU?feature=share | L76: =IF(AND(A76="", C76="", D76=""), "Z", "A") -> A | O76: =IF(AND(C76<>"", D76<>""), IF(COUNTIFS(sublease_contract!$C:$C, C76, sublease_contract!$D:$D, "*" & D76 & "*", sublease_contract!$G:$G, "<>已退租") = 0, "空房招租中", IF(COUNTIFS(sublease_contract!$C:$C, C76, sublease_contract!$D:$D, "*" & D76 & "*", sublease_contract!$G:$G, "<>已退租", sublease_contract!$N:$N, ">" & (TODAY()+20)) > 0, "入住中", IF(COUNTIFS(sublease_contract!$C:$C, C76, sublease_contract!$D:$D, "*" & D76 & "*", sublease_contract!$G:$G, "<>已退租", sublease_contract!$N:$N, ">=" & TODAY(), sublease_contract!$N:$N, "<=" & (TODAY()+20)) > 0, MINIFS(sublease_contract!$N:$N, sublease_contract!$C:$C, C76, sublease_contract!$D:$D, "*" & D76 & "*", sublease_contract!$G:$G, "<>已退租", sublease_contract!$N:$N, ">=" & TODAY(), sublease_contract!$N:$N, "<=" & (TODAY()+20)), "入住中"))), "") -> 入住中
A77: {=IFERROR( INDEX(big_rental_contract!A:A, MATCH(C77, big_rental_contract!F:F, 0)), "" )} -> A0016 | B77: RL00075 | C77: 內湖CityLink | D77: A | E77: 分租雅房 | F77: 無 | G77: 11.48 | H77: 14800 | I77: =IF(O77<>"空房招租中", O77, IF(N77="", "空房招租中", IF(ISNUMBER(SEARCH("分層", E77)), IF(COUNTIFS(N:N, N77, O:O, "<>空房招租中") > 0, "入住中", "空房招租中"), IF(COUNTIFS(N:N, N77, O:O, "<>空房招租中", E:E, "*分層*") > 0, "入住中", IF(COUNTIFS(N:N, N77, O:O, "空房招租中", E:E, "*分層*") > 0, "分層優先(隱藏)", "空房招租中") ) ) ) ) -> 入住中 | J77: 採光Cozy躺椅雅房 | K77: https://youtu.be/n_TEh6a0Z4Y | L77: =IF(AND(A77="", C77="", D77=""), "Z", "A") -> A | O77: =IF(AND(C77<>"", D77<>""), IF(COUNTIFS(sublease_contract!$C:$C, C77, sublease_contract!$D:$D, "*" & D77 & "*", sublease_contract!$G:$G, "<>已退租") = 0, "空房招租中", IF(COUNTIFS(sublease_contract!$C:$C, C77, sublease_contract!$D:$D, "*" & D77 & "*", sublease_contract!$G:$G, "<>已退租", sublease_contract!$N:$N, ">" & (TODAY()+20)) > 0, "入住中", IF(COUNTIFS(sublease_contract!$C:$C, C77, sublease_contract!$D:$D, "*" & D77 & "*", sublease_contract!$G:$G, "<>已退租", sublease_contract!$N:$N, ">=" & TODAY(), sublease_contract!$N:$N, "<=" & (TODAY()+20)) > 0, MINIFS(sublease_contract!$N:$N, sublease_contract!$C:$C, C77, sublease_contract!$D:$D, "*" & D77 & "*", sublease_contract!$G:$G, "<>已退租", sublease_contract!$N:$N, ">=" & TODAY(), sublease_contract!$N:$N, "<=" & (TODAY()+20)), "入住中"))), "") -> 入住中
A78: {=IFERROR( INDEX(big_rental_contract!A:A, MATCH(C78, big_rental_contract!F:F, 0)), "" )} -> A0016 | B78: RL00076 | C78: 內湖CityLink | D78: B | E78: 分租雅房 | F78: 無 | G78: 9.29 | H78: 12000 | I78: =IF(O78<>"空房招租中", O78, IF(N78="", "空房招租中", IF(ISNUMBER(SEARCH("分層", E78)), IF(COUNTIFS(N:N, N78, O:O, "<>空房招租中") > 0, "入住中", "空房招租中"), IF(COUNTIFS(N:N, N78, O:O, "<>空房招租中", E:E, "*分層*") > 0, "入住中", IF(COUNTIFS(N:N, N78, O:O, "空房招租中", E:E, "*分層*") > 0, "分層優先(隱藏)", "空房招租中") ) ) ) ) -> 入住中 | J78: 舒適精緻雅房 | K78: https://youtu.be/ncfVbrE2o2s | L78: =IF(AND(A78="", C78="", D78=""), "Z", "A") -> A | O78: =IF(AND(C78<>"", D78<>""), IF(COUNTIFS(sublease_contract!$C:$C, C78, sublease_contract!$D:$D, "*" & D78 & "*", sublease_contract!$G:$G, "<>已退租") = 0, "空房招租中", IF(COUNTIFS(sublease_contract!$C:$C, C78, sublease_contract!$D:$D, "*" & D78 & "*", sublease_contract!$G:$G, "<>已退租", sublease_contract!$N:$N, ">" & (TODAY()+20)) > 0, "入住中", IF(COUNTIFS(sublease_contract!$C:$C, C78, sublease_contract!$D:$D, "*" & D78 & "*", sublease_contract!$G:$G, "<>已退租", sublease_contract!$N:$N, ">=" & TODAY(), sublease_contract!$N:$N, "<=" & (TODAY()+20)) > 0, MINIFS(sublease_contract!$N:$N, sublease_contract!$C:$C, C78, sublease_contract!$D:$D, "*" & D78 & "*", sublease_contract!$G:$G, "<>已退租", sublease_contract!$N:$N, ">=" & TODAY(), sublease_contract!$N:$N, "<=" & (TODAY()+20)), "入住中"))), "") -> 入住中
A79: {=IFERROR( INDEX(big_rental_contract!A:A, MATCH(C79, big_rental_contract!F:F, 0)), "" )} -> A0016 | B79: RL00077 | C79: 內湖CityLink | D79: C | E79: 分租雅房 | F79: 無 | G79: 9.91 | H79: 12500 | I79: =IF(O79<>"空房招租中", O79, IF(N79="", "空房招租中", IF(ISNUMBER(SEARCH("分層", E79)), IF(COUNTIFS(N:N, N79, O:O, "<>空房招租中") > 0, "入住中", "空房招租中"), IF(COUNTIFS(N:N, N79, O:O, "<>空房招租中", E:E, "*分層*") > 0, "入住中", IF(COUNTIFS(N:N, N79, O:O, "空房招租中", E:E, "*分層*") > 0, "分層優先(隱藏)", "空房招租中") ) ) ) ) -> 入住中 | J79: 全實心牆經典房 | K79: https://youtu.be/nYCGsW03IBg | L79: =IF(AND(A79="", C79="", D79=""), "Z", "A") -> A | O79: =IF(AND(C79<>"", D79<>""), IF(COUNTIFS(sublease_contract!$C:$C, C79, sublease_contract!$D:$D, "*" & D79 & "*", sublease_contract!$G:$G, "<>已退租") = 0, "空房招租中", IF(COUNTIFS(sublease_contract!$C:$C, C79, sublease_contract!$D:$D, "*" & D79 & "*", sublease_contract!$G:$G, "<>已退租", sublease_contract!$N:$N, ">" & (TODAY()+20)) > 0, "入住中", IF(COUNTIFS(sublease_contract!$C:$C, C79, sublease_contract!$D:$D, "*" & D79 & "*", sublease_contract!$G:$G, "<>已退租", sublease_contract!$N:$N, ">=" & TODAY(), sublease_contract!$N:$N, "<=" & (TODAY()+20)) > 0, MINIFS(sublease_contract!$N:$N, sublease_contract!$C:$C, C79, sublease_contract!$D:$D, "*" & D79 & "*", sublease_contract!$G:$G, "<>已退租", sublease_contract!$N:$N, ">=" & TODAY(), sublease_contract!$N:$N, "<=" & (TODAY()+20)), "入住中"))), "") -> 入住中
A80: {=IFERROR( INDEX(big_rental_contract!A:A, MATCH(C80, big_rental_contract!F:F, 0)), "" )} -> A0016 | B80: RL00078 | C80: 內湖CityLink | D80: D | E80: 分租雅房 | F80: 無 | G80: 10.37 | H80: 12500 | I80: =IF(O80<>"空房招租中", O80, IF(N80="", "空房招租中", IF(ISNUMBER(SEARCH("分層", E80)), IF(COUNTIFS(N:N, N80, O:O, "<>空房招租中") > 0, "入住中", "空房招租中"), IF(COUNTIFS(N:N, N80, O:O, "<>空房招租中", E:E, "*分層*") > 0, "入住中", IF(COUNTIFS(N:N, N80, O:O, "空房招租中", E:E, "*分層*") > 0, "分層優先(隱藏)", "空房招租中") ) ) ) ) -> 入住中 | J80: 方正格局雙窗房 | K80: https://youtube.com/shorts/5HVt4A5vjL8?feature=share | L80: =IF(AND(A80="", C80="", D80=""), "Z", "A") -> A | O80: =IF(AND(C80<>"", D80<>""), IF(COUNTIFS(sublease_contract!$C:$C, C80, sublease_contract!$D:$D, "*" & D80 & "*", sublease_contract!$G:$G, "<>已退租") = 0, "空房招租中", IF(COUNTIFS(sublease_contract!$C:$C, C80, sublease_contract!$D:$D, "*" & D80 & "*", sublease_contract!$G:$G, "<>已退租", sublease_contract!$N:$N, ">" & (TODAY()+20)) > 0, "入住中", IF(COUNTIFS(sublease_contract!$C:$C, C80, sublease_contract!$D:$D, "*" & D80 & "*", sublease_contract!$G:$G, "<>已退租", sublease_contract!$N:$N, ">=" & TODAY(), sublease_contract!$N:$N, "<=" & (TODAY()+20)) > 0, MINIFS(sublease_contract!$N:$N, sublease_contract!$C:$C, C80, sublease_contract!$D:$D, "*" & D80 & "*", sublease_contract!$G:$G, "<>已退租", sublease_contract!$N:$N, ">=" & TODAY(), sublease_contract!$N:$N, "<=" & (TODAY()+20)), "入住中"))), "") -> 入住中
A81: {=IFERROR( INDEX(big_rental_contract!A:A, MATCH(C81, big_rental_contract!F:F, 0)), "" )} -> A0016 | B81: RL00079 | C81: 內湖CityLink | D81: E | E81: 分租雅房 | F81: 無 | G81: 8.73 | H81: 13300 | I81: =IF(O81<>"空房招租中", O81, IF(N81="", "空房招租中", IF(ISNUMBER(SEARCH("分層", E81)), IF(COUNTIFS(N:N, N81, O:O, "<>空房招租中") > 0, "入住中", "空房招租中"), IF(COUNTIFS(N:N, N81, O:O, "<>空房招租中", E:E, "*分層*") > 0, "入住中", IF(COUNTIFS(N:N, N81, O:O, "空房招租中", E:E, "*分層*") > 0, "分層優先(隱藏)", "空房招租中") ) ) ) ) -> 入住中 | J81: 雙面採光開窗呼吸雅房 | K81: https://youtu.be/crA7sh3T0rk | L81: =IF(AND(A81="", C81="", D81=""), "Z", "A") -> A | O81: =IF(AND(C81<>"", D81<>""), IF(COUNTIFS(sublease_contract!$C:$C, C81, sublease_contract!$D:$D, "*" & D81 & "*", sublease_contract!$G:$G, "<>已退租") = 0, "空房招租中", IF(COUNTIFS(sublease_contract!$C:$C, C81, sublease_contract!$D:$D, "*" & D81 & "*", sublease_contract!$G:$G, "<>已退租", sublease_contract!$N:$N, ">" & (TODAY()+20)) > 0, "入住中", IF(COUNTIFS(sublease_contract!$C:$C, C81, sublease_contract!$D:$D, "*" & D81 & "*", sublease_contract!$G:$G, "<>已退租", sublease_contract!$N:$N, ">=" & TODAY(), sublease_contract!$N:$N, "<=" & (TODAY()+20)) > 0, MINIFS(sublease_contract!$N:$N, sublease_contract!$C:$C, C81, sublease_contract!$D:$D, "*" & D81 & "*", sublease_contract!$G:$G, "<>已退租", sublease_contract!$N:$N, ">=" & TODAY(), sublease_contract!$N:$N, "<=" & (TODAY()+20)), "入住中"))), "") -> 入住中
A82: {=IFERROR( INDEX(big_rental_contract!A:A, MATCH(C82, big_rental_contract!F:F, 0)), "" )} -> A0016 | B82: RL00080 | C82: 內湖CityLink | D82: F | E82: 分租雅房 | F82: 無 | G82: 8.73 | H82: 13300 | I82: =IF(O82<>"空房招租中", O82, IF(N82="", "空房招租中", IF(ISNUMBER(SEARCH("分層", E82)), IF(COUNTIFS(N:N, N82, O:O, "<>空房招租中") > 0, "入住中", "空房招租中"), IF(COUNTIFS(N:N, N82, O:O, "<>空房招租中", E:E, "*分層*") > 0, "入住中", IF(COUNTIFS(N:N, N82, O:O, "空房招租中", E:E, "*分層*") > 0, "分層優先(隱藏)", "空房招租中") ) ) ) ) -> 入住中 | J82: 方正採光雅房 | K82: https://youtu.be/Y_GV-Qa8PPg | L82: =IF(AND(A82="", C82="", D82=""), "Z", "A") -> A | O82: =IF(AND(C82<>"", D82<>""), IF(COUNTIFS(sublease_contract!$C:$C, C82, sublease_contract!$D:$D, "*" & D82 & "*", sublease_contract!$G:$G, "<>已退租") = 0, "空房招租中", IF(COUNTIFS(sublease_contract!$C:$C, C82, sublease_contract!$D:$D, "*" & D82 & "*", sublease_contract!$G:$G, "<>已退租", sublease_contract!$N:$N, ">" & (TODAY()+20)) > 0, "入住中", IF(COUNTIFS(sublease_contract!$C:$C, C82, sublease_contract!$D:$D, "*" & D82 & "*", sublease_contract!$G:$G, "<>已退租", sublease_contract!$N:$N, ">=" & TODAY(), sublease_contract!$N:$N, "<=" & (TODAY()+20)) > 0, MINIFS(sublease_contract!$N:$N, sublease_contract!$C:$C, C82, sublease_contract!$D:$D, "*" & D82 & "*", sublease_contract!$G:$G, "<>已退租", sublease_contract!$N:$N, ">=" & TODAY(), sublease_contract!$N:$N, "<=" & (TODAY()+20)), "入住中"))), "") -> 入住中
A83: {=IFERROR( INDEX(big_rental_contract!A:A, MATCH(C83, big_rental_contract!F:F, 0)), "" )} -> A0001 | B83: RL00083 | C83: 永春四號 | D83: 兩房 | E83: 分層出租 | F83: 頂加 | G83: 65.09 | H83: 33000 | I83: =IF(O83<>"空房招租中", O83, IF(N83="", "空房招租中", IF(ISNUMBER(SEARCH("分層", E83)), IF(COUNTIFS(N:N, N83, O:O, "<>空房招租中") > 0, "入住中", "空房招租中"), IF(COUNTIFS(N:N, N83, O:O, "<>空房招租中", E:E, "*分層*") > 0, "入住中", IF(COUNTIFS(N:N, N83, O:O, "空房招租中", E:E, "*分層*") > 0, "分層優先(隱藏)", "空房招租中") ) ) ) ) -> 入住中 | J83: 雙面大採光兩房一廳大陽台頂加 | K83: https://youtu.be/xwtOSmCtkFk | L83: =IF(AND(A83="", C83="", D83=""), "Z", "A") -> A | M83: 無 | O83: =IF(AND(C83<>"", D83<>""), IF(COUNTIFS(sublease_contract!$C:$C, C83, sublease_contract!$D:$D, "*" & D83 & "*", sublease_contract!$G:$G, "<>已退租") = 0, "空房招租中", IF(COUNTIFS(sublease_contract!$C:$C, C83, sublease_contract!$D:$D, "*" & D83 & "*", sublease_contract!$G:$G, "<>已退租", sublease_contract!$N:$N, ">" & (TODAY()+20)) > 0, "入住中", IF(COUNTIFS(sublease_contract!$C:$C, C83, sublease_contract!$D:$D, "*" & D83 & "*", sublease_contract!$G:$G, "<>已退租", sublease_contract!$N:$N, ">=" & TODAY(), sublease_contract!$N:$N, "<=" & (TODAY()+20)) > 0, MINIFS(sublease_contract!$N:$N, sublease_contract!$C:$C, C83, sublease_contract!$D:$D, "*" & D83 & "*", sublease_contract!$G:$G, "<>已退租", sublease_contract!$N:$N, ">=" & TODAY(), sublease_contract!$N:$N, "<=" & (TODAY()+20)), "入住中"))), "") -> 入住中
A84: {=IFERROR( INDEX(big_rental_contract!A:A, MATCH(C84, big_rental_contract!F:F, 0)), "" )} -> A0005 | B84: RL00084 | C84: 北醫醫師府 | D84: 兩房 | E84: 分層出租 | F84: 頂加 | G84: 27.6 | H84: 29600 | I84: =IF(O84<>"空房招租中", O84, IF(N84="", "空房招租中", IF(ISNUMBER(SEARCH("分層", E84)), IF(COUNTIFS(N:N, N84, O:O, "<>空房招租中") > 0, "入住中", "空房招租中"), IF(COUNTIFS(N:N, N84, O:O, "<>空房招租中", E:E, "*分層*") > 0, "入住中", IF(COUNTIFS(N:N, N84, O:O, "空房招租中", E:E, "*分層*") > 0, "分層優先(隱藏)", "空房招租中") ) ) ) ) -> 入住中 | J84: 兩房一廳 - 大採光超多收納開窗賞101夜景頂加 | K84: https://youtu.be/yGleqHhSkqU | L84: =IF(AND(A84="", C84="", D84=""), "Z", "A") -> A | M84: 無 | N84: Group_Top_01 | O84: =IF(AND(C84<>"", D84<>""), IF(COUNTIFS(sublease_contract!$C:$C, C84, sublease_contract!$D:$D, "*" & D84 & "*", sublease_contract!$G:$G, "<>已退租") = 0, "空房招租中", IF(COUNTIFS(sublease_contract!$C:$C, C84, sublease_contract!$D:$D, "*" & D84 & "*", sublease_contract!$G:$G, "<>已退租", sublease_contract!$N:$N, ">" & (TODAY()+20)) > 0, "入住中", IF(COUNTIFS(sublease_contract!$C:$C, C84, sublease_contract!$D:$D, "*" & D84 & "*", sublease_contract!$G:$G, "<>已退租", sublease_contract!$N:$N, ">=" & TODAY(), sublease_contract!$N:$N, "<=" & (TODAY()+20)) > 0, MINIFS(sublease_contract!$N:$N, sublease_contract!$C:$C, C84, sublease_contract!$D:$D, "*" & D84 & "*", sublease_contract!$G:$G, "<>已退租", sublease_contract!$N:$N, ">=" & TODAY(), sublease_contract!$N:$N, "<=" & (TODAY()+20)), "入住中"))), "") -> 空房招租中
A85: {=IFERROR( INDEX(big_rental_contract!A:A, MATCH(C85, big_rental_contract!F:F, 0)), "" )} -> A0013 | B85: RL00085 | C85: 行天宮夏野良栗 | D85: 兩房 | E85: 分層出租 | F85: 頂加 | G85: 27.04 | H85: 27800 | I85: =IF(O85<>"空房招租中", O85, IF(N85="", "空房招租中", IF(ISNUMBER(SEARCH("分層", E85)), IF(COUNTIFS(N:N, N85, O:O, "<>空房招租中") > 0, "入住中", "空房招租中"), IF(COUNTIFS(N:N, N85, O:O, "<>空房招租中", E:E, "*分層*") > 0, "入住中", IF(COUNTIFS(N:N, N85, O:O, "空房招租中", E:E, "*分層*") > 0, "分層優先(隱藏)", "空房招租中") ) ) ) ) -> 入住中 | J85: 兩房一廳 - 行天宮站2分鐘雙面採光大客廳頂加 | K85: https://youtu.be/ZscsdId_Mg8 | L85: =IF(AND(A85="", C85="", D85=""), "Z", "A") -> A | M85: 無 | N85: Group_Top_02 | O85: =IF(AND(C85<>"", D85<>""), IF(COUNTIFS(sublease_contract!$C:$C, C85, sublease_contract!$D:$D, "*" & D85 & "*", sublease_contract!$G:$G, "<>已退租") = 0, "空房招租中", IF(COUNTIFS(sublease_contract!$C:$C, C85, sublease_contract!$D:$D, "*" & D85 & "*", sublease_contract!$G:$G, "<>已退租", sublease_contract!$N:$N, ">" & (TODAY()+20)) > 0, "入住中", IF(COUNTIFS(sublease_contract!$C:$C, C85, sublease_contract!$D:$D, "*" & D85 & "*", sublease_contract!$G:$G, "<>已退租", sublease_contract!$N:$N, ">=" & TODAY(), sublease_contract!$N:$N, "<=" & (TODAY()+20)) > 0, MINIFS(sublease_contract!$N:$N, sublease_contract!$C:$C, C85, sublease_contract!$D:$D, "*" & D85 & "*", sublease_contract!$G:$G, "<>已退租", sublease_contract!$N:$N, ">=" & TODAY(), sublease_contract!$N:$N, "<=" & (TODAY()+20)), "入住中"))), "") -> 入住中
A86: {=IFERROR( INDEX(big_rental_contract!A:A, MATCH(C86, big_rental_contract!F:F, 0)), "" )} -> A0014 | B86: RL00086 | C86: 中山北Feli家 | D86: 兩房 | E86: 分層出租 | F86: 頂加 | G86: 19.57 | H86: 30000 | I86: =IF(O86<>"空房招租中", O86, IF(N86="", "空房招租中", IF(ISNUMBER(SEARCH("分層", E86)), IF(COUNTIFS(N:N, N86, O:O, "<>空房招租中") > 0, "入住中", "空房招租中"), IF(COUNTIFS(N:N, N86, O:O, "<>空房招租中", E:E, "*分層*") > 0, "入住中", IF(COUNTIFS(N:N, N86, O:O, "空房招租中", E:E, "*分層*") > 0, "分層優先(隱藏)", "空房招租中") ) ) ) ) -> 入住中 | J86: 兩房一廳 - 天母核心大採光超大客廳頂加 | K86: https://youtu.be/TJK-1_1QY_k?si=VSoka00YRegdQaRX | L86: =IF(AND(A86="", C86="", D86=""), "Z", "A") -> A | M86: 無 | N86: Group_Top_03 | O86: =IF(AND(C86<>"", D86<>""), IF(COUNTIFS(sublease_contract!$C:$C, C86, sublease_contract!$D:$D, "*" & D86 & "*", sublease_contract!$G:$G, "<>已退租") = 0, "空房招租中", IF(COUNTIFS(sublease_contract!$C:$C, C86, sublease_contract!$D:$D, "*" & D86 & "*", sublease_contract!$G:$G, "<>已退租", sublease_contract!$N:$N, ">" & (TODAY()+20)) > 0, "入住中", IF(COUNTIFS(sublease_contract!$C:$C, C86, sublease_contract!$D:$D, "*" & D86 & "*", sublease_contract!$G:$G, "<>已退租", sublease_contract!$N:$N, ">=" & TODAY(), sublease_contract!$N:$N, "<=" & (TODAY()+20)) > 0, MINIFS(sublease_contract!$N:$N, sublease_contract!$C:$C, C86, sublease_contract!$D:$D, "*" & D86 & "*", sublease_contract!$G:$G, "<>已退租", sublease_contract!$N:$N, ">=" & TODAY(), sublease_contract!$N:$N, "<=" & (TODAY()+20)), "入住中"))), "") -> 空房招租中
A87: A0017 | B87: RL00087 | C87: 天母搜狗 | D87: A | E87: 分租雅房 | F87: 無 | G87: 13.59 | H87: 13800 | I87: =IF(O87<>"空房招租中", O87, IF(N87="", "空房招租中", IF(ISNUMBER(SEARCH("分層", E87)), IF(COUNTIFS(N:N, N87, O:O, "<>空房招租中") > 0, "入住中", "空房招租中"), IF(COUNTIFS(N:N, N87, O:O, "<>空房招租中", E:E, "*分層*") > 0, "入住中", IF(COUNTIFS(N:N, N87, O:O, "空房招租中", E:E, "*分層*") > 0, "分層優先(隱藏)", "空房招租中") ) ) ) ) -> 空房招租中 | J87: 天母搜狗｜類套房規格(兩房一衛)｜優質採光A房 | K87: https://youtu.be/vA8Z0Oh0xNE | L87: =IF(AND(A87="", C87="", D87=""), "Z", "A") -> A | O87: =IF(AND(C87<>"", D87<>""), IF(COUNTIFS(sublease_contract!$C:$C, C87, sublease_contract!$D:$D, "*" & D87 & "*", sublease_contract!$G:$G, "<>已退租") = 0, "空房招租中", IF(COUNTIFS(sublease_contract!$C:$C, C87, sublease_contract!$D:$D, "*" & D87 & "*", sublease_contract!$G:$G, "<>已退租", sublease_contract!$N:$N, ">" & (TODAY()+20)) > 0, "入住中", IF(COUNTIFS(sublease_contract!$C:$C, C87, sublease_contract!$D:$D, "*" & D87 & "*", sublease_contract!$G:$G, "<>已退租", sublease_contract!$N:$N, ">=" & TODAY(), sublease_contract!$N:$N, "<=" & (TODAY()+20)) > 0, MINIFS(sublease_contract!$N:$N, sublease_contract!$C:$C, C87, sublease_contract!$D:$D, "*" & D87 & "*", sublease_contract!$G:$G, "<>已退租", sublease_contract!$N:$N, ">=" & TODAY(), sublease_contract!$N:$N, "<=" & (TODAY()+20)), "入住中"))), "") -> 空房招租中
A88: A0017 | B88: RL00088 | C88: 天母搜狗 | D88: B | E88: 分租雅房 | F88: 無 | G88: 16.56 | H88: 15400 | I88: =IF(O88<>"空房招租中", O88, IF(N88="", "空房招租中", IF(ISNUMBER(SEARCH("分層", E88)), IF(COUNTIFS(N:N, N88, O:O, "<>空房招租中") > 0, "入住中", "空房招租中"), IF(COUNTIFS(N:N, N88, O:O, "<>空房招租中", E:E, "*分層*") > 0, "入住中", IF(COUNTIFS(N:N, N88, O:O, "空房招租中", E:E, "*分層*") > 0, "分層優先(隱藏)", "空房招租中") ) ) ) ) -> 空房招租中 | J88: 天母搜狗｜類套房規格(兩房一衛)｜採光大B房 | K88: https://youtu.be/vA8Z0Oh0xNE | L88: =IF(AND(A88="", C88="", D88=""), "Z", "A") -> A | O88: =IF(AND(C88<>"", D88<>""), IF(COUNTIFS(sublease_contract!$C:$C, C88, sublease_contract!$D:$D, "*" & D88 & "*", sublease_contract!$G:$G, "<>已退租") = 0, "空房招租中", IF(COUNTIFS(sublease_contract!$C:$C, C88, sublease_contract!$D:$D, "*" & D88 & "*", sublease_contract!$G:$G, "<>已退租", sublease_contract!$N:$N, ">" & (TODAY()+20)) > 0, "入住中", IF(COUNTIFS(sublease_contract!$C:$C, C88, sublease_contract!$D:$D, "*" & D88 & "*", sublease_contract!$G:$G, "<>已退租", sublease_contract!$N:$N, ">=" & TODAY(), sublease_contract!$N:$N, "<=" & (TODAY()+20)) > 0, MINIFS(sublease_contract!$N:$N, sublease_contract!$C:$C, C88, sublease_contract!$D:$D, "*" & D88 & "*", sublease_contract!$G:$G, "<>已退租", sublease_contract!$N:$N, ">=" & TODAY(), sublease_contract!$N:$N, "<=" & (TODAY()+20)), "入住中"))), "") -> 空房招租中
A89: A0017 | B89: RL00089 | C89: 天母搜狗 | D89: C | E89: 分租雅房 | F89: 無 | G89: 13.05 | H89: 14000 | I89: =IF(O89<>"空房招租中", O89, IF(N89="", "空房招租中", IF(ISNUMBER(SEARCH("分層", E89)), IF(COUNTIFS(N:N, N89, O:O, "<>空房招租中") > 0, "入住中", "空房招租中"), IF(COUNTIFS(N:N, N89, O:O, "<>空房招租中", E:E, "*分層*") > 0, "入住中", IF(COUNTIFS(N:N, N89, O:O, "空房招租中", E:E, "*分層*") > 0, "分層優先(隱藏)", "空房招租中") ) ) ) ) -> 空房招租中 | J89: 天母搜狗｜類套房規格(兩房一衛)｜採光C房 | K89: https://youtube.com/shorts/L2QykZ_zdyA | L89: =IF(AND(A89="", C89="", D89=""), "Z", "A") -> A | O89: =IF(AND(C89<>"", D89<>""), IF(COUNTIFS(sublease_contract!$C:$C, C89, sublease_contract!$D:$D, "*" & D89 & "*", sublease_contract!$G:$G, "<>已退租") = 0, "空房招租中", IF(COUNTIFS(sublease_contract!$C:$C, C89, sublease_contract!$D:$D, "*" & D89 & "*", sublease_contract!$G:$G, "<>已退租", sublease_contract!$N:$N, ">" & (TODAY()+20)) > 0, "入住中", IF(COUNTIFS(sublease_contract!$C:$C, C89, sublease_contract!$D:$D, "*" & D89 & "*", sublease_contract!$G:$G, "<>已退租", sublease_contract!$N:$N, ">=" & TODAY(), sublease_contract!$N:$N, "<=" & (TODAY()+20)) > 0, MINIFS(sublease_contract!$N:$N, sublease_contract!$C:$C, C89, sublease_contract!$D:$D, "*" & D89 & "*", sublease_contract!$G:$G, "<>已退租", sublease_contract!$N:$N, ">=" & TODAY(), sublease_contract!$N:$N, "<=" & (TODAY()+20)), "入住中"))), "") -> 空房招租中
A90: A0017 | B90: RL00090 | C90: 天母搜狗 | D90: D | E90: 分租雅房 | F90: 無 | G90: 11.04 | H90: 14000 | I90: =IF(O90<>"空房招租中", O90, IF(N90="", "空房招租中", IF(ISNUMBER(SEARCH("分層", E90)), IF(COUNTIFS(N:N, N90, O:O, "<>空房招租中") > 0, "入住中", "空房招租中"), IF(COUNTIFS(N:N, N90, O:O, "<>空房招租中", E:E, "*分層*") > 0, "入住中", IF(COUNTIFS(N:N, N90, O:O, "空房招租中", E:E, "*分層*") > 0, "分層優先(隱藏)", "空房招租中") ) ) ) ) -> 空房招租中 | J90: 天母搜狗｜類套房規格(兩房一衛)｜採光D房 | K90: https://youtube.com/shorts/L2QykZ_zdyA | L90: =IF(AND(A90="", C90="", D90=""), "Z", "A") -> A | O90: =IF(AND(C90<>"", D90<>""), IF(COUNTIFS(sublease_contract!$C:$C, C90, sublease_contract!$D:$D, "*" & D90 & "*", sublease_contract!$G:$G, "<>已退租") = 0, "空房招租中", IF(COUNTIFS(sublease_contract!$C:$C, C90, sublease_contract!$D:$D, "*" & D90 & "*", sublease_contract!$G:$G, "<>已退租", sublease_contract!$N:$N, ">" & (TODAY()+20)) > 0, "入住中", IF(COUNTIFS(sublease_contract!$C:$C, C90, sublease_contract!$D:$D, "*" & D90 & "*", sublease_contract!$G:$G, "<>已退租", sublease_contract!$N:$N, ">=" & TODAY(), sublease_contract!$N:$N, "<=" & (TODAY()+20)) > 0, MINIFS(sublease_contract!$N:$N, sublease_contract!$C:$C, C90, sublease_contract!$D:$D, "*" & D90 & "*", sublease_contract!$G:$G, "<>已退租", sublease_contract!$N:$N, ">=" & TODAY(), sublease_contract!$N:$N, "<=" & (TODAY()+20)), "入住中"))), "") -> 空房招租中
A91: A0017 | B91: RL00091 | C91: 天母搜狗 | D91: E | E91: 分租雅房 | F91: 無 | G91: 12.14 | H91: 12800 | I91: =IF(O91<>"空房招租中", O91, IF(N91="", "空房招租中", IF(ISNUMBER(SEARCH("分層", E91)), IF(COUNTIFS(N:N, N91, O:O, "<>空房招租中") > 0, "入住中", "空房招租中"), IF(COUNTIFS(N:N, N91, O:O, "<>空房招租中", E:E, "*分層*") > 0, "入住中", IF(COUNTIFS(N:N, N91, O:O, "空房招租中", E:E, "*分層*") > 0, "分層優先(隱藏)", "空房招租中") ) ) ) ) -> 空房招租中 | J91: 天母搜狗｜採光實心牆E房 | K91: https://youtube.com/shorts/iNf0X3UT8NM | L91: =IF(AND(A91="", C91="", D91=""), "Z", "A") -> A | O91: =IF(AND(C91<>"", D91<>""), IF(COUNTIFS(sublease_contract!$C:$C, C91, sublease_contract!$D:$D, "*" & D91 & "*", sublease_contract!$G:$G, "<>已退租") = 0, "空房招租中", IF(COUNTIFS(sublease_contract!$C:$C, C91, sublease_contract!$D:$D, "*" & D91 & "*", sublease_contract!$G:$G, "<>已退租", sublease_contract!$N:$N, ">" & (TODAY()+20)) > 0, "入住中", IF(COUNTIFS(sublease_contract!$C:$C, C91, sublease_contract!$D:$D, "*" & D91 & "*", sublease_contract!$G:$G, "<>已退租", sublease_contract!$N:$N, ">=" & TODAY(), sublease_contract!$N:$N, "<=" & (TODAY()+20)) > 0, MINIFS(sublease_contract!$N:$N, sublease_contract!$C:$C, C91, sublease_contract!$D:$D, "*" & D91 & "*", sublease_contract!$G:$G, "<>已退租", sublease_contract!$N:$N, ">=" & TODAY(), sublease_contract!$N:$N, "<=" & (TODAY()+20)), "入住中"))), "") -> 空房招租中
L92: =IF(AND(A92="", C92="", D92=""), "Z", "A") -> Z
L93: =IF(AND(A93="", C93="", D93=""), "Z", "A") -> Z
L94: =IF(AND(A94="", C94="", D94=""), "Z", "A") -> Z
L95: =IF(AND(A95="", C95="", D95=""), "Z", "A") -> Z
L96: =IF(AND(A96="", C96="", D96=""), "Z", "A") -> Z
L97: =IF(AND(A97="", C97="", D97=""), "Z", "A") -> Z
L98: =IF(AND(A98="", C98="", D98=""), "Z", "A") -> Z
L99: =IF(AND(A99="", C99="", D99=""), "Z", "A") -> Z
L100: =IF(AND(A100="", C100="", D100=""), "Z", "A") -> Z
...

Sheet big_rental_contract
A1: id | B1: tax_reduction_applied | C1: file_archived | D1: auto_transfer | E1: system_registered | F1: property_name | G1: owner_name | H1: monthly_rent | I1: contract_signed_date | J1: contract_start_date | K1: contract_end_date | L1: city | M1: district | N1: address | O1: land_section | P1: land_number | Q1: building_number | R1: building_area_sqm | S1: living_room_count | T1: bathroom_count | U1: bedroom_count | V1: total_floors | W1: rented_floor | X1: rented_floor_cn | Y1: building_type | Z1: owner_id_number | AA1: owner_contact | AB1: remittance_account | AC1: secondary_remittance_account | AD1: contract_signed_date_minguo | AE1: contract_start_date_minguo | AF1: contract_end_date_minguo | AG1: case_number | AH1: phase1_rent_start_date | AI1: phase1_rent_amount | AJ1: phase2_rent_start_date | AK1: phase2_rent_amount | AL1: phase3_rent_start_date | AM1: phase3_rent_amount | AN1: phase4_rent_start_date | AO1: phase4_rent_amount | AP1: next_payment_date_estimated | AQ1: auto_transfer_last_date | AR1: transfer_date | AS1: transfer_amount_estimated | AT1: first_month_amount | AU1: last_payment_date | AV1: last_payment_amount | AW1: notes | AX1: tag | AY1: second_owner_name | AZ1: second_owner_id | BA1: third_owner_name | BB1: third_owner_id | BC1: Description | BD1: 垃圾代收/樓梯清潔/管理費 | BE1: public_area_video | BF1: full_description
A2: A0001 | B2: TRUE | C2: TRUE | D2: TRUE | E2: TRUE | F2: 永春四號 | G2: 郭宗仁 | H2: 34000 | I2: 45212 | J2: 45212 | K2: 48883 | L2: 臺北市 | M2: 信義區 | N2: 忠孝東路五段466號四樓 | O2: 信義段一小段 | P2: 0104-0000 | Q2: 00791000 | R2: 95.4 | S2: 2 | T2: 1 | U2: 4 | V2: 4 | W2: 4 | X2: 四層 | Y2: 公寓(無電梯) | Z2: F122308421 | AA2: 0987249595 | AB2: (012)00620168284509 0000721168746295 | AC2: (012)00721168746295 | AD2: =if(ISBLANK(I2),, YEAR(I2)-1911&TEXT(I2,"mmdd")) -> 1121013 | AE2: =if(ISBLANK(J2),, YEAR(J2)-1911&TEXT(J2,"mmdd")) -> 1121013 | AF2: =if(ISBLANK(K2),, YEAR(K2)-1911&TEXT(K2,"mmdd")) -> 1221031 | AG2: BAA9405318211240143 | AH2: 45212 | AI2: 34000 | AJ2: 46096 | AK2: 54000 | AP2: 台銀在 台幣簡易轉帳 歷史紀錄選用 可以一次"多選"設定 進入草稿後編輯 | AQ2: 2025.06.1 | AR2: 每個月一號給兩個帳戶 | AS2: 17000*2(雙帳號) | AX2: 貓狗企鵝 | AY2: 郭玟君 | AZ2: F228154223 | BC2: 📌租金包含: 網路費 📌押金: 2個月 📌仲介費: 免仲介費 📌租期: 可短租 📌能源費: 水、電、瓦斯依帳單 室友人頭均攤 🚶步行 1分鐘 7-11便利商店 1分鐘 康是美 1分鐘 捷運永春站 2分鐘 虎林街美食、虎林市場 3分鐘 壽司郎 🚲 YouBike 4分鐘ubike到 五分埔 5分鐘ubike到 饒河夜市 | BD2: 無 | BF2: 🚇永春站正樓上🚇, 到站就到家 󠀠 在繁忙的城市生活中，有什麼比每天返家更讓人舒適的呢？我們位於捷運站樓上，意味著當你到達站點，你已經回到了溫馨的家。 󠀠 居家辦公、下班累了想吃美食，6分鐘內的距離絕對不怕沒食物 1分鐘捷運到 信義商圈 2分鐘走路到 虎林街美食、虎林市場 3分鐘走路到 壽司郎 4分鐘ubike到 五分埔 5分鐘ubike到 饒河夜市 󠀠 臨時想買點東西, 10秒內步行即可到達便利商店&康是美. 󠀠 📌地點: 永春站 信義區 忠孝東路五段 四樓 公寓 📌格局: 【房型】公寓2層 4F & 5F → 4F 共生公寓 四房一衛一廳一廚一陽台 → 5F 兩房一衛一廳一廚一陽台 頂加 📌設備: 冷氣、雙人床、衣櫃、40吋以上電視、桌椅、洗衣機、冰箱、瓦斯爐、抽油煙機、熱水器、120M網路&WIFI 📌租金包含: 網路費
A3: A0002 | B3: TRUE | C3: TRUE | D3: TRUE | E3: TRUE | F3: 內湖秘境 | G3: 周佳慧 | H3: 45000 | I3: 45190 | J3: 45190 | K3: 48883 | L3: 臺北市 | M3: 內湖區 | N3: 內湖路一段47巷46號五樓 | O3: 西湖段二小段 | P3: 0439-0000 | Q3: 01432-000 | R3: 103.04 | S3: 1 | T3: 1 | U3: 5 | V3: 5 | W3: 5 | X3: 五層 | Y3: 公寓(無電梯) | Z3: A221172157 | AA3: 02-29671862 | AB3: 012/0000689168153048 700/03116810484843 810/6709177212 | AD3: =if(ISBLANK(I3),, YEAR(I3)-1911&TEXT(I3,"mmdd")) -> 1120921 | AE3: =if(ISBLANK(J3),, YEAR(J3)-1911&TEXT(J3,"mmdd")) -> 1120921 | AF3: =if(ISBLANK(K3),, YEAR(K3)-1911&TEXT(K3,"mmdd")) -> 1221031 | AG3: BAA9405318211231268 | AH3: 45190 | AI3: 45000 | AJ3: 47058 | AK3: 47000 | AO3: 47000 | AQ3: 2025.12.1 | AR3: 每個月1號 | AS3: 15000*3 | AX3: 鯰魚大大 | BC3: =====內 科 綠 樹 景 觀 房===== 與綠蔭共居 適合重視生活品質的你 💲󠀠垃圾代收 💲公共區清潔 💲1G超高速網路 =====歡 迎 申 請 租 金 補 貼===== 󠀠 󠀠 近美麗華 / 內科 / 內湖路一段 / 文湖街󠀠 劍南路站 / 騎車4MIN / 步行12MIN 西湖站 / 騎車5MIN / 步行16MIN 【房型】公寓2層 7雅 2衛 1廚 大露臺󠀠 󠀠 【租金包含】垃圾代收、公共區清潔、1G超高速網路費 【押金】2個月，租期1年起 【能源費】水、電、瓦斯依帳單 室友人頭均攤 【設備】3M生飲濾水器、冷氣、掀床床墊組、衣櫃、書桌椅、洗衣機*2、冰箱*2、餐桌、瓦斯爐、抽油煙機、熱水器、1G 網路 & WIFI 󠀠 󠀠 | BD3: Local廠商 放一樓 | BE3: https://youtu.be/o8CQn0wxxQQ | BF3: =====內 科 綠 樹 景 觀 房===== 󠀠 󠀠 與綠蔭共居 適合重視生活品質的你 💲󠀠垃圾代收 💲公共區清潔 💲1G超高速網路 =====歡 迎 申 請 租 金 補 貼===== 󠀠 󠀠 近美麗華 / 內科 / 內湖路一段 / 文湖街󠀠 劍南路站 / 騎車4MIN / 步行12MIN 西湖站 / 騎車5MIN / 步行16MIN 󠀠󠀠 雖然距離捷運要走一小段，但因為這樣的距離， 換到遠離塵囂的生活品質 󠀠 󠀠 【房型】公寓2層 7雅 2衛 1廚 大露臺 󠀠 󠀠 󠀠 󠀠 【租金包含】垃圾代收、公共區清潔、1G超高速網路費 【設備】3M生飲濾水器、冷氣、掀床床墊組、衣櫃、書桌椅、洗衣機*2、冰箱*2、餐桌、瓦斯爐、抽油煙機、熱水器、1G 網路 & WIFI
A4: A0003 | B4: TRUE | C4: TRUE | D4: TRUE | E4: TRUE | F4: 龍江229 | G4: 游為傑 | H4: 27000 | I4: 45264 | J4: 45264 | K4: 47087 | L4: 臺北市 | M4: 中山區 | N4: 龍江路229巷2之3號三樓 | O4: 長春段一小段 | P4: 0061-0000 | Q4: 01553-000 | R4: 89.42 | S4: 1 | T4: 2 | U4: 5 | V4: 4 | W4: 3 | X4: 三層 | Y4: 公寓(無電梯) | Z4: A124455973 | AA4: 0920488835 | AB4: 700-00021680019509 | AD4: =if(ISBLANK(I4),, YEAR(I4)-1911&TEXT(I4,"mmdd")) -> 1121204 | AE4: =if(ISBLANK(J4),, YEAR(J4)-1911&TEXT(J4,"mmdd")) -> 1121204 | AF4: =if(ISBLANK(K4),, YEAR(K4)-1911&TEXT(K4,"mmdd")) -> 1171130 | AG4: BAA9405318211240558 | AH4: 45264 | AI4: 27000 | AQ4: 2025.06.13 | AR4: 每個月1號 跟 15號 | AS4: 13500*2 | AU4: 47058 | AV4: 22830 | AX4: 貓狗企鵝 | BC4: 📌地點: 中山區 龍江路229巷 3樓 公寓 📌格局: 1廚1廳2陽台2衛浴 (4雅1套) 📌設備: 冷氣、單/雙人床、衣櫃、桌椅、蒸氣洗衣機、冰箱、瓦斯爐、抽油煙機、熱水器、濾水器、120M網路&WIFI 📌租金包含: 網路費、垃圾代收費 📌押金: 2個月 📌租期: 1年起 📌能源費: 水、電、瓦斯依帳單 室友人頭均攤 🚶步行 3分鐘走路到 台北大學 🚲 YouBike 3分鐘 Ubike到 錦州街美食區 3分鐘 Ubike到 中山國中捷運站 3分鐘 Ubike到 南京復興捷運站 4分鐘 Ubike到 行天宮捷運站 4分鐘 Ubike到 遼寧夜市 5分鐘 Ubike到 錢櫃松江 6分鐘 Ubike到 長春國賓影城 | BD4: 垃可 | BE4: https://youtube.com/shorts/p2uw-IupzaE?si=zpNopgBQCQ7OBNQx | BF4: 近台北大學, 寧靜優雅的書香環境. 黃線 綠線 棕線捷運 都不缺席, 無論你在台北哪個角落都能輕鬆回家.󠀠 󠀠 每個房間都有對外窗, 近9成設備皆是全新搬入.󠀠 󠀠 🚲 YouBike 3分鐘 Ubike到 錦州街美食區 3分鐘 Ubike到 中山國中捷運站 3分鐘 Ubike到 南京復興捷運站 4分鐘 Ubike到 行天宮捷運站 4分鐘 Ubike到 遼寧夜市 5分鐘 Ubike到 錢櫃松江 6分鐘 Ubike到 長春國賓影城 󠀠 󠀠 📌地點: 中山區 龍江路229巷 3樓 公寓 📌格局: 1廚1廳2陽台2衛浴 (4雅1套) 📌設備: 冷氣、單/雙人床、衣櫃、桌椅、蒸氣洗衣機、冰箱、瓦斯爐、抽油煙機、熱水器、濾水器、120M網路&WIFI 📌租金包含: 網路費、垃圾代收費
A5: A0004 | B5: TRUE | C5: TRUE | D5: TRUE | E5: TRUE | F5: 哈拉對面 | G5: 陳哲聰 | H5: 26000 | I5: 45306 | J5: 45307 | K5: 47133 | L5: 臺北市 | M5: 內湖區 | N5: 康寧路三段175號四樓 | O5: 東湖段二小段 | P5: 0027-0006 | Q5: 01658-000 | R5: 75.94 | S5: 1 | T5: 2 | U5: 4 | V5: 5 | W5: 4 | X5: 四層 | Y5: 公寓(無電梯) | Z5: A102252441 | AA5: 0918090027 | AB5: 807-15400400106659 | AD5: =if(ISBLANK(I5),, YEAR(I5)-1911&TEXT(I5,"mmdd")) -> 1130115 | AE5: =if(ISBLANK(J5),, YEAR(J5)-1911&TEXT(J5,"mmdd")) -> 1130116 | AF5: =if(ISBLANK(K5),, YEAR(K5)-1911&TEXT(K5,"mmdd")) -> 1180115 | AG5: BAA9405318211310081 | AH5: 45307 | AI5: 26000 | AQ5: 2025.06.1 | AR5: 每個月1號 跟 15號 | AS5: 13000*2 | AU5: 47088 | AX5: 貓狗企鵝 | BC5: 📌地點: 內湖區 康寧路三段17X號 4樓 公寓 📌格局: 1廚1廳 2陽台 2衛浴 (3雅1套) 📌設備: 冷氣、單/雙人床、衣櫃、桌椅、洗衣機、冰箱、瓦斯爐、抽油煙機、天然瓦斯、熱水器、濾水器、120M網路&WIFI 📌租金包含: 網路費、垃圾代收費 📌押金: 2個月 📌租期: 1年起 📌能源費: 水、電、瓦斯依帳單 室友人頭均攤 🚶步行 1分鐘 東湖立體停車場 3分鐘 麥當勞、星巴克、麵屋昕家、長生塩人 3分鐘 健身工廠 5分鐘 哈拉影城 | BD5: 垃圾代收跟樓梯清潔也是輪流收，頻率跟規則待確認 垃圾代收是900 樓梯清潔1500-1550 清運垃圾 廠商 0960785837 | BE5: https://youtu.be/UVZ39Ee_XhE | BF5: 位在哈拉影城正對面， 📌地點: 內湖區 康寧路三段17X號 4樓 公寓 📌格局: 1廚1廳 2陽台 2衛浴 (3雅1套) 📌設備: 冷氣、單/雙人床、衣櫃、桌椅、洗衣機、冰箱、瓦斯爐、抽油煙機、天然瓦斯、熱水器、濾水器、120M網路&WIFI 📌租金包含: 網路費、垃圾代收費 🚶步行 1分鐘 東湖立體停車場 3分鐘 麥當勞、星巴克、麵屋昕家、長生塩人 3分鐘 健身工廠 5分鐘 哈拉影城 5分鐘 騎車過橋到南港經貿園區 中信大樓 Lalaport 󠀠
A6: A0005 | B6: TRUE | C6: TRUE | D6: TRUE | E6: TRUE | F6: 北醫醫師府 | G6: 陳俊良 | H6: 25600 | I6: 45346 | J6: 45348 | K6: 47174 | L6: 臺北市 | M6: 信義區 | N6: 吳興街284巷36弄12號五樓 | O6: 吳興段二小段 | P6: 0569-0002 | Q6: 00568-000 | R6: 77.24 | S6: 1 | T6: 2 | U6: 4 | V6: 5 | W6: 5 | X6: 五層 | Y6: 公寓(無電梯) | Z6: J120062505 | AA6: 0975379075 | AB6: 700-03117680192128 | AD6: =if(ISBLANK(I6),, YEAR(I6)-1911&TEXT(I6,"mmdd")) -> 1130224 | AE6: =if(ISBLANK(J6),, YEAR(J6)-1911&TEXT(J6,"mmdd")) -> 1130226 | AF6: =if(ISBLANK(K6),, YEAR(K6)-1911&TEXT(K6,"mmdd")) -> 1180225 | AG6: BAA9405318211310299 | AH6: 45348 | AI6: 25600 | AQ6: 2025.06.1 | AR6: 每個月1號 跟 15號 | AS6: 12800*2 | AU6: 47119 | AX6: 貓狗企鵝 | BC6: 📌 地點: 台北市信義區吳興街284巷36弄Ｘ號 5樓 公寓 📌 格局: 1廚1廳 2陽台 2衛浴 (3雅1套) 📌 能源費: 水電依照台水台電💧💡帳單計算，沒有一度6,7,8元的問題，室友人頭均攤 📌 租金包含: 網路費、垃圾代收費 📌 押金: 2個月 📌 租期: 1年起 📌 設備: 冷氣、單/雙人床、衣櫃、桌椅、洗衣機、冰箱、瓦斯爐、抽油煙機、天然瓦斯、熱水器、濾水器、120M網路&Wi-Fi 🚲 YouBike 2分鐘到 北醫 🏥 2分鐘到 吳興街美食區 🍽️ 3分鐘到 麥當勞🍟、肯德基🍗、摩斯漢堡🍔 6分鐘到 信義商圈 6分鐘到 象山步道 6分鐘到 通化夜市 | BD6: 垃可 | BE6: https://youtube.com/shorts/K2bdVQRikDk?feature=share | BF6: 🚲 YouBike 2分鐘到 北醫 🏥 2分鐘到 吳興街美食區 🍽️ 3分鐘到 麥當勞🍟、肯德基🍗、摩斯漢堡🍔 6分鐘到 信義商圈 6分鐘到 象山步道 6分鐘到 通化夜市 󠀠 󠀠 󠀠 󠀠 📌 地點: 台北市信義區吳興街284巷36弄Ｘ號 5樓 公寓 📌 格局: 【房型】公寓2層 5F & 6F → 5F 共生公寓 1套 3雅 二衛一廳一廚二陽台 → 6F 兩房一衛一廳一廚二陽台 頂加 📌 租金包含: 網路費、垃圾代收費 📌 設備: 冷氣、單/雙人床、衣櫃、桌椅、洗衣機、冰箱、瓦斯爐、抽油煙機、天然瓦斯、熱水器、濾水器、120M網路&Wi-Fi 󠀠 󠀠
A7: A0006 | B7: TRUE | C7: TRUE | D7: TRUE | E7: TRUE | F7: 大湖山莊 | G7: 陳彩霞 | H7: 38800 | I7: 45382 | J7: 45383 | K7: 47208 | L7: 臺北市 | M7: 內湖區 | N7: 大湖山莊街219巷12號四樓 | O7: 大湖段二小段 | P7: 0003-0001 | Q7: 01872-000 | R7: 136.38 | S7: 2 | T7: 2 | U7: 5 | V7: 5 | W7: 4 | X7: 四層 | Y7: 公寓(無電梯) | Z7: A223691931 | AA7: 0936069224 | AB7: 053-117280005202 | AD7: =if(ISBLANK(I7),, YEAR(I7)-1911&TEXT(I7,"mmdd")) -> 1130331 | AE7: =if(ISBLANK(J7),, YEAR(J7)-1911&TEXT(J7,"mmdd")) -> 1130401 | AF7: =if(ISBLANK(K7),, YEAR(K7)-1911&TEXT(K7,"mmdd")) -> 1180331 | AG7: BAA9405318211310742 | AH7: 45383 | AI7: 38800 | AQ7: 2025.06.1 | AR7: 每個月1號 跟 15號 | AS7: 19400*2 | AU7: 47178 | AX7: 貓狗企鵝 | BC7: 📌 地點: 114台北市內湖區大湖山莊街219巷X號 4~6樓 公寓 📌 格局: 1廚1廳 3陽台 3衛浴 (6雅1套) 📌 能源費: 水電依照台水台電帳單計算 📌 租金包含: 網路費、垃圾代收費、定期公區清潔 📌 押金: 2個月 📌 租期: 1年起 📌 設備: 冷氣、單/雙人床、衣櫃、桌椅、滾筒洗脫烘洗衣機、冰箱、瓦斯爐、抽油煙機、天然瓦斯、熱水器、濾水器、1G網路&Wi-Fi 🚲 YouBike 1分鐘到 內湖大溝溪親水步道 1分鐘到 美聯社 1分鐘到 平價美食4.4顆星 2分鐘到 全聯 3分鐘到 大湖公園捷運站 | BD7: Local廠商 放一樓 | BE7: https://youtu.be/Rk2l4DeBJRg | BF7: 🚲 YouBike 1分鐘到 內湖大溝溪親水步道 1分鐘到 美聯社 1分鐘到 平價美食4.4顆星 2分鐘到 全聯 3分鐘到 大湖公園捷運站 󠀠 󠀠 我有1套6雅房，每間都是採光對外窗，空間很大適合練瑜伽 我離捷運站有一小段距離，但我的地理位置很清幽 #適合喜歡登山 #喜歡親近大自然 #機車族 #UBike族 󠀠 󠀠 📌 地點: 114台北市內湖區大湖山莊街219巷X號 4~6樓 公寓 📌 格局: 1廚1廳 3陽台 3衛浴 (6雅1套) 📌 租金包含: 網路費、垃圾代收費、定期公區清潔 📌 設備: 冷氣、單/雙人床、衣櫃、桌椅、滾筒洗脫烘洗衣機、冰箱、瓦斯爐、抽油煙機、天然瓦斯、熱水器、濾水器、1G網路&Wi-Fi
A8: A0007 | B8: TRUE | C8: TRUE | D8: TRUE | E8: TRUE | F8: 士林和豐 | G8: 楊政偉 | H8: 28800 | I8: 45465 | J8: 45474 | K8: 46599 | L8: 臺北市 | M8: 士林區 | N8: 和豐街31號三樓 | O8: 百齡段四小段 | P8: 0390-0000 | Q8: 41509-000 | R8: 123.48 | S8: 2 | T8: 2 | U8: 4 | V8: 5 | W8: 3 | X8: 三層 | Y8: 公寓(無電梯) | Z8: A124566588 | AA8: 0953578737 | AB8: 013-0000699513778744 | AD8: =if(ISBLANK(I8),, YEAR(I8)-1911&TEXT(I8,"mmdd")) -> 1130622 | AE8: =if(ISBLANK(J8),, YEAR(J8)-1911&TEXT(J8,"mmdd")) -> 1130701 | AF8: =if(ISBLANK(K8),, YEAR(K8)-1911&TEXT(K8,"mmdd")) -> 1160731 | AG8: BAA9405318211420436 | AH8: 45474 | AI8: 28800 | AQ8: 2025.12.1 | AR8: 每個月1號 跟 15號 | AS8: 14400*2 | AU8: 46082 | AX8: 鯰魚大大 | BC8: 📌 地點: 內湖路一段47巷xx號5樓 【房型】公寓2層 7雅 2衛 1廚 大露臺 󠀠 【租金包含】垃圾代收、公共區清潔、1G超高速網路費 【能源費】水、電、瓦斯依帳單 室友人頭均攤 【設備】3M生飲濾水器、冷氣、掀床床墊組、衣櫃、書桌椅、洗衣機*2、冰箱*2、餐桌、瓦斯爐、抽油煙機、熱水器、1G 網路 & WIFI 近美麗華 / 內科 / 內湖路一段 / 文湖街󠀠 劍南路站 / 騎車4MIN / 步行12MIN 西湖站 / 騎車5MIN / 步行16MI | BD8: 無 | BE8: https://youtube.com/shorts/AWKkpIiUcwE?si=M_-EwlIMUNGptSJz | BF8: ╔═════════╗ 🚶走路 1分鐘 街口小吃 2分鐘 傳統市場 3分鐘 便利商店 5分鐘 前港公園 5分鐘 百齡河濱 🚲 YouBike 3分鐘 捷運劍潭站 5分鐘 士林夜市 ╚═════════╝ 󠀠 📌地點: 劍潭 士林區和豐街 📌類別: 爬起來一點都不像3樓的三樓 📌房型: 3雅1套, 無暗房, 每間都有採光良好的對外窗 📌設備: 分離式冷氣、單人加大 / 雙人床、衣櫃、桌椅、洗衣機、冰箱、櫻花牌瓦斯爐、抽油煙機、莊頭北天然氣恆溫熱水器、120M網路&WIFI 📌租金包含: 網路費、樓梯間清潔費
A9: A0008 | B9: TRUE | C9: TRUE | D9: TRUE | E9: TRUE | F9: 南港站挑高宅 | G9: 林淑華 | H9: 36500 | I9: 45478 | J9: 45478 | K9: 49129 | L9: 臺北市 | M9: 南港區 | N9: 興中路44巷2弄9號一樓 | O9: 南港段一小段 | P9: 1187-0000 | Q9: 00516-000 | R9: 100.51 | S9: 2 | T9: 2 | U9: 5 | V9: 4 | W9: 1 | X9: 一層 | Y9: 公寓(無電梯) | Z9: F220678280 | AA9: 0922100017 | AB9: 004-107004358372 | AD9: =if(ISBLANK(I9),, YEAR(I9)-1911&TEXT(I9,"mmdd")) -> 1130705 | AE9: =if(ISBLANK(J9),, YEAR(J9)-1911&TEXT(J9,"mmdd")) -> 1130705 | AF9: =if(ISBLANK(K9),, YEAR(K9)-1911&TEXT(K9,"mmdd")) -> 1230704 | AG9: BAA9405318211330031 | AH9: 45478 | AI9: 36500 | AJ9: 48458 | AK9: 37560 | AO9: 37560 | AQ9: 2025.06.1 | AR9: 每個月1號 跟 15號 | AS9: 18250*2 | AU9: 49096 | AV9: 37500/2 | AX9: 貓狗企鵝 | AY9: 張嘉琪 | AZ9: A227599232 | BA9: 李海清 | BB9: T120938762 | BC9: 📌 地點: 115台北市南港區興中路44巷2弄X號1樓 公寓 📌 格局: 5房1廳2衛浴 📌 能源費: 水電依照台水台電帳單計算 📌 租金包含: 網路費、垃圾代收費 📌 押金: 2個月 📌 租期: 1年起 📌 設備: 冷氣、雙人床、衣櫃、桌椅、洗衣機、冰箱、桶裝瓦斯、120M網路&Wi-Fi 🚲 YouBike 2分鐘到 全聯福利中心 2分鐘到 南港捷運/高鐵/台鐵 2分鐘到 CityLink大型購物中心 3分鐘到 喜樂時代影城 4分鐘到 中國信託金融園區 4分鐘到 南港軟體園區 | BD9: 垃可 | BE9: https://youtube.com/shorts/fu3kXrLTZSo?feature=share | BF9: 🚴腳踏車 2分鐘到 全聯福利中心 2分鐘到 南港捷運/高鐵/台鐵 2分鐘到 CityLink大型購物中心 3分鐘到 喜樂時代影城 4分鐘到 中國信託金融園區 4分鐘到 南港軟體園區 󠀠 󠀠 󠀠 󠀠 󠀠 📌 地點: 115台北市南港區興中路44巷2弄X號1樓 公寓 📌 格局: 5房1廳2衛浴 📌 租金包含: 網路費、垃圾代收費 📌 設備: 冷氣、雙人床、衣櫃、桌椅、洗衣機、冰箱、桶裝瓦斯、120M網路&Wi-Fi
A10: A0009 | B10: TRUE | C10: TRUE | D10: TRUE | E10: TRUE | F10: 市府爺爺家 | G10: 常永年 | H10: 12000 | I10: 45482 | J10: 45483 | K10: 47308 | L10: 臺北市 | M10: 信義區 | N10: 基隆路一段350號四樓之25 | O10: 逸仙段三小段 | P10: 0032-0000 | Q10: 01121-000 | R10: 30.32 | S10: 1 | T10: 1 | U10: 1 | V10: 6 | W10: 4 | X10: 四層 | Y10: 公寓(無電梯) | Z10: A100530308 | AA10: 0963500836 | AB10: 012-530210174779 | AD10: =if(ISBLANK(I10),, YEAR(I10)-1911&TEXT(I10,"mmdd")) -> 1130709 | AE10: =if(ISBLANK(J10),, YEAR(J10)-1911&TEXT(J10,"mmdd")) -> 1130710 | AF10: =if(ISBLANK(K10),, YEAR(K10)-1911&TEXT(K10,"mmdd")) -> 1180709 | AG10: BAA9405318211330030 | AH10: 45483 | AI10: 12000 | AQ10: 2025.06.1 | AR10: 每個月1號 | AS10: 12000 | AX10: 貓狗企鵝 | BC10: 📌 地點: 110台北市信義區基隆路一段xx號4樓 公寓 📌 格局: 1房1廳1衛浴 📌 能源費: 水電依照台水台電帳單計算 📌 租金包含: 網路費、垃圾代收費 📌 押金: 2個月 📌 租期: 1年起 📌 設備: 冷氣、雙人床、衣櫃、桌椅、洗衣機、冰箱、桶裝瓦斯、120M網路&Wi-Fi 󠀠 󠀠 🚲YouBike 1分鐘到 國父紀念館 2分鐘到 新光三越 2分鐘到 威秀影城 2分鐘到 百貨美食街 3分鐘到 台北101 4分鐘到 吳興街美食街 | BD10: 包含在管理費，垃圾放在中庭區 | BF10: 獨立一房一廳, 獨立居住無需共居，自主選擇室友. 單人入住很舒服, 雙人入住剛剛好 󠀠 󠀠 🚲YouBike 1分鐘到 國父紀念館 2分鐘到 新光三越 2分鐘到 威秀影城 2分鐘到 百貨美食街 3分鐘到 台北101 4分鐘到 吳興街美食街 󠀠󠀠 台北市政府正對面，全新裝潢的溫馨住所，位於老舊的國宅，從入口走到房內的這1分鐘相較不美觀, 但內裡卻別有洞天。寬敞明亮的空間，為您打造舒適的生活環境。最令人驚喜的是，客廳窗外即可欣賞101大樓的璀璨夜景和絢爛煙火，無需擠進人群。位處繁華地段，享受便利生活，同時又能遠離喧囂。適合比較能接受老舊國宅公寓的朋友 󠀠 󠀠 󠀠 照片中的投影機是跟泡麵的封面一樣 僅供裝飾參考使用唷 : ) 󠀠 󠀠 󠀠 󠀠 󠀠 📌 地點: 110台北市信義區基隆路一段xx號4樓 公寓 📌 格局: 1房1廳1衛浴 📌 租金包含: 網路費、管理費、垃圾代收費 📌 設備: 冷氣、雙人床、衣櫃、桌椅、洗衣機、冰箱、桶裝瓦斯
A11: A0010 | B11: TRUE | C11: TRUE | D11: TRUE | E11: TRUE | F11: 金龍帽子先生 | G11: 郭娟伶 | H11: 35500 | I11: 45532 | J11: 45536 | K11: 47726 | L11: 臺北市 | M11: 內湖區 | N11: 金龍路109號三樓 | O11: 碧湖段一小段 | P11: 0388-0000 | Q11: 00349-000 | R11: 86.26 | S11: 1 | T11: 2 | U11: 4 | V11: 4 | W11: 3 | X11: 三層 | Y11: 公寓(無電梯) | Z11: P222283955 | AA11: 0939010408 | AB11: 822-901535206708 | AD11: =if(ISBLANK(I11),, YEAR(I11)-1911&TEXT(I11,"mmdd")) -> 1130828 | AE11: =if(ISBLANK(J11),, YEAR(J11)-1911&TEXT(J11,"mmdd")) -> 1130901 | AF11: =if(ISBLANK(K11),, YEAR(K11)-1911&TEXT(K11,"mmdd")) -> 1190831 | AG11: BAA9405318211330919 | AH11: 45536 | AI11: 35500 | AQ11: 2025.06.1 | AR11: 每個月1號 跟 15號 | AS11: 17750*2 | AU11: 47710 | AX11: 貓狗企鵝 | BC11: 📌 地點: 114台北市內湖區金龍路10x號3樓 公寓 📌 格局: 4房1廳2衛浴 📌 能源費: 水電依照台水台電帳單計算 📌 租金包含: 網路費、垃圾代收費 📌 押金: 2個月 📌 租期: 1年起 📌 設備: 冷氣、雙人床、衣櫃、桌椅、洗衣機、冰箱、桶裝瓦斯、120M網路&Wi-Fi 󠀠 🚲 YouBike 1分鐘到 7-11便利商店 1分鐘到 CITYLINK 內湖店 2分鐘到 內湖捷運站 2分鐘到 全聯福利中心 4分鐘到 湖光市場 🏍️騎車 5分鐘到 內湖科學園區 4站 到南港軟體園區 | BD11: Local廠商 放一樓 | BE11: https://youtu.be/-R69MXHoNkM | BF11: 捷運內湖站7分鐘 󠀠 🚴腳踏車 1分鐘到 7-11便利商店 1分鐘到 CITYLINK 內湖店 2分鐘到 內湖捷運站 2分鐘到 全聯福利中心 4分鐘到 湖光市場 🏍️騎車 5分鐘到 內湖科學園區 4站 到南港軟體園區 󠀠 󠀠 󠀠 󠀠 󠀠 📌 地點: 114台北市內湖區金龍路10x號3樓 公寓 📌 格局: 4房1廳2衛浴 📌 租金包含: 網路費、垃圾代收費 📌 設備: 冷氣、雙人床、衣櫃、桌椅、洗衣機、冰箱、天然瓦斯、垃圾代收、120M網路&Wi-Fi
A12: A0011 | B12: TRUE | C12: TRUE | D12: TRUE | E12: TRUE | F12: 景安2分鐘 | G12: 王逸荃 | H12: 25000 | I12: 45544 | J12: 45545 | K12: 49287 | L12: 新北市 | M12: 中和區 | N12: 景安路177巷16號3樓 | O12: 新和段 | P12: 0221-0000 | Q12: 02359-000 | R12: 100.39 | S12: 1 | T12: 2 | U12: 5 | V12: 5 | W12: 3 | X12: 三層 | Y12: 公寓(無電梯) | Z12: A225328637 | AA12: 0975257700 | AB12: 013-699501520652 | AD12: =if(ISBLANK(I12),, YEAR(I12)-1911&TEXT(I12,"mmdd")) -> 1130909 | AE12: =if(ISBLANK(J12),, YEAR(J12)-1911&TEXT(J12,"mmdd")) -> 1130910 | AF12: =if(ISBLANK(K12),, YEAR(K12)-1911&TEXT(K12,"mmdd")) -> 1231209 | AG12: BAF9405318211331260 | AH12: 45545 | AI12: 25000 | AQ12: 2025.06.1 | AR12: 每個月1號 跟 15號 | AS12: 12500*2 | AU12: 2034/11/15(因為2025.1.1提前支付2025.1.10起算的租金) | AX12: 貓狗企鵝 | AY12: 王滄浪 | AZ12: Y100803921 | BC12: 📌 地點: 235新北市中和區景安路177巷xx號3樓 公寓 📌 格局: 5房1廳2陽台2衛浴 📌 能源費: 水電依照台水台電帳單計算 📌 租金包含: 網路費、垃圾代收費 📌 押金: 2個月 📌 租期: 1年起 📌 設備: 冷氣、雙人床/單人床、衣櫃、桌椅、洗衣機、冰箱、天然瓦斯、120M網路&Wi-Fi 󠀠 󠀠 🚶步行 2分鐘到 美食手搖飲街 2分鐘到 景安捷運站(橘線/環狀線) 3分鐘到 全家便利商店 3分鐘到 Starbucks 7分鐘到 全聯福利中心 🏍️騎車 5分鐘到 迪卡儂 6分鐘到 Costco | BD12: 有管理費 | BF12: 雙捷運 景安站兩分鐘, 到站就到家 每間房都有對外窗, 採光極佳, 還有代收包裹喲 󠀠 󠀠 🚶步行 2分鐘到 美食手搖飲街 2分鐘到 景安捷運站(橘線/環狀線) 3分鐘到 全家便利商店 3分鐘到 Starbucks 7分鐘到 全聯福利中心 🏍️騎車 5分鐘到 迪卡儂 6分鐘到 Costco 󠀠󠀠 󠀠 󠀠 󠀠 󠀠 󠀠󠀠 󠀠 📌 地點: 235新北市中和區景安路177巷xx號3樓 公寓 📌 格局: 5房1廳2陽台2衛浴 📌 租金包含: 網路費 📌 設備: 冷氣、雙人床/單人床、衣櫃、桌椅、洗衣機、冰箱、天然瓦斯、360M網路&Wi-Fi
A13: A0012 | B13: TRUE | C13: TRUE | D13: TRUE | E13: TRUE | F13: 中山北娘家旁 | G13: 方彥捷 | H13: 23000 | I13: 45559 | J13: 45566 | K13: 49217 | L13: 臺北市 | M13: 中山區 | N13: 中山北路3段53之1號3樓 | O13: 中山段一小段 | P13: 0141-0000 | Q13: 02711-000 | R13: 74.92 | S13: 1 | T13: 1 | U13: 4 | V13: 5 | W13: 3 | X13: 三層 | Y13: 公寓(無電梯) | Z13: L100024680 | AA13: 0937999958 | AB13: 013-019507343662 | AD13: =if(ISBLANK(I13),, YEAR(I13)-1911&TEXT(I13,"mmdd")) -> 1130924 | AE13: =if(ISBLANK(J13),, YEAR(J13)-1911&TEXT(J13,"mmdd")) -> 1131001 | AF13: =if(ISBLANK(K13),, YEAR(K13)-1911&TEXT(K13,"mmdd")) -> 1230930 | AG13: BAA9405318211331472 | AH13: 45566 | AI13: 23000 | AJ13: 47027 | AK13: 25000 | AL13: 48122 | AM13: 30000 | AP13: 2025.1.1 | AQ13: 2025.06.1 | AR13: 每個月1號 跟 15號 | AS13: 11500*2 | AU13: 49202 | AX13: 貓狗企鵝 | BC13: 📌 地點: 10491台北市中山區中山北路三段53之xx號3樓 公寓 📌 格局: 4房1陽台1衛浴 📌 能源費: 水電依照台水台電帳單計算 📌 租金包含: 網路費、垃圾代收 📌 押金: 2個月 📌 租期: 1年起 📌 設備: 冷氣、雙人床/單人床、衣櫃、桌椅、洗脫烘、冰箱、電熱水器、150M網路&Wi-Fi 📌 其他: 禁菸、禁寵、性別友善、為增加居住品質、雅房限居一人 🚶步行 1分鐘到 7-11 2分鐘到 花博公園 3分鐘到 丸林滷肉飯 3分鐘到 大同大學 6分鐘到 晴光市場 7分鐘到 全聯福利中心 󠀠 🚴Youbike 2分鐘到 Starbucks 3分鐘到 全聯福利中心 4分鐘到 捷運民權西路站 5分鐘到 捷運圓山站 | BD13: 垃可 | BE13: https://youtu.be/CanmS-4D6Kw?si=xQUmYACid_86F21Z | BF13: 我空間不大，沒有廚房，但步行2~6分鐘就有晴光市場、花博市集 󠀠 🚶步行 1分鐘到 7-11 2分鐘到 花博公園 3分鐘到 丸林滷肉飯 3分鐘到 大同大學 6分鐘到 晴光市場 7分鐘到 全聯福利中心 󠀠 🚴Youbike 2分鐘到 Starbucks 3分鐘到 全聯福利中心 4分鐘到 捷運民權西路站 5分鐘到 捷運圓山站 󠀠 󠀠 󠀠 󠀠 󠀠󠀠 󠀠󠀠 📌 地點: 10491台北市中山區中山北路三段53之xx號3樓 公寓 📌 格局: 4房1陽台1衛浴 📌 租金包含: 網路費、垃圾代收 📌 設備: 冷氣、雙人床/單人床、衣櫃、桌椅、洗脫烘、冰箱、電熱水器、150M網路&Wi-Fi
A14: A0013 | B14: TRUE | C14: TRUE | D14: TRUE | E14: TRUE | F14: 行天宮夏野良栗 | G14: 沈蕙萱 | H14: 39800 | I14: 45562 | J14: 45566 | K14: 48121 | L14: 臺北市 | M14: 中山區 | N14: 松江路330巷14號4樓 | O14: 吉林段一小段 | P14: 0308-0000 | Q14: 00729-000 | R14: 54.29 | S14: 1 | T14: 1 | U14: 4 | V14: 4 | W14: 4 | X14: 四層 | Y14: 公寓(無電梯) | Z14: F224740830 | AA14: 0912565858 | AB14: 012-726168168447 | AD14: =if(ISBLANK(I14),, YEAR(I14)-1911&TEXT(I14,"mmdd")) -> 1130927 | AE14: =if(ISBLANK(J14),, YEAR(J14)-1911&TEXT(J14,"mmdd")) -> 1131001 | AF14: =if(ISBLANK(K14),, YEAR(K14)-1911&TEXT(K14,"mmdd")) -> 1200930 | AG14: BAA9405318211331473 | AH14: 45566 | AI14: 39800 | AQ14: 2025.12.1 | AR14: 每個月1號 跟 15號 | AS14: 19900*2 | AU14: 48106 | AX14: 鯰魚大大 | BC14: 📌 地點: 台北市中山區松江路330巷 【租金包含】網路費，雙層共用垃圾代收 【押金】2個月，租期1年起 【能源費】4F+5F 水、瓦斯依帳單 室友人頭均攤，電費依各樓電錶 【設備】生飲濾水器、全新冷氣、掀床床墊組、衣櫃、書桌椅、洗衣機、冰箱、餐桌、瓦斯爐、抽油煙機、熱水器、網路 & WIFI 💲󠀠 捷運行天宮站 →走路 2 分鐘 💲 捷運中山國小站 →走路 9 分鐘󠀠 󠀠 💲 󠀠 󠀠近錦州街美食街 & 行天宮 | BD14: 垃可 | BE14: https://youtu.be/NXcYXt3PaZc?si=OyBT6tHSDoGNRXIa | BF14: ====行 天 宮 站 2 分 鐘 → 夏 野 良 栗 ==== 󠀠 󠀠󠀠 💲󠀠 捷運行天宮站 →走路 2 分鐘 💲 捷運中山國小站 →走路 9 分鐘󠀠 󠀠 💲 󠀠 󠀠近錦州街美食街 & 行天宮 󠀠 󠀠 每天早晨 帶一杯巷口夏野豆行的咖啡 再帶一份良栗商號的肉蛋吐司 幫早晨添加50%↑的幸福感~ 󠀠󠀠 󠀠 【房型】公寓2層 4F & 5F → 4F 共生公寓 四房一衛一廳一廚一陽台 → 5F 兩房一衛一廳一廚一陽台 頂加 👌歡迎來訊索取線上看屋影片 󠀠 󠀠 【租金包含】網路費，雙層共用垃圾代收 【能源費】4F+5F 水、瓦斯依帳單 室友人頭均攤，電費依各樓電錶 【設備】生飲濾水器、全新冷氣、掀床床墊組、衣櫃、書桌椅、洗衣機、冰箱、餐桌、瓦斯爐、抽油煙機、熱水器、網路 & WIFI
A15: A0014 | B15: TRUE | C15: TRUE | D15: TRUE | E15: TRUE | F15: 中山北Feli家 | G15: 陳玉蘭 | H15: 36000 | I15: 45572 | J15: 45580 | K15: 49231 | L15: 臺北市 | M15: 士林區 | N15: 中山北路六段419巷25號五樓 | O15: 天母段一小段 | P15: 0316-0000 | Q15: 10998-000 | R15: 100.67 | S15: 1 | T15: 2 | U15: 4 | V15: 5 | W15: 5 | X15: 五層 | Y15: 公寓(無電梯) | Z15: C200997263 | AA15: 0935138805 | AB15: 052-11320000222609 | AD15: =if(ISBLANK(I15),, YEAR(I15)-1911&TEXT(I15,"mmdd")) -> 1131007 | AE15: =if(ISBLANK(J15),, YEAR(J15)-1911&TEXT(J15,"mmdd")) -> 1131015 | AF15: =if(ISBLANK(K15),, YEAR(K15)-1911&TEXT(K15,"mmdd")) -> 1231014 | AG15: BAA9405318211340061 | AH15: 45580 | AI15: 36000 | AJ15: 46675 | AK15: 38000 | AL15: 47406 | AM15: 42000 | AN15: 48502 | AO15: 45000 | AQ15: 2025.06.1 | AR15: 每個月1號 跟 15號 | AS15: 18000*2 | AU15: 49218 | AX15: 貓狗企鵝 | BC15: 📌 地點: 111台北市士林區中山北路六段419巷2x號5樓、6樓 公寓 📌 5樓格局: 4房2陽台2衛浴1廳 📌 6樓格局: 2房1廳1衛1陽台 📌 能源費: 水電依照台水台電帳單計算 📌 租金包含: 網路費、垃圾代收 📌 押金: 2個月 📌 租期: 1年起 📌 設備: 冷氣、雙人床/單人床、衣櫃、桌椅、洗衣機、冰箱、天然瓦斯熱水器、120M網路&Wi-Fi 📌 其他: 禁菸、禁寵、性別友善、為增加居住品質、雅房限居一人 🚴Youbike 1分鐘到 Starbucks 2分鐘到 全聯福利中心 4分鐘到 天母生活市集 4分鐘到 天母棒球場 4分鐘到 大葉高島屋 6分鐘到 新光三越 7分鐘到 芝山捷運站 | BD15: 0921643690陳先生 收 樓梯清潔費 每一戶會輪流 我們有頂加，所以要多分一次 因為兩戶，8個月輪兩次，之前是1600元，2026改成2400 | BE15: https://youtube.com/shorts/RZ_wXh8ThPE?si=QbuLD6PBOsXTRF_Y | BF15: #適合機車族 遠離市中心急促的步調 低調樸實、生活環境獨樹一格是天母的特色 下班回到家享受他鄉的異國情調 󠀠 🚴Youbike 1分鐘到 Starbucks 2分鐘到 全聯福利中心 4分鐘到 天母生活市集 4分鐘到 天母棒球場 4分鐘到 大葉高島屋 6分鐘到 新光三越 7分鐘到 芝山捷運站 󠀠 󠀠 󠀠 󠀠 󠀠󠀠 󠀠󠀠 📌 地點: 111台北市士林區中山北路六段419巷2x號5樓、6樓 公寓 📌 5樓格局: 4房2陽台2衛浴1廳 📌 6樓格局: 2房1廳1衛1陽台 📌 租金包含: 網路費、垃圾代收 📌 設備: 冷氣、雙人床/單人床、衣櫃、桌椅、洗衣機、冰箱、天然瓦斯熱水器、120M網路&Wi-Fi
A16: A0015 | B16: TRUE | C16: TRUE | D16: TRUE | E16: TRUE | F16: 書香民生 | G16: 吳高寶玉 | H16: 50000 | I16: 45723 | J16: 45809 | K16: 49460 | L16: 臺北市 | M16: 松山區 | N16: 延壽街327號四樓 | O16: 民生段 | P16: 0080-0010 | Q16: 06623-000 | R16: 119.55 | S16: 2 | T16: 2 | U16: 5 | V16: 4 | W16: 4 | X16: 四層 | Y16: 公寓(無電梯) | Z16: A201772900 | AA16: 0932917766 | AB16: 700-00015610514204 | AD16: =if(ISBLANK(I16),, YEAR(I16)-1911&TEXT(I16,"mmdd")) -> 1140307 | AE16: =if(ISBLANK(J16),, YEAR(J16)-1911&TEXT(J16,"mmdd")) -> 1140601 | AF16: =if(ISBLANK(K16),, YEAR(K16)-1911&TEXT(K16,"mmdd")) -> 1240531 | AG16: BAA9405318211411259 | AH16: 45809 | AI16: 50000 | AR16: 每個月1號 / 10號 / 20號 | AS16: 16667 16667 16666 | AU16: 49430 | AX16: 貓狗企鵝 | BC16: 📌 地點: 台北市松山區延壽街3xx號四樓 公寓 📌格局: 4房2陽台2衛浴2廳 + 2房 頂樓曬衣曬被大陽台 📌 租金包含: 網路費、垃圾代收 📌 設備: 冷氣、雙人床/單人床、衣櫃、桌椅、雙洗衣機、雙冰箱、天然瓦斯熱水器、網路&Wi-Fi | BD16: 垃可 | BE16: https://youtu.be/3132CN9-UOM | BF16: 🚲 YouBike 1分鐘到 7-11 2分鐘到 全聯 5分鐘到 捷運南京三民站 6分鐘到 台北小巨蛋 8分鐘到 IKEA、微風南京 📌 地點: 105台北市松山區延壽街32x號4~5樓 公寓 📌 格局: 1廚1廳 3陽台 3衛浴 7雅房 1洗衣房 📌 租金包含: 網路費、垃圾代收費、定期公區清潔 📌 設備: 冷氣、單/雙人床、衣櫃、桌椅、滾筒洗脫烘洗衣機、冰箱、瓦斯爐、抽油煙機、天然瓦斯、熱水器、濾水器、網路&Wi-Fi
A17: A0016 | B17: FALSE | C17: TRUE | D17: TRUE | E17: TRUE | F17: 內湖CityLink | G17: 周佳慧 | H17: 33000 | I17: 45782 | J17: 45778 | K17: 49429 | L17: 臺北市 | M17: 內湖區 | N17: 內湖路二段355巷7弄7號四樓 | O17: 碧湖段二小段 | P17: 0056-0000 0060-0000 0061-0000 0062-0000 | Q17: 00392-000 | R17: 114.48 | S17: 2 | T17: 2 | U17: 6 | V17: 4 | W17: 4 | X17: 四層 | Y17: 公寓(無電梯) | Z17: A221172157 | AA17: 0937954493 | AB17: 806-21672000026435 | AD17: =if(ISBLANK(I17),, YEAR(I17)-1911&TEXT(I17,"mmdd")) -> 1140505 | AE17: =if(ISBLANK(J17),, YEAR(J17)-1911&TEXT(J17,"mmdd")) -> 1140501 | AF17: =if(ISBLANK(K17),, YEAR(K17)-1911&TEXT(K17,"mmdd")) -> 1240430 | AG17: BAA9405318211420667 | AH17: 45778 | AI17: 33000 | AR17: 每個月1號 跟 15號 | AS17: 16500*2 | AU17: 49400 | AX17: 鯰魚大大 | BC17: 📌 地點: 台北市內湖區內湖路二段355巷7弄x號四樓 公寓 📌格局: 6房1陽台2衛浴2廳 + 頂樓曬衣曬被大陽台 📌 租金包含: 網路費、垃圾代收 📌 設備: 冷氣、雙人床/單人床、衣櫃、桌椅、雙洗衣機、雙冰箱、天然瓦斯熱水器、網路&Wi-Fi | BD17: 垃可 | BE17: https://youtube.com/shorts/AZDV_Y6AMvs?feature=share | BF17: 🚇 內湖站走路4分鐘到家 🏡 搶手六房共生宅｜可申請租金補貼 💰 在城市裡找一個平衡點，一個下班後能靜靜喘口氣、早晨能迎著陽光晾衣服的家，你現在找到了。 📍地點優勢： 走路3分鐘 ➜ 內湖 Citylink 走路4分鐘 ➜ 捷運內湖站（文湖線） 走路7分鐘 ➜ 湖光市場 騎車5分鐘 ➜ 內湖737巷夜市 捷運4站 ➜ 南港軟體園區 每間房皆有對外窗，每房限住一人，垃圾代收服務 📌 地點: 台北市內湖區內湖路二段355巷7弄x號四樓 公寓 📌格局: 6房1陽台2衛浴2廳 + 頂樓曬衣曬被大陽台 📌 租金包含: 網路費、垃圾代收 📌 設備: 冷氣、雙人床/單人床、衣櫃、桌椅、雙洗衣機、雙冰箱、天然瓦斯熱水器、網路&Wi-Fi ☀️ 房子位於安靜巷弄中，遠離車流嘈雜，生活機能卻又一應俱全。無論你是內科上班族、學生族、或剛畢業的社會新鮮人，都很適合這個有質感的小社區。 📬 歡迎私訊索取看屋影片或預約實體參觀 📩 可申請租金補貼｜報稅合法透明 🧾
A18: A0017 | B18: FALSE | C18: FALSE | D18: FALSE | E18: TRUE | F18: 天母搜狗 | G18: 陳怡安 | H18: 19800 | I18: 45933 | J18: 45943 | K18: 51440 | L18: 臺北市 | M18: 士林區 | N18: 德行東路74巷22號5樓 | O18: 芝山段二小段 | P18: 0408-0000 | Q18: 23301-000 | R18: 141.26 | S18: 1 | T18: 2 | U18: 4 | V18: 5 | W18: 5 | X18: 五層 | Y18: 公寓(無電梯) | Z18: A227884889 | AA18: 0902272069 | AB18: 812-28881015177469 | AD18: 1141003 | AE18: 1141013 | AF18: 1291031 | AG18: BAA9405318211440077 | AH18: 46023 | AI18: 19800 | AX18: 貓狗企鵝 | BC18: 📌 地點: 111臺北市士林區德行東路74巷2x號5樓 公寓 📌 能源費: 水電依照台水台電帳單計算 📌 租金包含: 網路費、垃圾代收 📌 押金: 2個月 📌 租期: 1年起 📌 設備: 冷氣、雙人床/單人床、衣櫃、桌椅、洗衣機、烘衣機、微波爐、冰箱、天然瓦斯熱水器、網路&Wi-Fi 📌 其他: 禁菸、禁寵、性別友善 | BF18: 🚲 YouBike 1分鐘到 超好吃 榕屋Pasta 3分鐘到 大葉高島屋 3分鐘到 新光三越 4分鐘到 天母棒球場 4分鐘到 芝山捷運站 8分鐘到 天母生活市集 8分鐘到 全聯福利中心 ======================= 📌 地點: 111臺北市士林區德行東路74巷2x號5樓 公寓 📌 能源費: 水電依照台水台電帳單計算 📌 租金包含: 網路費、垃圾代收 📌 押金: 2個月 📌 租期: 1年起 📌 設備: 冷氣、雙人床/單人床、衣櫃、桌椅、洗衣機、烘衣機、微波爐、冰箱、天然瓦斯熱水器、網路&Wi-Fi 📌 其他: 禁菸、禁寵、性別友善
A19: A0018 | B19: FALSE | C19: FALSE | D19: FALSE | E19: TRUE | F19: 葫洲維也納 | G19: 林霈蓉 | H19: 0 | I19: 45933 | J19: 45962 | K19: 45944 | L19: 臺北市 | M19: 內湖區 | N19: 康寧路三段99巷39弄72號 | O19: 內湖區東湖段二小段 | P19: 0012-0001 | Q19: 02797-000 | R19: 100.925 | S19: 1 | T19: 2 | U19: 3 | V19: 7 | W19: 1 | X19: 一層 | Y19: 華廈(10層含以下有電梯) | Z19: A223499526 | AA19: 0905556049 | AB19: 822-587540229712 | AD19: 1141003 | AE19: 1141101 | AF19: 1241031 | AG19: BAA9405318211440079 | AH19: 46023 | AI19: 0 | AR19: 每個月1號 跟 15號 | AX19: 貓狗企鵝
A20: A0019 | B20: FALSE | C20: FALSE | D20: FALSE | E20: FALSE
A21: A0020 | B21: FALSE | C21: FALSE | D21: FALSE | E21: FALSE
A22: A0021 | B22: FALSE | C22: FALSE | D22: FALSE | E22: FALSE
A23: A0022 | B23: FALSE | C23: FALSE | D23: FALSE | E23: FALSE
A24: A0023 | B24: FALSE | C24: FALSE | D24: FALSE | E24: FALSE
A25: A0024 | B25: FALSE | C25: FALSE | D25: FALSE | E25: FALSE
A26: A0025 | B26: FALSE | C26: FALSE | D26: FALSE | E26: FALSE
A27: A0026 | B27: FALSE | C27: FALSE | D27: FALSE | E27: FALSE
A28: A0027 | B28: FALSE | C28: FALSE | D28: FALSE | E28: FALSE
A29: A0028 | B29: FALSE | C29: FALSE | D29: FALSE | E29: FALSE

Sheet sublease_contract
A1: room_key | B1: contract_key | C1: =IFERROR(__xludf.DUMMYFUNCTION("{""property""; MAP(A2:A265, LAMBDA(key, IF(key="""",, IFERROR( IF(COUNTUNIQUE(ARRAYFORMULA(VLOOKUP(SPLIT(key, CHAR(10)), room_list!B:D, 2, FALSE))) = 1, VLOOKUP(SPLIT(key, CHAR(10), TRUE), room_list!B:D, 2, FALSE), ""屬性不一致"" ), "&"""查無資料"" )) ))}"),"property") -> property | D1: =IFERROR(__xludf.DUMMYFUNCTION("{""room_number""; MAP(A2:A265, LAMBDA(key, IF(key="""",, IFERROR( TEXTJOIN("", "", TRUE, ARRAYFORMULA(VLOOKUP(SPLIT(key, CHAR(10)), room_list!B:D, 3, FALSE))), ""查無資料"" )) ))}"),"room_number") -> room_number | E1: tenant_key | F1: =IFERROR(__xludf.DUMMYFUNCTION("{""tenant_name""; MAP(E2:E265, LAMBDA(key, IF(key="""",, IFERROR( TEXTJOIN(CHAR(10), TRUE, ARRAYFORMULA(VLOOKUP(SPLIT(key, CHAR(10)), tenant_list!A:B, 2, FALSE))), ""查無資料"" )) ))}"),"tenant_name") -> tenant_name | G1: {={"occupancy_status"; IF((M2:M265 = "") * (N2:N265 = ""), "", IF((M2:M265 = "") + (N2:N265 = ""), "日期錯誤", IF(TODAY() > N2:N265, "已退租", IF(TODAY() < M2:M265, "尚未入住", "入住中") ) ) )}} -> occupancy_status | H1: sublease_registration | I1: actual_price_registration | J1: rent_subsidy | K1: payment_method | L1: contract_signed_date | M1: contract_start_date | N1: contract_end_date | O1: next_payment_date | P1: final_payment_date | Q1: {={"reconciliation"; IF((M2:M265="") + (N2:N265=""), , N2:N265-M2:M265+1)}} -> reconciliation | R1: sublease_rent | S1: receivable_rent | T1: previous_received_rent | U1: {={"difference"; IF(T2:T265="",, S2:S265-T2:T265)}} -> difference | V1: sublease_deposit | W1: {={"contract_signed_date_minguo"; MAP(L2:L265, LAMBDA(d, IF(d="",, YEAR(d)-1911 & TEXT(d, "mmdd")) ))}} -> contract_signed_date_minguo | X1: {={"contract_start_date_minguo"; MAP(M2:M265, LAMBDA(d, IF(d="",, YEAR(d)-1911 & TEXT(d, "mmdd")) ))}} -> contract_start_date_minguo | Y1: {={"contract_end_date_minguo"; MAP(N2:N265, LAMBDA(d, IF(d="",, YEAR(d)-1911 & TEXT(d, "mmdd")) ))}} -> contract_end_date_minguo | Z1: initial_payment_method | AA1: final_payment_method | AB1: final_month_days | AC1: final_month_amount | AD1: actual_price_registration_form_number | AE1: water_fee | AF1: electricity_fee | AG1: gas_fee | AH1: withheld_utilities | AI1: adjustment_refund
A2: RL00002 | B2: CR00002 | C2: =IFERROR(__xludf.DUMMYFUNCTION("""COMPUTED_VALUE"""),"永春四號") -> 永春四號 | D2: =IFERROR(__xludf.DUMMYFUNCTION("""COMPUTED_VALUE"""),"A") -> A | E2: PP00002 | F2: =IFERROR(__xludf.DUMMYFUNCTION("""COMPUTED_VALUE"""),"辜馨嬅") -> 辜馨嬅 | G2: 已退租 | H2: 已登記 | I2: 已登記 | J2: 要申請 | K2: 半年繳 | L2: 45278 | M2: 45292 | N2: 45716 | O2: 45658 | P2: 45689 | Q2: 425 | R2: 12900 | S2: 12900 | V2: 25800 | W2: 1121218 | X2: 1130101 | Y2: 1140228 | Z2: 標準足月 | AA2: 足月 | AB2: 28 | AC2: 0 | AD2: C1AD11212300001
A3: RL00002 | B3: CR00003 | C3: =IFERROR(__xludf.DUMMYFUNCTION("""COMPUTED_VALUE"""),"永春四號") -> 永春四號 | D3: =IFERROR(__xludf.DUMMYFUNCTION("""COMPUTED_VALUE"""),"A") -> A | E3: PP00002 | F3: =IFERROR(__xludf.DUMMYFUNCTION("""COMPUTED_VALUE"""),"辜馨嬅") -> 辜馨嬅 | G3: 入住中 | H3: 已登記 | I3: 已登記 | J3: 要申請 | K3: 半年繳 | L3: 45659 | M3: 45717 | N3: 46081 | O3: 46082 | P3: 45901 | Q3: 365 | R3: 12900 | S3: 12900 | V3: 25800 | W3: 1140102 | X3: 1140301 | Y3: 1150228 | Z3: 標準足月 | AA3: 足月 | AB3: 28 | AC3: 0 | AD3: C1AD11401040003
A4: RL00003 | B4: CR00004 | C4: =IFERROR(__xludf.DUMMYFUNCTION("""COMPUTED_VALUE"""),"永春四號") -> 永春四號 | D4: =IFERROR(__xludf.DUMMYFUNCTION("""COMPUTED_VALUE"""),"B") -> B | E4: PP00003 | F4: =IFERROR(__xludf.DUMMYFUNCTION("""COMPUTED_VALUE"""),"袁家鳳") -> 袁家鳳 | G4: 已退租 | H4: 已登記 | I4: 已登記 | J4: 要申請 | K4: 月繳 | L4: 45256 | M4: 45261 | N4: 45747 | O4: 45748 | P4: 45717 | Q4: 487 | R4: 13500 | S4: 13500 | V4: 27000 | W4: 1121126 | X4: 1121201 | Y4: 1140331 | Z4: 標準足月 | AA4: 足月 | AB4: 31 | AC4: 0 | AD4: C1AD11211260001
A5: RL00004 | B5: CR00005 | C5: =IFERROR(__xludf.DUMMYFUNCTION("""COMPUTED_VALUE"""),"永春四號") -> 永春四號 | D5: =IFERROR(__xludf.DUMMYFUNCTION("""COMPUTED_VALUE"""),"C") -> C | E5: PP00004 | F5: =IFERROR(__xludf.DUMMYFUNCTION("""COMPUTED_VALUE"""),"林聿妡") -> 林聿妡 | G5: 已退租 | H5: 已登記 | I5: 已登記 | J5: 要申請 | K5: 月繳 | L5: 45239 | M5: 45240 | N5: 45688 | O5: 45689 | P5: 45658 | Q5: 449 | R5: 13300 | S5: 13300 | V5: 26600 | W5: 1121109 | X5: 1121110 | Y5: 1140131 | Z5: 第二個月付差額 | AA5: 不足月 | AB5: 22 | AC5: #REF! | AD5: C1AD11211200005
A6: RL00004 | B6: CR00006 | C6: =IFERROR(__xludf.DUMMYFUNCTION("""COMPUTED_VALUE"""),"永春四號") -> 永春四號 | D6: =IFERROR(__xludf.DUMMYFUNCTION("""COMPUTED_VALUE"""),"C") -> C | E6: PP00004 | F6: =IFERROR(__xludf.DUMMYFUNCTION("""COMPUTED_VALUE"""),"林聿妡") -> 林聿妡 | G6: 已退租 | H6: 已登記 | I6: 已登記 | J6: 要申請 | K6: 月繳 | L6: 45658 | M6: 45689 | N6: 45716 | O6: 45717 | P6: 45689 | Q6: 28 | R6: 13300 | S6: 13300 | V6: 26600 | W6: 1140101 | X6: 1140201 | Y6: 1140228 | Z6: 第二個月付差額 | AA6: 不足月 | AB6: 28 | AC6: #REF! | AD6: C1AD11401040004
A7: RL00005 | B7: CR00007 | C7: =IFERROR(__xludf.DUMMYFUNCTION("""COMPUTED_VALUE"""),"永春四號") -> 永春四號 | D7: =IFERROR(__xludf.DUMMYFUNCTION("""COMPUTED_VALUE"""),"D") -> D | E7: PP00005 | F7: =IFERROR(__xludf.DUMMYFUNCTION("""COMPUTED_VALUE"""),"翁政熙") -> 翁政熙 | G7: 已退租 | H7: 已註銷 | I7: 已登記 | J7: 要申請 | K7: 月繳 | L7: 45237 | M7: 45243 | N7: 45657 | O7: 45689 | P7: 45627 | Q7: 415 | R7: 14800 | S7: 14800 | V7: 29600 | W7: 1121107 | X7: 1121113 | Y7: 1131231 | Z7: 第二個月付差額 | AA7: 不足月 | AB7: 19 | AC7: #REF! | AD7: C1AD11211260002
A8: RL00005 | B8: CR00008 | C8: =IFERROR(__xludf.DUMMYFUNCTION("""COMPUTED_VALUE"""),"永春四號") -> 永春四號 | D8: =IFERROR(__xludf.DUMMYFUNCTION("""COMPUTED_VALUE"""),"D") -> D | E8: PP00005 | F8: =IFERROR(__xludf.DUMMYFUNCTION("""COMPUTED_VALUE"""),"翁政熙") -> 翁政熙 | G8: 已退租 | H8: 已登記 | I8: 已登記 | J8: 要申請 | K8: 月繳 | L8: 45631 | M8: 45658 | N8: 45716 | O8: 45717 | P8: 45689 | Q8: 59 | R8: 14800 | S8: 14800 | V8: 29600 | W8: 1131205 | X8: 1140101 | Y8: 1140228 | Z8: 標準足月 | AA8: 足月 | AB8: 28 | AC8: 0 | AD8: C1AD11312090002
A9: RL00011 | B9: CR00009 | C9: =IFERROR(__xludf.DUMMYFUNCTION("""COMPUTED_VALUE"""),"內湖秘境") -> 內湖秘境 | D9: =IFERROR(__xludf.DUMMYFUNCTION("""COMPUTED_VALUE"""),"F") -> F | E9: PP00006 | F9: =IFERROR(__xludf.DUMMYFUNCTION("""COMPUTED_VALUE"""),"陳俊宇") -> 陳俊宇 | G9: 已退租 | H9: 已註銷 | I9: 已登記 | J9: 要申請 | K9: 月繳 | L9: 45250 | M9: 45255 | N9: 45459 | O9: 45474 | P9: 45658 | Q9: 205 | R9: 12800 | S9: 12300 | V9: 25600 | W9: 1121120 | X9: 1121125 | Y9: 1130616 | Z9: 標準足月 | AA9: 不足月 | AB9: -8 | AC9: #REF! | AD9: C1AC11211200018 | AE9: 已退 | AF9: 已退 | AG9: 已退
A10: RL00006 | B10: CR00010 | C10: =IFERROR(__xludf.DUMMYFUNCTION("""COMPUTED_VALUE"""),"內湖秘境") -> 內湖秘境 | D10: =IFERROR(__xludf.DUMMYFUNCTION("""COMPUTED_VALUE"""),"A") -> A | E10: PP00007 | F10: =IFERROR(__xludf.DUMMYFUNCTION("""COMPUTED_VALUE"""),"陳玟涵") -> 陳玟涵 | G10: 已退租 | H10: 已註銷 | I10: 已登記 | J10: 要申請 | K10: 月繳 | L10: 45262 | M10: 45275 | N10: 45640 | O10: 45689 | P10: 45597 | Q10: 366 | R10: 12000 | S10: 12000 | V10: 24000 | W10: 1121202 | X10: 1121215 | Y10: 1131214 | Z10: 標準足月 | AA10: 足月 | AB10: 0 | AC10: 0 | AD10: C1AC11212050006
A11: RL00006 | B11: CR00011 | C11: =IFERROR(__xludf.DUMMYFUNCTION("""COMPUTED_VALUE"""),"內湖秘境") -> 內湖秘境 | D11: =IFERROR(__xludf.DUMMYFUNCTION("""COMPUTED_VALUE"""),"A") -> A | E11: PP00007 | F11: =IFERROR(__xludf.DUMMYFUNCTION("""COMPUTED_VALUE"""),"陳玟涵") -> 陳玟涵 | G11: 入住中 | H11: 已登記 | I11: 已登記 | J11: 要申請 | K11: 月繳 | L11: 45616 | M11: 45610 | N11: 46081 | O11: 46082 | P11: 45962 | Q11: 472 | R11: 11700 | S11: 11700 | T11: 0 | U11: 11700 | V11: 24000 | W11: 1131120 | X11: 1131114 | Y11: 1150228 | Z11: 標準足月 | AA11: 足月 | AB11: 15 | AC11: 0 | AD11: C1AC11312010006
A12: RL00007 | B12: CR00012 | C12: =IFERROR(__xludf.DUMMYFUNCTION("""COMPUTED_VALUE"""),"內湖秘境") -> 內湖秘境 | D12: =IFERROR(__xludf.DUMMYFUNCTION("""COMPUTED_VALUE"""),"B") -> B | E12: PP00008 | F12: =IFERROR(__xludf.DUMMYFUNCTION("""COMPUTED_VALUE"""),"李方羽") -> 李方羽 | G12: 已退租 | H12: 已註銷 | I12: 已登記 | J12: 要申請 | K12: 月繳 | L12: 45246 | M12: 45246 | N12: 45611 | O12: 45597 | P12: 45597 | Q12: 366 | R12: 12800 | S12: 12800 | V12: 25600 | W12: 1121116 | X12: 1121116 | Y12: 1131115 | Z12: 標準足月 | AA12: 不足月 | AB12: 15 | AC12: #REF! | AD12: C1AC11211190001 | AE12: 150 | AF12: 659 | AG12: 77 | AH12: 1000 | AI12: 完成
A13: RL00007 | B13: CR00013 | C13: =IFERROR(__xludf.DUMMYFUNCTION("""COMPUTED_VALUE"""),"內湖秘境") -> 內湖秘境 | D13: =IFERROR(__xludf.DUMMYFUNCTION("""COMPUTED_VALUE"""),"B") -> B | E13: PP00009 | F13: =IFERROR(__xludf.DUMMYFUNCTION("""COMPUTED_VALUE"""),"劉桀綸") -> 劉桀綸 | G13: 已退租 | H13: 已登記 | I13: 已登記 | J13: 要申請 | K13: 月繳 | L13: 45623 | M13: 45627 | N13: 45984 | O13: 45992 | P13: 45962 | Q13: 358 | R13: 12300 | S13: 12300 | V13: 24600 | W13: 1131127 | X13: 1131201 | Y13: 1141123 | Z13: 標準足月 | AA13: 足月 | AB13: 23 | AC13: 0 | AD13: C1AC11312060049 | AI13: 完成
A14: RL00008 | B14: CR00014 | C14: =IFERROR(__xludf.DUMMYFUNCTION("""COMPUTED_VALUE"""),"內湖秘境") -> 內湖秘境 | D14: =IFERROR(__xludf.DUMMYFUNCTION("""COMPUTED_VALUE"""),"C") -> C | E14: PP00010 | F14: =IFERROR(__xludf.DUMMYFUNCTION("""COMPUTED_VALUE"""),"黃詩穎") -> 黃詩穎 | G14: 已退租 | H14: 已登記 | I14: 已登記 | J14: 要申請 | K14: 月繳 | L14: 45250 | M14: 45261 | N14: 45716 | O14: 45717 | P14: 45689 | Q14: 456 | R14: 14800 | S14: 14800 | V14: 29600 | W14: 1121120 | X14: 1121201 | Y14: 1140228 | Z14: 標準足月 | AA14: 足月 | AB14: 28 | AC14: 0 | AD14: C1AC11211200019
A15: RL00009 | B15: CR00015 | C15: =IFERROR(__xludf.DUMMYFUNCTION("""COMPUTED_VALUE"""),"內湖秘境") -> 內湖秘境 | D15: =IFERROR(__xludf.DUMMYFUNCTION("""COMPUTED_VALUE"""),"D") -> D | E15: PP00011 | F15: =IFERROR(__xludf.DUMMYFUNCTION("""COMPUTED_VALUE"""),"王敏誠") -> 王敏誠 | G15: 已退租 | H15: 已註銷 | I15: 已登記 | J15: 不申請 | K15: 半年繳 | L15: 45243 | M15: 45249 | N15: 45614 | Q15: 366 | R15: 13200 | S15: 13200 | V15: 26400 | W15: 1121113 | X15: 1121119 | Y15: 1131118 | Z15: 標準足月 | AA15: 足月 | AB15: 0 | AC15: 0 | AE15: 已退 | AF15: 已退 | AG15: 已退
A16: RL00009 | B16: CR00016 | C16: =IFERROR(__xludf.DUMMYFUNCTION("""COMPUTED_VALUE"""),"內湖秘境") -> 內湖秘境 | D16: =IFERROR(__xludf.DUMMYFUNCTION("""COMPUTED_VALUE"""),"D") -> D | E16: PP00011 | F16: =IFERROR(__xludf.DUMMYFUNCTION("""COMPUTED_VALUE"""),"王敏誠") -> 王敏誠 | G16: 已退租 | H16: 已登記 | I16: 已登記 | J16: 要申請 | K16: 半年繳 | L16: 45587 | M16: 45615 | N16: 45979 | O16: 45992 | P16: 45778 | Q16: 365 | R16: 13200 | S16: 13200 | V16: 26400 | W16: 1131022 | X16: 1131119 | Y16: 1141118 | Z16: 標準足月 | AA16: 足月 | AB16: 0 | AC16: 0 | AD16: C1AC11311010028
A17: RL00010 | B17: CR00017 | C17: =IFERROR(__xludf.DUMMYFUNCTION("""COMPUTED_VALUE"""),"內湖秘境") -> 內湖秘境 | D17: =IFERROR(__xludf.DUMMYFUNCTION("""COMPUTED_VALUE"""),"E") -> E | E17: PP00012 | F17: =IFERROR(__xludf.DUMMYFUNCTION("""COMPUTED_VALUE"""),"鄧又晨") -> 鄧又晨 | G17: 已退租 | H17: 已註銷 | I17: 已登記 | J17: 不申請 | K17: 年繳 | L17: 45245 | M17: 45261 | N17: 45626 | Q17: 366 | R17: 13000 | S17: 13000 | V17: 26000 | W17: 1121115 | X17: 1121201 | Y17: 1131130 | Z17: 標準足月 | AA17: 足月 | AB17: 30 | AC17: 0 | AE17: 已退 | AF17: 已退 | AG17: 已退
A18: RL00010 | B18: CR00018 | C18: =IFERROR(__xludf.DUMMYFUNCTION("""COMPUTED_VALUE"""),"內湖秘境") -> 內湖秘境 | D18: =IFERROR(__xludf.DUMMYFUNCTION("""COMPUTED_VALUE"""),"E") -> E | E18: PP00013 | F18: =IFERROR(__xludf.DUMMYFUNCTION("""COMPUTED_VALUE"""),"鄧又慈") -> 鄧又慈 | G18: 已退租 | H18: 已註銷 | I18: 已登記 | J18: 要申請 | K18: 月繳 | L18: 45586 | M18: 45582 | N18: 45628 | O18: 45658 | P18: 45962 | Q18: 47 | R18: 14500 | S18: 14500 | V18: 26000 | W18: 1131021 | X18: 1131017 | Y18: 1131202 | Z18: 標準足月 | AA18: 足月 | AB18: -14 | AC18: 0 | AD18: C1AC11311010029 | AE18: 199 | AG18: 126 | AH18: 1000 | AI18: 已退
A19: RL00010 | B19: CR00019 | C19: =IFERROR(__xludf.DUMMYFUNCTION("""COMPUTED_VALUE"""),"內湖秘境") -> 內湖秘境 | D19: =IFERROR(__xludf.DUMMYFUNCTION("""COMPUTED_VALUE"""),"E") -> E | E19: PP00014 | F19: =IFERROR(__xludf.DUMMYFUNCTION("""COMPUTED_VALUE"""),"林芷妤") -> 林芷妤 | G19: 入住中 | H19: 已登記 | I19: 已登記 | J19: 要申請 | K19: 月繳 | L19: 45641 | M19: 45646 | N19: 46081 | O19: 46082 | P19: 46054 | Q19: 436 | R19: 13600 | S19: 13600 | T19: 0 | U19: 13600 | V19: 27200 | W19: 1131215 | X19: 1131220 | Y19: 1150228 | Z19: 標準足月 | AA19: 足月 | AB19: 9 | AC19: 0 | AD19: C1AC11312150001
A20: RL00011 | B20: CR00020 | C20: =IFERROR(__xludf.DUMMYFUNCTION("""COMPUTED_VALUE"""),"內湖秘境") -> 內湖秘境 | D20: =IFERROR(__xludf.DUMMYFUNCTION("""COMPUTED_VALUE"""),"F") -> F | E20: PP00015 | F20: =IFERROR(__xludf.DUMMYFUNCTION("""COMPUTED_VALUE"""),"楊芯岳") -> 楊芯岳 | G20: 已退租 | H20: 已登記 | I20: 已登記 | J20: 要申請 | K20: 月繳 | L20: 45461 | M20: 45474 | N20: 45838 | O20: 45839 | P20: 45809 | Q20: 365 | R20: 13500 | S20: 13500 | V20: 26000 | W20: 1130618 | X20: 1130701 | Y20: 1140630 | Z20: 標準足月 | AA20: 足月 | AB20: 30 | AC20: 0 | AD20: C1AC11306290008
A21: RL00012 | B21: CR00021 | C21: =IFERROR(__xludf.DUMMYFUNCTION("""COMPUTED_VALUE"""),"內湖秘境") -> 內湖秘境 | D21: =IFERROR(__xludf.DUMMYFUNCTION("""COMPUTED_VALUE"""),"G") -> G | E21: PP00016 | F21: =IFERROR(__xludf.DUMMYFUNCTION("""COMPUTED_VALUE"""),"徐若洹") -> 徐若洹 | G21: 已退租 | H21: 已註銷 | I21: 已登記 | J21: 要申請 | K21: 月繳 | L21: 45250 | M21: 45261 | N21: 45626 | O21: 45597 | P21: 45597 | Q21: 366 | R21: 12600 | S21: 12600 | V21: 25200 | W21: 1121120 | X21: 1121201 | Y21: 1131130 | Z21: 標準足月 | AA21: 足月 | AB21: 30 | AC21: 0 | AD21: C1AC11211200017 | AE21: 已退 | AF21: 已退 | AG21: 已退
A22: RL00012 | B22: CR00022 | C22: =IFERROR(__xludf.DUMMYFUNCTION("""COMPUTED_VALUE"""),"內湖秘境") -> 內湖秘境 | D22: =IFERROR(__xludf.DUMMYFUNCTION("""COMPUTED_VALUE"""),"G") -> G | E22: PP00016 | F22: =IFERROR(__xludf.DUMMYFUNCTION("""COMPUTED_VALUE"""),"徐若洹") -> 徐若洹 | G22: 已退租 | H22: 已登記 | I22: 已登記 | J22: 要申請 | K22: 月繳 | L22: 45579 | M22: 45627 | N22: 45991 | O22: 45992 | P22: 45962 | Q22: 365 | R22: 12600 | S22: 12100 | V22: 25200 | W22: 1131014 | X22: 1131201 | Y22: 1141130 | Z22: 標準足月 | AA22: 足月 | AB22: 30 | AC22: 0 | AD22: C1AC11311010030
A23: RL00014 | B23: CR00023 | C23: =IFERROR(__xludf.DUMMYFUNCTION("""COMPUTED_VALUE"""),"士林和豐") -> 士林和豐 | D23: =IFERROR(__xludf.DUMMYFUNCTION("""COMPUTED_VALUE"""),"B") -> B | E23: PP00017 | F23: =IFERROR(__xludf.DUMMYFUNCTION("""COMPUTED_VALUE"""),"Totto") -> Totto | G23: 已退租 | H23: 已註銷 | I23: 已登記 | J23: 不申請 | K23: 月繳 | M23: 45078 | N23: 45443 | Q23: 366 | R23: 12500 | S23: 12000 | V23: 25000 | X23: 1120601 | Y23: 1130531 | Z23: 標準足月 | AB23: 31 | AC23: 0 | AE23: 已退 | AF23: 已退 | AG23: 已退
A24: RL00015 | B24: CR00024 | C24: =IFERROR(__xludf.DUMMYFUNCTION("""COMPUTED_VALUE"""),"士林和豐") -> 士林和豐 | D24: =IFERROR(__xludf.DUMMYFUNCTION("""COMPUTED_VALUE"""),"C") -> C | E24: PP00018 | F24: =IFERROR(__xludf.DUMMYFUNCTION("""COMPUTED_VALUE"""),"梁譯心") -> 梁譯心 | G24: 已退租 | H24: 已註銷 | I24: 已登記 | J24: 不申請 | K24: 月繳 | M24: 45092 | N24: 45465 | O24: 45444 | Q24: 374 | R24: 11000 | S24: 11000 | V24: 22000 | X24: 1120615 | Y24: 1130622 | AB24: 16 | AC24: #REF! | AE24: 已退 | AF24: 已退 | AG24: 已退
A25: RL00013 | B25: CR00025 | C25: =IFERROR(__xludf.DUMMYFUNCTION("""COMPUTED_VALUE"""),"士林和豐") -> 士林和豐 | D25: =IFERROR(__xludf.DUMMYFUNCTION("""COMPUTED_VALUE"""),"A") -> A | E25: PP00019 | F25: =IFERROR(__xludf.DUMMYFUNCTION("""COMPUTED_VALUE"""),"巫思予") -> 巫思予 | G25: 已退租 | H25: 已註銷 | I25: 已登記 | J25: 不申請 | K25: 月繳 | L25: 45265 | M25: 45271 | N25: 45636 | O25: 45627 | Q25: 366 | R25: 15800 | S25: 15800 | V25: 31600 | W25: 1121205 | X25: 1121211 | Y25: 1131210 | Z25: 標準足月 | AB25: 0 | AC25: 0 | AE25: 已退 | AF25: 已退 | AG25: 已退
A26: RL00013 | B26: CR00026 | C26: =IFERROR(__xludf.DUMMYFUNCTION("""COMPUTED_VALUE"""),"士林和豐") -> 士林和豐 | D26: =IFERROR(__xludf.DUMMYFUNCTION("""COMPUTED_VALUE"""),"A") -> A | E26: PP00020 PP00082 | F26: =IFERROR(__xludf.DUMMYFUNCTION("""COMPUTED_VALUE"""),"許瑜芳 黃俞安") -> 許瑜芳 黃俞安 | G26: 入住中 | H26: 已登記 | I26: 已登記 | J26: 要申請 | K26: 月繳 | L26: 45635 | M26: 45647 | N26: 46112 | O26: 46082 | P26: 46082 | Q26: 466 | R26: 19500 | S26: 19500 | V26: 39000 | W26: 1131209 | X26: 1131221 | Y26: 1150331 | Z26: 首月切到月底 | AA26: 足月 | AB26: 11 | AC26: 0 | AD26: C1AE11312150001
A27: RL00014 | B27: CR00027 | C27: =IFERROR(__xludf.DUMMYFUNCTION("""COMPUTED_VALUE"""),"士林和豐") -> 士林和豐 | D27: =IFERROR(__xludf.DUMMYFUNCTION("""COMPUTED_VALUE"""),"B") -> B | E27: PP00021 | F27: =IFERROR(__xludf.DUMMYFUNCTION("""COMPUTED_VALUE"""),"郭昱慧") -> 郭昱慧 | G27: 已退租 | H27: 已登記 | I27: 已登記 | J27: 要申請 | K27: 月繳 | L27: 45471 | M27: 45474 | N27: 45827 | O27: 45839 | P27: 45838 | Q27: 354 | R27: 14100 | S27: 14100 | V27: 25000 | W27: 1130628 | X27: 1130701 | Y27: 1140619 | Z27: 標準足月 | AA27: 足月 | AB27: 19 | AC27: 0 | AD27: C1AE11306290003 | AE27: 已退 | AF27: 已退 | AG27: 已退 | AH27: 1000
A28: RL00015 | B28: CR00028 | C28: =IFERROR(__xludf.DUMMYFUNCTION("""COMPUTED_VALUE"""),"士林和豐") -> 士林和豐 | D28: =IFERROR(__xludf.DUMMYFUNCTION("""COMPUTED_VALUE"""),"C") -> C | E28: PP00022 | F28: =IFERROR(__xludf.DUMMYFUNCTION("""COMPUTED_VALUE"""),"李宛宸") -> 李宛宸 | G28: 已退租 | H28: 已登記 | I28: 已登記 | J28: 要申請 | K28: 月繳 | L28: 45469 | M28: 45474 | N28: 45828 | O28: 45839 | P28: 45838 | Q28: 355 | R28: 13100 | S28: 13100 | V28: 23000 | W28: 1130626 | X28: 1130701 | Y28: 1140620 | Z28: 標準足月 | AA28: 足月 | AB28: 20 | AC28: 0 | AD28: C1AE11306290002 | AE28: 已退 | AF28: 已退 | AG28: 已退 | AH28: 1000
A29: RL00016 | B29: CR00029 | C29: =IFERROR(__xludf.DUMMYFUNCTION("""COMPUTED_VALUE"""),"士林和豐") -> 士林和豐 | D29: =IFERROR(__xludf.DUMMYFUNCTION("""COMPUTED_VALUE"""),"D") -> D | E29: PP00023 | F29: =IFERROR(__xludf.DUMMYFUNCTION("""COMPUTED_VALUE"""),"曹淑宜") -> 曹淑宜 | G29: 已退租 | H29: 未登記 | I29: 未登記 | J29: 不申請 | K29: 月繳 | L29: 45396 | M29: 45444 | N29: 45808 | O29: 45809 | P29: 45778 | Q29: 365 | R29: 12500 | S29: 12500 | V29: 25000 | W29: 1130414 | X29: 1130601 | Y29: 1140531 | Z29: 標準足月 | AB29: 31 | AC29: #REF!
A30: RL00021 | B30: CR00030 | C30: =IFERROR(__xludf.DUMMYFUNCTION("""COMPUTED_VALUE"""),"龍江229") -> 龍江229 | D30: =IFERROR(__xludf.DUMMYFUNCTION("""COMPUTED_VALUE"""),"E") -> E | E30: PP00024 | F30: =IFERROR(__xludf.DUMMYFUNCTION("""COMPUTED_VALUE"""),"李茂生") -> 李茂生 | G30: 已退租 | H30: 已註銷 | I30: 已登記 | J30: 要申請 | K30: 月繳 | L30: 45296 | M30: 45298 | N30: 45473 | O30: 45474 | P30: 45627 | Q30: 176 | R30: 12500 | S30: 12500 | V30: 25000 | W30: 1130105 | X30: 1130107 | Y30: 1130630 | Z30: 標準足月 | AA30: 足月 | AB30: 24 | AC30: 0 | AD30: C1AC11301060004 | AE30: 27 | AF30: 372 | AH30: 已退601 | AI30: 完成
A31: RL00017 | B31: CR00031 | C31: =IFERROR(__xludf.DUMMYFUNCTION("""COMPUTED_VALUE"""),"龍江229") -> 龍江229 | D31: =IFERROR(__xludf.DUMMYFUNCTION("""COMPUTED_VALUE"""),"A") -> A | E31: PP00025 | F31: =IFERROR(__xludf.DUMMYFUNCTION("""COMPUTED_VALUE"""),"莊美娟") -> 莊美娟 | G31: 已退租 | H31: 已登記 | I31: 已登記 | J31: 要申請 | K31: 月繳 | L31: 45297 | M31: 45306 | N31: 45716 | O31: 45717 | P31: 45689 | Q31: 411 | R31: 12800 | S31: 12800 | V31: 25600 | W31: 1130106 | X31: 1130115 | Y31: 1140228 | AA31: 不足月 | AB31: 14 | AC31: #REF! | AD31: C1AC11301060003 | AH31: 沒有扣, 他要自己處理 | AI31: 完成
A32: RL00018 | B32: CR00032 | C32: =IFERROR(__xludf.DUMMYFUNCTION("""COMPUTED_VALUE"""),"龍江229") -> 龍江229 | D32: =IFERROR(__xludf.DUMMYFUNCTION("""COMPUTED_VALUE"""),"B") -> B | E32: PP00026 | F32: =IFERROR(__xludf.DUMMYFUNCTION("""COMPUTED_VALUE"""),"陳佩娟") -> 陳佩娟 | G32: 已退租 | H32: 已登記 | I32: 已登記 | J32: 要申請 | K32: 月繳 | L32: 45305 | M32: 45310 | N32: 45716 | O32: 45717 | P32: 45689 | Q32: 407 | R32: 13000 | S32: 13000 | V32: 26000 | W32: 1130114 | X32: 1130119 | Y32: 1140228 | AA32: 不足月 | AB32: 10 | AC32: #REF! | AD32: C1AC11301230001 | AH32: 沒有扣, 他要自己處理 | AI32: 完成
A33: RL00019 | B33: CR00033 | C33: =IFERROR(__xludf.DUMMYFUNCTION("""COMPUTED_VALUE"""),"龍江229") -> 龍江229 | D33: =IFERROR(__xludf.DUMMYFUNCTION("""COMPUTED_VALUE"""),"C") -> C | E33: PP00027 | F33: =IFERROR(__xludf.DUMMYFUNCTION("""COMPUTED_VALUE"""),"陳雨彤") -> 陳雨彤 | G33: 已退租 | H33: 已登記 | I33: 已登記 | J33: 要申請 | K33: 月繳 | L33: 45299 | M33: 45311 | N33: 45716 | O33: 45717 | P33: 45689 | Q33: 406 | R33: 16800 | S33: 16800 | V33: 33600 | W33: 1130108 | X33: 1130120 | Y33: 1140228 | AA33: 不足月 | AB33: 9 | AC33: #REF! | AD33: C1AC11301090001
A34: RL00020 | B34: CR00034 | C34: =IFERROR(__xludf.DUMMYFUNCTION("""COMPUTED_VALUE"""),"龍江229") -> 龍江229 | D34: =IFERROR(__xludf.DUMMYFUNCTION("""COMPUTED_VALUE"""),"D") -> D | E34: PP00028 | F34: =IFERROR(__xludf.DUMMYFUNCTION("""COMPUTED_VALUE"""),"黃依婷") -> 黃依婷 | G34: 已退租 | H34: 已登記 | I34: 已登記 | J34: 要申請 | K34: 月繳 | L34: 45297 | M34: 45300 | N34: 45716 | O34: 45717 | P34: 45689 | Q34: 417 | R34: 13300 | S34: 13300 | V34: 26600 | W34: 1130106 | X34: 1130109 | Y34: 1140228 | AA34: 不足月 | AB34: 20 | AC34: #REF! | AD34: C1AC11301060005
A35: RL00021 | B35: CR00035 | C35: =IFERROR(__xludf.DUMMYFUNCTION("""COMPUTED_VALUE"""),"龍江229") -> 龍江229 | D35: =IFERROR(__xludf.DUMMYFUNCTION("""COMPUTED_VALUE"""),"E") -> E | E35: PP00029 | F35: =IFERROR(__xludf.DUMMYFUNCTION("""COMPUTED_VALUE"""),"許霈琪") -> 許霈琪 | G35: 已退租 | H35: 已登記 | I35: 已登記 | J35: 要申請 | K35: 月繳 | L35: 45467 | M35: 45474 | N35: 45716 | O35: 45717 | P35: 45809 | Q35: 243 | R35: 13500 | S35: 13500 | V35: 27000 | W35: 1130624 | X35: 1130701 | Y35: 1140228 | Z35: 標準足月 | AA35: 足月 | AB35: 28 | AC35: 0 | AD35: C1AC11307110007
A36: RL00023 | B36: CR00036 | C36: =IFERROR(__xludf.DUMMYFUNCTION("""COMPUTED_VALUE"""),"哈拉對面") -> 哈拉對面 | D36: =IFERROR(__xludf.DUMMYFUNCTION("""COMPUTED_VALUE"""),"B") -> B | E36: PP00030 | F36: =IFERROR(__xludf.DUMMYFUNCTION("""COMPUTED_VALUE"""),"林宜芳") -> 林宜芳 | G36: 已退租 | H36: 已註銷 | I36: 已登記 | J36: 要申請 | K36: 月繳 | L36: 45335 | M36: 45335 | N36: 45514 | O36: 45506 | P36: 45505 | Q36: 180 | R36: 19100 | S36: 19100 | V36: 38200 | W36: 1130213 | X36: 1130213 | Y36: 1130810 | AA36: 不足月 | AB36: 12 | AC36: #REF! | AD36: C1AC11302270001 | AE36: 已退 | AF36: 已退 | AG36: 已退
A37: RL00022 | B37: CR00037 | C37: =IFERROR(__xludf.DUMMYFUNCTION("""COMPUTED_VALUE"""),"哈拉對面") -> 哈拉對面 | D37: =IFERROR(__xludf.DUMMYFUNCTION("""COMPUTED_VALUE"""),"A") -> A | E37: PP00031 | F37: =IFERROR(__xludf.DUMMYFUNCTION("""COMPUTED_VALUE"""),"李柏緯") -> 李柏緯 | G37: 已退租 | H37: 已登記 | I37: 已登記 | J37: 要申請 | K37: 月繳 | L37: 45351 | M37: 45355 | N37: 45719 | O37: 45748 | P37: 45717 | Q37: 365 | R37: 11300 | S37: 11300 | V37: 22600 | W37: 1130229 | X37: 1130304 | Y37: 1140303 | Z37: 標準足月 | AA37: 不足月 | AB37: 3 | AC37: #REF! | AD37: C1AC11303140017
A38: RL00023 | B38: CR00038 | C38: =IFERROR(__xludf.DUMMYFUNCTION("""COMPUTED_VALUE"""),"哈拉對面") -> 哈拉對面 | D38: =IFERROR(__xludf.DUMMYFUNCTION("""COMPUTED_VALUE"""),"B") -> B | E38: PP00032 | F38: =IFERROR(__xludf.DUMMYFUNCTION("""COMPUTED_VALUE"""),"黃彥瑞") -> 黃彥瑞 | G38: 已退租 | H38: 已登記 | I38: 已登記 | J38: 要申請 | K38: 月繳 | L38: 45525 | M38: 45536 | N38: 45716 | O38: 45717 | P38: 45870 | Q38: 181 | R38: 15800 | S38: 15800 | V38: 31600 | W38: 1130821 | X38: 1130901 | Y38: 1140228 | Z38: 標準足月 | AA38: 足月 | AB38: 28 | AC38: 0 | AD38: C1AC11308260025 | AG38: 600
A39: RL00024 | B39: CR00039 | C39: =IFERROR(__xludf.DUMMYFUNCTION("""COMPUTED_VALUE"""),"哈拉對面") -> 哈拉對面 | D39: =IFERROR(__xludf.DUMMYFUNCTION("""COMPUTED_VALUE"""),"C") -> C | E39: PP00033 | F39: =IFERROR(__xludf.DUMMYFUNCTION("""COMPUTED_VALUE"""),"徐鉦庭") -> 徐鉦庭 | G39: 已退租 | H39: 已登記 | I39: 已登記 | J39: 要申請 | K39: 月繳 | L39: 45327 | M39: 45366 | N39: 45730 | O39: 45748 | P39: 45717 | Q39: 365 | R39: 11800 | S39: 11800 | V39: 23600 | W39: 1130205 | X39: 1130315 | Y39: 1140314 | Z39: 標準足月 | AA39: 不足月 | AB39: 14 | AC39: #REF! | AD39: C1AC11302270002
A40: RL00025 | B40: CR00040 | C40: =IFERROR(__xludf.DUMMYFUNCTION("""COMPUTED_VALUE"""),"哈拉對面") -> 哈拉對面 | D40: =IFERROR(__xludf.DUMMYFUNCTION("""COMPUTED_VALUE"""),"D") -> D | E40: PP00034 | F40: =IFERROR(__xludf.DUMMYFUNCTION("""COMPUTED_VALUE"""),"柳翰洋") -> 柳翰洋 | G40: 已退租 | H40: 已登記 | I40: 已登記 | J40: 要申請 | K40: 月繳 | L40: 45358 | M40: 45359 | N40: 45723 | O40: 45748 | P40: 45717 | Q40: 365 | R40: 12300 | S40: 12300 | V40: 24600 | W40: 1130307 | X40: 1130308 | Y40: 1140307 | Z40: 標準足月 | AA40: 不足月 | AB40: 7 | AC40: #REF! | AD40: C1AC11303140016
A41: RL00026 | B41: CR00041 | C41: =IFERROR(__xludf.DUMMYFUNCTION("""COMPUTED_VALUE"""),"北醫醫師府") -> 北醫醫師府 | D41: =IFERROR(__xludf.DUMMYFUNCTION("""COMPUTED_VALUE"""),"A") -> A | E41: PP00035 | F41: =IFERROR(__xludf.DUMMYFUNCTION("""COMPUTED_VALUE"""),"鄭伊彤") -> 鄭伊彤 | G41: 已退租 | H41: 已註銷 | I41: 已登記 | J41: 要申請 | K41: 月繳 | L41: 45395 | M41: 45397 | N41: 45619 | O41: 45597 | P41: 45717 | Q41: 223 | R41: 13500 | S41: 13500 | V41: 27000 | W41: 1130413 | X41: 1130415 | Y41: 1131123 | Z41: 標準足月 | AA41: 足月 | AB41: 9 | AC41: 0 | AD41: C1AD11305020009 | AH41: 沒有扣, 他要自己處理 | AI41: 完成
A42: RL00027 | B42: CR00043 | C42: =IFERROR(__xludf.DUMMYFUNCTION("""COMPUTED_VALUE"""),"北醫醫師府") -> 北醫醫師府 | D42: =IFERROR(__xludf.DUMMYFUNCTION("""COMPUTED_VALUE"""),"B") -> B | E42: PP00036 PP00084 | F42: =IFERROR(__xludf.DUMMYFUNCTION("""COMPUTED_VALUE"""),"王品涵 賴泓賓") -> 王品涵 賴泓賓 | G42: 已退租 | H42: 已登記 | I42: 已登記 | J42: 要申請 | K42: 月繳 | L42: 45527 | M42: 45525 | N42: 45777 | O42: 45778 | P42: 45748 | Q42: 253 | R42: 19800 | S42: 19800 | V42: 39600 | W42: 1130823 | X42: 1130821 | Y42: 1140430 | Z42: 標準足月 | AA42: 不足月 | AB42: 10 | AC42: #REF! | AD42: C1AD11308260012
A43: RL00028 | B43: CR00044 | C43: =IFERROR(__xludf.DUMMYFUNCTION("""COMPUTED_VALUE"""),"北醫醫師府") -> 北醫醫師府 | D43: =IFERROR(__xludf.DUMMYFUNCTION("""COMPUTED_VALUE"""),"C") -> C | E43: PP00037 | F43: =IFERROR(__xludf.DUMMYFUNCTION("""COMPUTED_VALUE"""),"余典蓉") -> 余典蓉 | G43: 已退租 | H43: 已登記 | I43: 已登記 | J43: 要申請 | K43: 月繳 | L43: 45387 | M43: 45403 | N43: 45858 | O43: 45870 | P43: 45809 | Q43: 456 | R43: 13000 | S43: 13000 | V43: 26000 | W43: 1130405 | X43: 1130421 | Y43: 1140720 | AA43: 足月 | AB43: 0 | AC43: 0 | AD43: C1AD11304090002
A44: RL00029 | B44: CR00045 | C44: =IFERROR(__xludf.DUMMYFUNCTION("""COMPUTED_VALUE"""),"北醫醫師府") -> 北醫醫師府 | D44: =IFERROR(__xludf.DUMMYFUNCTION("""COMPUTED_VALUE"""),"D") -> D | E44: PP00038 | F44: =IFERROR(__xludf.DUMMYFUNCTION("""COMPUTED_VALUE"""),"劉怡秀") -> 劉怡秀 | G44: 已退租 | H44: 已登記 | I44: 已登記 | J44: 要申請 | K44: 月繳 | L44: 45397 | M44: 45405 | N44: 45769 | O44: 45778 | P44: 45717 | Q44: 365 | R44: 12000 | S44: 12000 | V44: 24000 | W44: 1130415 | X44: 1130423 | Y44: 1140422 | Z44: 標準足月 | AA44: 足月 | AB44: 0 | AC44: 0 | AD44: C1AD11305020010
A45: RL00030 | B45: CR00046 | C45: =IFERROR(__xludf.DUMMYFUNCTION("""COMPUTED_VALUE"""),"北醫醫師府") -> 北醫醫師府 | D45: =IFERROR(__xludf.DUMMYFUNCTION("""COMPUTED_VALUE"""),"E") -> E | E45: PP00039 | F45: =IFERROR(__xludf.DUMMYFUNCTION("""COMPUTED_VALUE"""),"洪睿佑") -> 洪睿佑 | G45: 已退租 | H45: 已登記 | I45: 已登記 | J45: 要申請 | K45: 月繳 | L45: 45384 | M45: 45413 | N45: 45838 | O45: 45839 | P45: 45809 | Q45: 426 | R45: 14800 | S45: 14800 | V45: 29600 | W45: 1130402 | X45: 1130501 | Y45: 1140630 | AA45: 足月 | AB45: 30 | AC45: 0 | AD45: C1AD11304090003 | AG45: 750 | AH45: 1000
A46: RL00031 | B46: CR00047 | C46: =IFERROR(__xludf.DUMMYFUNCTION("""COMPUTED_VALUE"""),"北醫醫師府") -> 北醫醫師府 | D46: =IFERROR(__xludf.DUMMYFUNCTION("""COMPUTED_VALUE"""),"F") -> F | E46: PP00040 | F46: =IFERROR(__xludf.DUMMYFUNCTION("""COMPUTED_VALUE"""),"林雍勳") -> 林雍勳 | G46: 已退租 | H46: 已登記 | I46: 已登記 | J46: 要申請 | K46: 月繳 | L46: 45384 | M46: 45413 | N46: 45838 | O46: 45839 | P46: 45809 | Q46: 426 | R46: 14800 | S46: 14800 | V46: 29600 | W46: 1130402 | X46: 1130501 | Y46: 1140630 | AA46: 足月 | AB46: 30 | AC46: 0 | AD46: C1AD11304090004 | AG46: 750 | AH46: 1000
A47: RL00034 | B47: CR00048 | C47: =IFERROR(__xludf.DUMMYFUNCTION("""COMPUTED_VALUE"""),"大湖山莊") -> 大湖山莊 | D47: =IFERROR(__xludf.DUMMYFUNCTION("""COMPUTED_VALUE"""),"C") -> C | E47: PP00041 | F47: =IFERROR(__xludf.DUMMYFUNCTION("""COMPUTED_VALUE"""),"吳亭逸") -> 吳亭逸 | G47: 已退租 | H47: 已註銷 | I47: 已登記 | J47: 要申請 | K47: 月繳 | L47: 45428 | M47: 45431 | N47: 45468 | O47: 45474 | P47: 45778 | Q47: 38 | R47: 18800 | S47: 18800 | V47: 37600 | W47: 1130516 | X47: 1130519 | Y47: 1130625 | Z47: 首月切到月底 | AA47: 足月 | AB47: 7 | AC47: 0 | AD47: C1AC11306020003 | AE47: 已退 | AF47: 已退 | AG47: 已退
A48: RL00032 | B48: CR00049 | C48: =IFERROR(__xludf.DUMMYFUNCTION("""COMPUTED_VALUE"""),"大湖山莊") -> 大湖山莊 | D48: =IFERROR(__xludf.DUMMYFUNCTION("""COMPUTED_VALUE"""),"A") -> A | E48: PP00042 | F48: =IFERROR(__xludf.DUMMYFUNCTION("""COMPUTED_VALUE"""),"熊翊丞") -> 熊翊丞 | G48: 已退租 | H48: 已登記 | I48: 已登記 | J48: 要申請 | K48: 月繳 | L48: 45431 | M48: 45444 | N48: 45838 | O48: 45839 | P48: 45809 | Q48: 395 | R48: 13300 | S48: 13300 | V48: 26600 | W48: 1130519 | X48: 1130601 | Y48: 1140630 | Z48: 標準足月 | AA48: 足月 | AB48: 30 | AC48: 0 | AD48: C1AC11306020001 | AE48: 37 | AF48: 855 | AG48: 208 | AH48: 1000 | AI48: -100
A49: RL00033 | B49: CR00050 | C49: =IFERROR(__xludf.DUMMYFUNCTION("""COMPUTED_VALUE"""),"大湖山莊") -> 大湖山莊 | D49: =IFERROR(__xludf.DUMMYFUNCTION("""COMPUTED_VALUE"""),"B") -> B | E49: PP00043 | F49: =IFERROR(__xludf.DUMMYFUNCTION("""COMPUTED_VALUE"""),"施惠卿") -> 施惠卿 | G49: 已退租 | H49: 已登記 | I49: 已登記 | J49: 要申請 | K49: 月繳 | L49: 45428 | M49: 45443 | N49: 45789 | O49: 45809 | P49: 45778 | Q49: 347 | R49: 12800 | S49: 12800 | V49: 25600 | W49: 1130516 | X49: 1130531 | Y49: 1140512 | Z49: 標準足月 | AA49: 足月 | AB49: 0 | AC49: 0 | AD49: C1AC11306020002 | AE49: 52 | AF49: 611 | AG49: 65 | AH49: 1000 | AI49: 完成
A50: RL00034 | B50: CR00051 | C50: =IFERROR(__xludf.DUMMYFUNCTION("""COMPUTED_VALUE"""),"大湖山莊") -> 大湖山莊 | D50: =IFERROR(__xludf.DUMMYFUNCTION("""COMPUTED_VALUE"""),"C") -> C | E50: PP00044 | F50: =IFERROR(__xludf.DUMMYFUNCTION("""COMPUTED_VALUE"""),"姚伯謙") -> 姚伯謙 | G50: 已退租 | H50: 已登記 | I50: 已登記 | J50: 要申請 | K50: 月繳 | L50: 45463 | M50: 45474 | N50: 45838 | O50: 45839 | P50: 45809 | Q50: 365 | R50: 18800 | S50: 18800 | V50: 37600 | W50: 1130620 | X50: 1130701 | Y50: 1140630 | Z50: 標準足月 | AA50: 足月 | AB50: 30 | AC50: 0 | AD50: C1AC11306290007
A51: RL00035 | B51: CR00052 | C51: =IFERROR(__xludf.DUMMYFUNCTION("""COMPUTED_VALUE"""),"大湖山莊") -> 大湖山莊 | D51: =IFERROR(__xludf.DUMMYFUNCTION("""COMPUTED_VALUE"""),"D") -> D | E51: PP00045 | F51: =IFERROR(__xludf.DUMMYFUNCTION("""COMPUTED_VALUE"""),"陳昭瑄") -> 陳昭瑄 | G51: 已退租 | H51: 已登記 | I51: 已登記 | J51: 要申請 | K51: 月繳 | L51: 45428 | M51: 45444 | N51: 45808 | O51: 45809 | P51: 45778 | Q51: 365 | R51: 14300 | S51: 14300 | V51: 28600 | W51: 1130516 | X51: 1130601 | Y51: 1140531 | Z51: 標準足月 | AA51: 足月 | AB51: 31 | AC51: 0 | AD51: C1AC11306020004
A52: RL00036 | B52: CR00053 | C52: =IFERROR(__xludf.DUMMYFUNCTION("""COMPUTED_VALUE"""),"大湖山莊") -> 大湖山莊 | D52: =IFERROR(__xludf.DUMMYFUNCTION("""COMPUTED_VALUE"""),"E") -> E | E52: PP00046 | F52: =IFERROR(__xludf.DUMMYFUNCTION("""COMPUTED_VALUE"""),"吳彥霆") -> 吳彥霆 | G52: 已退租 | H52: 已登記 | I52: 已登記 | J52: 要申請 | K52: 月繳 | L52: 45451 | M52: 45452 | N52: 45838 | O52: 45839 | P52: 45809 | Q52: 387 | R52: 12500 | S52: 12500 | V52: 25000 | W52: 1130608 | X52: 1130609 | Y52: 1140630 | Z52: 首月切到月底 | AA52: 足月 | AB52: 22 | AC52: 0 | AD52: C1AC11306290006 | AE52: 37 | AF52: 855 | AG52: 208 | AH52: 1000 | AI52: -100
A53: RL00037 | B53: CR00054 | C53: =IFERROR(__xludf.DUMMYFUNCTION("""COMPUTED_VALUE"""),"大湖山莊") -> 大湖山莊 | D53: =IFERROR(__xludf.DUMMYFUNCTION("""COMPUTED_VALUE"""),"F") -> F | E53: PP00047 PP00085 | F53: =IFERROR(__xludf.DUMMYFUNCTION("""COMPUTED_VALUE"""),"吳智方 蘇婉彤") -> 吳智方 蘇婉彤 | G53: 已退租 | H53: 已登記 | I53: 已登記 | J53: 要申請 | K53: 月繳 | L53: 45481 | M53: 45488 | N53: 45852 | O53: 45870 | P53: 45839 | Q53: 365 | R53: 18000 | S53: 18000 | V53: 36000 | W53: 1130708 | X53: 1130715 | Y53: 1140714 | Z53: 標準足月 | AA53: 足月 | AB53: 0 | AC53: 0 | AD53: C1AC11307110009 | AE53: 106 | AF53: 2415 | AG53: 171 | AH53: 2000 | AI53: -692
A54: RL00038 | B54: CR00055 | C54: =IFERROR(__xludf.DUMMYFUNCTION("""COMPUTED_VALUE"""),"大湖山莊") -> 大湖山莊 | D54: =IFERROR(__xludf.DUMMYFUNCTION("""COMPUTED_VALUE"""),"G") -> G | E54: PP00048 | F54: =IFERROR(__xludf.DUMMYFUNCTION("""COMPUTED_VALUE"""),"林文心") -> 林文心 | G54: 已退租 | H54: 已登記 | I54: 已登記 | J54: 要申請 | K54: 月繳 | L54: 45428 | M54: 45430 | N54: 45712 | O54: 45717 | P54: 45809 | Q54: 283 | R54: 15000 | S54: 15000 | V54: 30000 | W54: 1130516 | X54: 1130518 | Y54: 1140224 | Z54: 首月切到月底 | AA54: 足月 | AB54: 7 | AC54: 0 | AD54: C1AC11306020005 | AE54: 34 | AF54: 275 | AG54: 25 | AH54: 3000 | AI54: 完成
A55: RL00039 | B55: CR00056 | C55: =IFERROR(__xludf.DUMMYFUNCTION("""COMPUTED_VALUE"""),"市府爺爺家") -> 市府爺爺家 | D55: =IFERROR(__xludf.DUMMYFUNCTION("""COMPUTED_VALUE"""),"A") -> A | E55: PP00049 | F55: =IFERROR(__xludf.DUMMYFUNCTION("""COMPUTED_VALUE"""),"蔡艾霖") -> 蔡艾霖 | G55: 已退租 | H55: 已註銷 | I55: 已登記 | J55: 要申請 | K55: 月繳 | L55: 45503 | M55: 45503 | N55: 45565 | O55: 45566 | P55: 45839 | Q55: 63 | R55: 23000 | S55: 23000 | V55: 46000 | W55: 1130730 | X55: 1130730 | Y55: 1130930 | Z55: 標準足月 | AA55: 足月 | AB55: 1 | AC55: 0 | AD55: C1AD11308060001 | AE55: 已退 | AF55: 已退 | AG55: 已退 | AI55: 完成
A56: RL00039 | B56: CR00057 | C56: =IFERROR(__xludf.DUMMYFUNCTION("""COMPUTED_VALUE"""),"市府爺爺家") -> 市府爺爺家 | D56: =IFERROR(__xludf.DUMMYFUNCTION("""COMPUTED_VALUE"""),"A") -> A | E56: PP00050 PP00086 | F56: =IFERROR(__xludf.DUMMYFUNCTION("""COMPUTED_VALUE"""),"董書鵬 張瑋珊") -> 董書鵬 張瑋珊 | G56: 已退租 | H56: 已登記 | I56: 已登記 | J56: 要申請 | K56: 月繳 | L56: 45578 | M56: 45578 | N56: 45961 | O56: 45962 | P56: 45931 | Q56: 384 | R56: 22000 | S56: 22000 | V56: 44000 | W56: 1131013 | X56: 1131013 | Y56: 1141031 | Z56: 首月切到月底 | AA56: 足月 | AB56: 19 | AC56: 0 | AD56: C1AD11310170001
A57: RL00040 | B57: CR00058 | C57: =IFERROR(__xludf.DUMMYFUNCTION("""COMPUTED_VALUE"""),"南港站挑高宅") -> 南港站挑高宅 | D57: =IFERROR(__xludf.DUMMYFUNCTION("""COMPUTED_VALUE"""),"A") -> A | E57: PP00051 | F57: =IFERROR(__xludf.DUMMYFUNCTION("""COMPUTED_VALUE"""),"莊以祺") -> 莊以祺 | G57: 已退租 | H57: 已登記 | I57: 已登記 | J57: 要申請 | K57: 月繳 | L57: 45526 | M57: 45536 | N57: 45900 | O57: 45901 | P57: 45870 | Q57: 365 | R57: 13000 | S57: 13000 | V57: 26000 | W57: 1130822 | X57: 1130901 | Y57: 1140831 | Z57: 標準足月 | AA57: 足月 | AB57: 31 | AC57: 0 | AD57: C1AD11308260011
A58: RL00041 | B58: CR00059 | C58: =IFERROR(__xludf.DUMMYFUNCTION("""COMPUTED_VALUE"""),"南港站挑高宅") -> 南港站挑高宅 | D58: =IFERROR(__xludf.DUMMYFUNCTION("""COMPUTED_VALUE"""),"B") -> B | E58: PP00052 | F58: =IFERROR(__xludf.DUMMYFUNCTION("""COMPUTED_VALUE"""),"林鍇蓓") -> 林鍇蓓 | G58: 已退租 | H58: 已登記 | I58: 已登記 | J58: 要申請 | K58: 月繳 | L58: 45535 | M58: 45536 | N58: 45893 | O58: 45901 | P58: 45870 | Q58: 358 | R58: 12300 | S58: 12300 | V58: 24600 | W58: 1130831 | X58: 1130901 | Y58: 1140824 | Z58: 標準足月 | AA58: 足月 | AB58: 24 | AC58: 0 | AD58: C1AD11309030001 | AE58: 354 | AF58: 955 | AG58: 288 | AH58: 3000 | AI58: 完成
A59: RL00042 | B59: CR00060 | C59: =IFERROR(__xludf.DUMMYFUNCTION("""COMPUTED_VALUE"""),"南港站挑高宅") -> 南港站挑高宅 | D59: =IFERROR(__xludf.DUMMYFUNCTION("""COMPUTED_VALUE"""),"C") -> C | E59: PP00053 | F59: =IFERROR(__xludf.DUMMYFUNCTION("""COMPUTED_VALUE"""),"王子昇") -> 王子昇 | G59: 已退租 | H59: 已登記 | I59: 已登記 | J59: 要申請 | K59: 月繳 | L59: 45542 | M59: 45550 | N59: 45689 | O59: 45689 | P59: 45901 | Q59: 140 | R59: 15800 | S59: 15800 | V59: 31600 | W59: 1130907 | X59: 1130915 | Y59: 1140201 | Z59: 標準足月 | AA59: 足月 | AB59: -13 | AC59: 0 | AD59: C1AD11309200002 | AE59: 185 | AF59: 185 | AG59: 0 | AH59: 3000 | AI59: 完成
A60: RL00043 | B60: CR00061 | C60: =IFERROR(__xludf.DUMMYFUNCTION("""COMPUTED_VALUE"""),"南港站挑高宅") -> 南港站挑高宅 | D60: =IFERROR(__xludf.DUMMYFUNCTION("""COMPUTED_VALUE"""),"D") -> D | E60: PP00054 | F60: =IFERROR(__xludf.DUMMYFUNCTION("""COMPUTED_VALUE"""),"吳城慕") -> 吳城慕 | G60: 已退租 | H60: 已登記 | I60: 已登記 | J60: 要申請 | K60: 月繳 | L60: 45526 | M60: 45528 | N60: 45900 | O60: 45901 | P60: 45870 | Q60: 373 | R60: 14300 | S60: 14300 | V60: 28600 | W60: 1130822 | X60: 1130824 | Y60: 1140831 | Z60: 標準足月 | AA60: 足月 | AB60: 8 | AC60: 0 | AD60: C1AD11308260013
A61: RL00044 | B61: CR00062 | C61: =IFERROR(__xludf.DUMMYFUNCTION("""COMPUTED_VALUE"""),"南港站挑高宅") -> 南港站挑高宅 | D61: =IFERROR(__xludf.DUMMYFUNCTION("""COMPUTED_VALUE"""),"E") -> E | E61: PP00055 | F61: =IFERROR(__xludf.DUMMYFUNCTION("""COMPUTED_VALUE"""),"張劉明翔") -> 張劉明翔 | G61: 已退租 | H61: 已登記 | I61: 已登記 | J61: 要申請 | K61: 月繳 | L61: 45526 | M61: 45536 | N61: 45900 | O61: 45901 | P61: 45870 | Q61: 365 | R61: 12800 | S61: 12800 | V61: 25600 | W61: 1130822 | X61: 1130901 | Y61: 1140831 | Z61: 標準足月 | AA61: 足月 | AB61: 31 | AC61: 0 | AD61: C1AD11308260014
A62: RL00045 | B62: CR00063 | C62: =IFERROR(__xludf.DUMMYFUNCTION("""COMPUTED_VALUE"""),"金龍帽子先生") -> 金龍帽子先生 | D62: =IFERROR(__xludf.DUMMYFUNCTION("""COMPUTED_VALUE"""),"A") -> A | E62: PP00056 | F62: =IFERROR(__xludf.DUMMYFUNCTION("""COMPUTED_VALUE"""),"范裕哲") -> 范裕哲 | G62: 已退租 | H62: 已註銷 | I62: 已登記 | J62: 要申請 | K62: 月繳 | L62: 45565 | M62: 45580 | N62: 45616 | O62: 45627 | P62: 45931 | Q62: 37 | R62: 18800 | S62: 18800 | V62: 37600 | W62: 1130930 | X62: 1131015 | Y62: 1131120 | Z62: 首月切到月底 | AA62: 足月 | AB62: 6 | AC62: 0 | AD62: C1AC11310010002 | AH62: 3000 | AI62: 完成
A63: RL00046 | B63: CR00064 | C63: =IFERROR(__xludf.DUMMYFUNCTION("""COMPUTED_VALUE"""),"金龍帽子先生") -> 金龍帽子先生 | D63: =IFERROR(__xludf.DUMMYFUNCTION("""COMPUTED_VALUE"""),"B") -> B | E63: PP00057 | F63: =IFERROR(__xludf.DUMMYFUNCTION("""COMPUTED_VALUE"""),"羅宇潔") -> 羅宇潔 | G63: 已退租 | H63: 已註銷 | I63: 已登記 | J63: 要申請 | K63: 月繳 | L63: 45561 | M63: 45570 | N63: 45606 | O63: 45627 | P63: 45992 | Q63: 37 | R63: 13300 | S63: 13300 | V63: 26600 | W63: 1130926 | X63: 1131005 | Y63: 1131110 | Z63: 首月切到月底 | AA63: 足月 | AB63: 6 | AC63: 0 | AD63: C1AC11310010003 | AH63: 3000 | AI63: 完成
A64: RL00045 | B64: CR00065 | C64: =IFERROR(__xludf.DUMMYFUNCTION("""COMPUTED_VALUE"""),"金龍帽子先生") -> 金龍帽子先生 | D64: =IFERROR(__xludf.DUMMYFUNCTION("""COMPUTED_VALUE"""),"A") -> A | E64: PP00058 | F64: =IFERROR(__xludf.DUMMYFUNCTION("""COMPUTED_VALUE"""),"何佩勳") -> 何佩勳 | G64: 入住中 | H64: 已登記 | I64: 已登記 | J64: 要申請 | K64: 月繳 | L64: 45616 | M64: 45627 | N64: 46081 | O64: 46082 | P64: 46054 | Q64: 455 | R64: 17200 | S64: 17200 | T64: 0 | U64: 17200 | V64: 34400 | W64: 1131120 | X64: 1131201 | Y64: 1150228 | Z64: 標準足月 | AA64: 足月 | AB64: 28 | AC64: 0 | AD64: C1AC11312090001
A65: RL00046 | B65: CR00066 | C65: =IFERROR(__xludf.DUMMYFUNCTION("""COMPUTED_VALUE"""),"金龍帽子先生") -> 金龍帽子先生 | D65: =IFERROR(__xludf.DUMMYFUNCTION("""COMPUTED_VALUE"""),"B") -> B | E65: PP00059 | F65: =IFERROR(__xludf.DUMMYFUNCTION("""COMPUTED_VALUE"""),"謝紫芩") -> 謝紫芩 | G65: 入住中 | H65: 已登記 | I65: 已登記 | J65: 要申請 | K65: 月繳 | L65: 45608 | M65: 45626 | N65: 46081 | O65: 46082 | P65: 46054 | Q65: 456 | R65: 12700 | S65: 12700 | T65: 0 | U65: 12700 | V65: 25400 | W65: 1131112 | X65: 1131130 | Y65: 1150228 | Z65: 標準足月 | AA65: 足月 | AB65: -1 | AC65: 0 | AD65: C1AC11311180001
A66: RL00047 | B66: CR00067 | C66: =IFERROR(__xludf.DUMMYFUNCTION("""COMPUTED_VALUE"""),"金龍帽子先生") -> 金龍帽子先生 | D66: =IFERROR(__xludf.DUMMYFUNCTION("""COMPUTED_VALUE"""),"C") -> C | E66: PP00060 | F66: =IFERROR(__xludf.DUMMYFUNCTION("""COMPUTED_VALUE"""),"李侑芯") -> 李侑芯 | G66: 已退租 | H66: 已登記 | I66: 已登記 | J66: 要申請 | K66: 月繳 | L66: 45560 | M66: 45570 | N66: 45693 | O66: 45717 | P66: 45901 | Q66: 124 | R66: 14800 | S66: 14800 | V66: 29600 | W66: 1130925 | X66: 1131005 | Y66: 1140205 | Z66: 標準足月 | AA66: 足月 | AB66: 1 | AC66: 0 | AD66: C1AC11310010005 | AH66: 3000 | AI66: 完成
A67: RL00048 | B67: CR00068 | C67: =IFERROR(__xludf.DUMMYFUNCTION("""COMPUTED_VALUE"""),"金龍帽子先生") -> 金龍帽子先生 | D67: =IFERROR(__xludf.DUMMYFUNCTION("""COMPUTED_VALUE"""),"D") -> D | E67: PP00061 | F67: =IFERROR(__xludf.DUMMYFUNCTION("""COMPUTED_VALUE"""),"劉曉婷") -> 劉曉婷 | G67: 已退租 | H67: 已註銷 | I67: 已登記 | J67: 要申請 | K67: 月繳 | L67: 45563 | M67: 45566 | N67: 45599 | O67: 45597 | P67: 45901 | Q67: 34 | R67: 15800 | S67: 15800 | V67: 31600 | W67: 1130928 | X67: 1131001 | Y67: 1131103 | Z67: 標準足月 | AA67: 足月 | AB67: 3 | AC67: 0 | AD67: C1AC11310010004 | AE67: 53 | AF67: 206 | AG67: 77 | AH67: 3000 | AI67: 完成
A68: RL00048 | B68: CR00069 | C68: =IFERROR(__xludf.DUMMYFUNCTION("""COMPUTED_VALUE"""),"金龍帽子先生") -> 金龍帽子先生 | D68: =IFERROR(__xludf.DUMMYFUNCTION("""COMPUTED_VALUE"""),"D") -> D | E68: PP00062 | F68: =IFERROR(__xludf.DUMMYFUNCTION("""COMPUTED_VALUE"""),"蔡婷欣") -> 蔡婷欣 | G68: 已退租 | H68: 已登記 | I68: 已登記 | J68: 要申請 | K68: 月繳 | L68: 45616 | M68: 45617 | N68: 45777 | O68: 45778 | P68: 45962 | Q68: 161 | R68: 14500 | S68: 14500 | V68: 29000 | W68: 1131120 | X68: 1131121 | Y68: 1140430 | Z68: 標準足月 | AA68: 足月 | AB68: 10 | AC68: 0 | AD68: C1AC11312010008 | AE68: 79 | AF68: 349 | AG68: 40 | AH68: 3000 | AI68: 完成
A69: RL00049 | B69: CR00070 | C69: =IFERROR(__xludf.DUMMYFUNCTION("""COMPUTED_VALUE"""),"景安2分鐘") -> 景安2分鐘 | D69: =IFERROR(__xludf.DUMMYFUNCTION("""COMPUTED_VALUE"""),"A") -> A | E69: PP00063 | F69: =IFERROR(__xludf.DUMMYFUNCTION("""COMPUTED_VALUE"""),"蕭宇榛") -> 蕭宇榛 | G69: 已退租 | H69: 已登記 | I69: 已登記 | J69: 要申請 | K69: 月繳 | L69: 45587 | M69: 45588 | N69: 45942 | O69: 45962 | P69: 45931 | Q69: 355 | R69: 14500 | S69: 14500 | V69: 29000 | W69: 1131022 | X69: 1131023 | Y69: 1141012 | Z69: 標準足月 | AA69: 足月 | AB69: -10 | AC69: 0 | AD69: C1FH11311010019 | AE69: 145 | AF69: 475 | AG69: 105 | AH69: 3000 | AI69: 2275
A70: RL00050 | B70: CR00071 | C70: =IFERROR(__xludf.DUMMYFUNCTION("""COMPUTED_VALUE"""),"景安2分鐘") -> 景安2分鐘 | D70: =IFERROR(__xludf.DUMMYFUNCTION("""COMPUTED_VALUE"""),"B") -> B | E70: PP00064 PP00089 | F70: =IFERROR(__xludf.DUMMYFUNCTION("""COMPUTED_VALUE"""),"張語婕 張依憑") -> 張語婕 張依憑 | G70: 已退租 | H70: 已登記 | I70: 已登記 | J70: 要申請 | K70: 月繳 | L70: 45579 | M70: 45581 | N70: 45961 | O70: 45962 | P70: 45931 | Q70: 381 | R70: 18800 | S70: 18800 | V70: 37600 | W70: 1131014 | X70: 1131016 | Y70: 1141031 | Z70: 標準足月 | AA70: 足月 | AB70: 16 | AC70: 0 | AD70: C1FH11310170004
A71: RL00051 | B71: CR00072 | C71: =IFERROR(__xludf.DUMMYFUNCTION("""COMPUTED_VALUE"""),"景安2分鐘") -> 景安2分鐘 | D71: =IFERROR(__xludf.DUMMYFUNCTION("""COMPUTED_VALUE"""),"C") -> C | E71: PP00065 | F71: =IFERROR(__xludf.DUMMYFUNCTION("""COMPUTED_VALUE"""),"楊玉如") -> 楊玉如 | G71: 已退租 | H71: 已登記 | I71: 已登記 | J71: 要申請 | K71: 月繳 | L71: 45594 | M71: 45597 | N71: 45900 | O71: 45901 | P71: 46054 | Q71: 304 | R71: 12300 | S71: 12300 | V71: 24600 | W71: 1131029 | X71: 1131101 | Y71: 1140831 | Z71: 標準足月 | AA71: 足月 | AB71: 31 | AC71: 0 | AD71: C1FH11311010020 | AE71: 103 | AF71: 184 | AG71: 43 | AH71: 3000 | AI71: 2670
A72: RL00052 | B72: CR00073 | C72: =IFERROR(__xludf.DUMMYFUNCTION("""COMPUTED_VALUE"""),"景安2分鐘") -> 景安2分鐘 | D72: =IFERROR(__xludf.DUMMYFUNCTION("""COMPUTED_VALUE"""),"D") -> D | E72: PP00066 | F72: =IFERROR(__xludf.DUMMYFUNCTION("""COMPUTED_VALUE"""),"鍾佩晶") -> 鍾佩晶 | G72: 入住中 | H72: 已登記 | I72: 已登記 | J72: 要申請 | K72: 月繳 | L72: 45600 | M72: 45607 | N72: 46081 | O72: 46082 | P72: 46054 | Q72: 475 | R72: 8600 | S72: 8600 | T72: 0 | U72: 8600 | V72: 17200 | W72: 1131104 | X72: 1131111 | Y72: 1150228 | Z72: 標準足月 | AA72: 足月 | AB72: 18 | AC72: 0 | AD72: C1FH11311180001
A73: RL00053 | B73: CR00074 | C73: =IFERROR(__xludf.DUMMYFUNCTION("""COMPUTED_VALUE"""),"景安2分鐘") -> 景安2分鐘 | D73: =IFERROR(__xludf.DUMMYFUNCTION("""COMPUTED_VALUE"""),"E") -> E | E73: PP00067 | F73: =IFERROR(__xludf.DUMMYFUNCTION("""COMPUTED_VALUE"""),"陳盈如") -> 陳盈如 | G73: 已退租 | H73: 已登記 | I73: 已登記 | J73: 要申請 | K73: 月繳 | L73: 45600 | M73: 45601 | N73: 45716 | O73: 45717 | P73: 46054 | Q73: 116 | R73: 9500 | S73: 9500 | V73: 19000 | W73: 1131104 | X73: 1131105 | Y73: 1140228 | Z73: 標準足月 | AA73: 足月 | AB73: 24 | AC73: 0 | AD73: C1FH11311180006 | AE73: 108 | AF73: 74 | AG73: 109 | AH73: 3000 | AI73: 完成
A74: RL00054 | B74: CR00075 | C74: =IFERROR(__xludf.DUMMYFUNCTION("""COMPUTED_VALUE"""),"中山北娘家旁") -> 中山北娘家旁 | D74: =IFERROR(__xludf.DUMMYFUNCTION("""COMPUTED_VALUE"""),"A") -> A | E74: PP00068 | F74: =IFERROR(__xludf.DUMMYFUNCTION("""COMPUTED_VALUE"""),"李亨加") -> 李亨加 | G74: 入住中 | H74: 已登記 | I74: 已登記 | J74: 要申請 | K74: 月繳 | L74: 45608 | M74: 45613 | N74: 46081 | O74: 46082 | P74: 46054 | Q74: 469 | R74: 12500 | S74: 12500 | T74: 0 | U74: 12500 | V74: 25000 | W74: 1131112 | X74: 1131117 | Y74: 1150228 | Z74: 標準足月 | AA74: 足月 | AB74: 12 | AC74: 0 | AD74: C1AC11311180012
A75: RL00055 | B75: CR00076 | C75: =IFERROR(__xludf.DUMMYFUNCTION("""COMPUTED_VALUE"""),"中山北娘家旁") -> 中山北娘家旁 | D75: =IFERROR(__xludf.DUMMYFUNCTION("""COMPUTED_VALUE"""),"B") -> B | E75: PP00069 | F75: =IFERROR(__xludf.DUMMYFUNCTION("""COMPUTED_VALUE"""),"Robert Sidey") -> Robert Sidey | G75: 已退租 | H75: 已登記 | I75: 已登記 | J75: 要申請 | K75: 月繳 | L75: 45608 | M75: 45618 | N75: 45716 | O75: 45689 | P75: 45689 | Q75: 99 | R75: 14800 | S75: 14800 | V75: 29600 | W75: 1131112 | X75: 1131122 | Y75: 1140228 | Z75: 標準足月 | AA75: 足月 | AB75: 7 | AC75: 0 | AD75: C1AC11311180011 | AF75: 250 | AI75: 完成
A76: RL00056 | B76: CR00077 | C76: =IFERROR(__xludf.DUMMYFUNCTION("""COMPUTED_VALUE"""),"中山北娘家旁") -> 中山北娘家旁 | D76: =IFERROR(__xludf.DUMMYFUNCTION("""COMPUTED_VALUE"""),"C") -> C | E76: PP00070 | F76: =IFERROR(__xludf.DUMMYFUNCTION("""COMPUTED_VALUE"""),"魏湘芸") -> 魏湘芸 | G76: 入住中 | H76: 已登記 | I76: 已登記 | J76: 要申請 | K76: 月繳 | L76: 45602 | M76: 45606 | N76: 46081 | O76: 46082 | P76: 46054 | Q76: 476 | R76: 14800 | S76: 14800 | T76: 0 | U76: 14800 | V76: 29600 | W76: 1131106 | X76: 1131110 | Y76: 1150228 | Z76: 標準足月 | AA76: 足月 | AB76: 19 | AC76: 0 | AD76: C1AC11311180010
A77: RL00057 | B77: CR00078 | C77: =IFERROR(__xludf.DUMMYFUNCTION("""COMPUTED_VALUE"""),"中山北娘家旁") -> 中山北娘家旁 | D77: =IFERROR(__xludf.DUMMYFUNCTION("""COMPUTED_VALUE"""),"D") -> D | E77: PP00071 | F77: =IFERROR(__xludf.DUMMYFUNCTION("""COMPUTED_VALUE"""),"許庭偉") -> 許庭偉 | G77: 已退租 | H77: 已登記 | I77: 已登記 | J77: 要申請 | K77: 月繳 | L77: 45623 | M77: 45627 | N77: 45765 | O77: 45778 | P77: 46054 | Q77: 139 | R77: 14500 | S77: 14500 | V77: 29000 | W77: 1131127 | X77: 1131201 | Y77: 1140418 | Z77: 標準足月 | AA77: 足月 | AB77: 18 | AC77: 0 | AD77: C1AC11312010007 | AG77: 844 | AH77: 3000 | AI77: 完成
A78: RL00058 | B78: CR00079 | C78: =IFERROR(__xludf.DUMMYFUNCTION("""COMPUTED_VALUE"""),"行天宮夏野良栗") -> 行天宮夏野良栗 | D78: =IFERROR(__xludf.DUMMYFUNCTION("""COMPUTED_VALUE"""),"A") -> A | E78: PP00072 | F78: =IFERROR(__xludf.DUMMYFUNCTION("""COMPUTED_VALUE"""),"鄒欣穎") -> 鄒欣穎 | G78: 入住中 | H78: 已登記 | I78: 已登記 | J78: 要申請 | K78: 月繳 | L78: 45608 | M78: 45612 | N78: 46081 | O78: 46082 | P78: 46054 | Q78: 470 | R78: 14200 | S78: 14200 | T78: 0 | U78: 14200 | V78: 28400 | W78: 1131112 | X78: 1131116 | Y78: 1150228 | Z78: 標準足月 | AA78: 足月 | AB78: 13 | AC78: 0 | AD78: C1AC11311180009
A79: RL00059 | B79: CR00080 | C79: =IFERROR(__xludf.DUMMYFUNCTION("""COMPUTED_VALUE"""),"行天宮夏野良栗") -> 行天宮夏野良栗 | D79: =IFERROR(__xludf.DUMMYFUNCTION("""COMPUTED_VALUE"""),"B") -> B | E79: PP00073 | F79: =IFERROR(__xludf.DUMMYFUNCTION("""COMPUTED_VALUE"""),"楊珺媁") -> 楊珺媁 | G79: 入住中 | H79: 已登記 | I79: 已登記 | J79: 要申請 | K79: 月繳 | L79: 45612 | M79: 45613 | N79: 46081 | O79: 46082 | P79: 46054 | Q79: 469 | R79: 14000 | S79: 14000 | T79: 0 | U79: 14000 | V79: 28000 | W79: 1131116 | X79: 1131117 | Y79: 1150228 | Z79: 標準足月 | AA79: 足月 | AB79: 12 | AC79: 0 | AD79: C1AC11311180013
A80: RL00060 | B80: CR00081 | C80: =IFERROR(__xludf.DUMMYFUNCTION("""COMPUTED_VALUE"""),"行天宮夏野良栗") -> 行天宮夏野良栗 | D80: =IFERROR(__xludf.DUMMYFUNCTION("""COMPUTED_VALUE"""),"C") -> C | E80: PP00074 | F80: =IFERROR(__xludf.DUMMYFUNCTION("""COMPUTED_VALUE"""),"黃伊妍") -> 黃伊妍 | G80: 入住中 | H80: 已登記 | I80: 已登記 | J80: 要申請 | K80: 月繳 | L80: 45612 | M80: 45613 | N80: 46081 | O80: 46082 | P80: 46054 | Q80: 469 | R80: 11000 | S80: 11000 | T80: 0 | U80: 11000 | V80: 22000 | W80: 1131116 | X80: 1131117 | Y80: 1150228 | Z80: 標準足月 | AA80: 足月 | AB80: 12 | AC80: 0 | AD80: C1AC11311180008
A81: RL00061 | B81: CR00082 | C81: =IFERROR(__xludf.DUMMYFUNCTION("""COMPUTED_VALUE"""),"行天宮夏野良栗") -> 行天宮夏野良栗 | D81: =IFERROR(__xludf.DUMMYFUNCTION("""COMPUTED_VALUE"""),"D") -> D | E81: PP00075 | F81: =IFERROR(__xludf.DUMMYFUNCTION("""COMPUTED_VALUE"""),"江仲元") -> 江仲元 | G81: 入住中 | H81: 已登記 | I81: 已登記 | J81: 要申請 | K81: 月繳 | L81: 45629 | M81: 45634 | N81: 46081 | O81: 46082 | P81: 46054 | Q81: 448 | R81: 11200 | S81: 11200 | T81: 0 | U81: 11200 | V81: 22400 | W81: 1131203 | X81: 1131208 | Y81: 1150228 | Z81: 標準足月 | AA81: 足月 | AB81: 21 | AC81: 0 | AD81: C1AC11312060050
A82: RL00085 | B82: CR00083 | C82: =IFERROR(__xludf.DUMMYFUNCTION("""COMPUTED_VALUE"""),"行天宮夏野良栗") -> 行天宮夏野良栗 | D82: =IFERROR(__xludf.DUMMYFUNCTION("""COMPUTED_VALUE"""),"兩房") -> 兩房 | E82: PP00076 PP00090 | F82: =IFERROR(__xludf.DUMMYFUNCTION("""COMPUTED_VALUE"""),"張宏祺 謝宗穎") -> 張宏祺 謝宗穎 | G82: 已退租 | H82: 已登記 | I82: 已登記 | J82: 要申請 | K82: 月繳 | L82: 45623 | M82: 45627 | N82: 45991 | O82: 45992 | P82: 45962 | Q82: 365 | R82: 31800 | S82: 31800 | V82: 63600 | W82: 1131127 | X82: 1131201 | Y82: 1141130 | Z82: 標準足月 | AA82: 足月 | AB82: 30 | AC82: 0 | AF82: 672 | AH82: 3000 | AI82: 完成
A83: RL00064 | B83: CR00084 | C83: =IFERROR(__xludf.DUMMYFUNCTION("""COMPUTED_VALUE"""),"中山北Feli家") -> 中山北Feli家 | D83: =IFERROR(__xludf.DUMMYFUNCTION("""COMPUTED_VALUE"""),"A") -> A | E83: PP00077 | F83: =IFERROR(__xludf.DUMMYFUNCTION("""COMPUTED_VALUE"""),"蔡亦翔") -> 蔡亦翔 | G83: 入住中 | H83: 已登記 | I83: 已登記 | J83: 要申請 | K83: 月繳 | L83: 45631 | M83: 45636 | N83: 46081 | O83: 46082 | P83: 46054 | Q83: 446 | R83: 13200 | S83: 13200 | T83: 0 | U83: 13200 | V83: 26400 | W83: 1131205 | X83: 1131210 | Y83: 1150228 | Z83: 首月切到月底 | AA83: 足月 | AB83: 19 | AC83: 0 | AD83: C1AE11312090001
A84: RL00065 | B84: CR00085 | C84: =IFERROR(__xludf.DUMMYFUNCTION("""COMPUTED_VALUE"""),"中山北Feli家") -> 中山北Feli家 | D84: =IFERROR(__xludf.DUMMYFUNCTION("""COMPUTED_VALUE"""),"B") -> B | E84: PP00078 PP00091 | F84: =IFERROR(__xludf.DUMMYFUNCTION("""COMPUTED_VALUE"""),"杜思瑀 陳廷瀀") -> 杜思瑀 陳廷瀀 | G84: 入住中 | H84: 已登記 | I84: 已登記 | J84: 要申請 | K84: 月繳 | L84: 45651 | M84: 45654 | N84: 46081 | O84: 46082 | P84: 46054 | Q84: 428 | R84: 17500 | S84: 17500 | T84: 0 | U84: 17500 | V84: 35000 | W84: 1131225 | X84: 1131228 | Y84: 1150228 | Z84: 首月切到月底 | AA84: 足月 | AB84: 1 | AC84: 0 | AD84: C1AE11401040001
A85: RL00066 | B85: CR00086 | C85: =IFERROR(__xludf.DUMMYFUNCTION("""COMPUTED_VALUE"""),"中山北Feli家") -> 中山北Feli家 | D85: =IFERROR(__xludf.DUMMYFUNCTION("""COMPUTED_VALUE"""),"C") -> C | E85: PP00079 | F85: =IFERROR(__xludf.DUMMYFUNCTION("""COMPUTED_VALUE"""),"郭亞潔") -> 郭亞潔 | G85: 已退租 | H85: 已登記 | I85: 已登記 | J85: 要申請 | K85: 月繳 | L85: 45636 | M85: 45639 | N85: 45991 | O85: 45992 | P85: 46054 | Q85: 353 | R85: 11500 | S85: 11500 | V85: 23000 | W85: 1131210 | X85: 1131213 | Y85: 1141130 | Z85: 首月切到月底 | AA85: 足月 | AB85: 18 | AC85: 0 | AD85: C1AE11312150002
